Workbook

Sheet README
A1: MEDIFIN · Case #01 Toy Kingdom Inc. — Decision Set (đã khớp USER_FLOW gốc)
A2: 👉 Xem tất cả ma trận tại sheet DECISION_MATRIX (tab đỏ, ngay sau README).
A4: 1. Cách dùng nhanh
A5: Bước 1: Mở Scorecard → đổi các ô dropdown màu vàng (mỗi cột = một người chơi).
A6: Bước 2: Xem điểm từng phần, điểm tổng, Uy tín, điểm Tài chính / Quản trị và kết cục 3×3 ở Scorecard; hoặc xem Comparison để so sánh song song.
A7: Bước 3: Muốn chỉnh cân bằng → sửa các ô chữ xanh (blue) trong sheet S*, M* và Config; mọi điểm tự tính lại.
A9: 2. Bản đồ sheet ↔ màn hình (theo USER_FLOW gốc)
A10: Màn hình | B10: Sheet | C10: Nội dung
A11: Màn 0–1 | B11: Case_Facts | C11: Tổng quan, bí mật nền, 3 trục theo dõi + các giả định thiết kế.
A12: Màn 4 | B12: Financials | C12: BCTC FY2024–26, chỉ số vận hành, snapshot bảng cân đối, đòn bẩy.
A13: Màn 2 | B13: S2_Files + M1 + M2 | C13: 7 hồ sơ HS-A..G (chọn 3); M1: hồ sơ × CH1 (cùng khu vực chỉ =1); M2: hồ sơ × CH2.
A14: Màn 3 | B14: S3_Questions | C14: 7 câu hỏi CH1-A..G (chọn 2), điểm bề mặt.
A15: Màn 5 | B15: S5_FinalQ | C15: 7 câu hỏi CH2-A..G (chọn 1).
A16: Màn 6 | B16: S6_Diagnosis + M3 | C16: 6 chẩn đoán CD-A..F (chọn 1), điều kiện CD-F, M3: chẩn đoán × hồ sơ.
A17: Màn 7 | B17: S7_Treatment + M4 | C17: 6 phác đồ PD-A..F (chọn 1), điều kiện Uy tín (PD-A ≥TB, PD-F Cao), M4: chẩn đoán × phác đồ.
A18: Màn 8 | B18: S8_Timing + M5 | C18: 4 thời điểm TG-A..D; M5: phác đồ × thời điểm.
A19: Màn 9 | B19: S9_Stakeholders + M6 | C19: 7 nhóm (chọn 3); M6: phác đồ × nhóm; điểm Quản trị của Governance & Family.
A20: Màn 10 | B20: S10_Consequence | C20: M7/M8/M9 = công thức điểm Tài chính; bảng 14 diễn biến (7 gốc + 4 phản bác chẩn đoán sai + 3 hệ quả nhóm ưu tiên) và dữ liệu mới biện minh Tái khám.
A21: Màn 11 | B21: S11_Reassess | C21: Giữ / Đổi chẩn đoán / Đổi phác đồ, chi phí Uy tín.
... A23: Hỗ trợ | B23: Config, Lists | C23: Ngưỡng, trọng số, điểm Uy tín; dropdown tự sinh.
A25: 3. Công thức chấm điểm
A26: Kết cục (theo USER_FLOW gốc) | B26: Điểm Tài chính = M7 (PD×TG) + M8/M9 (nhóm ưu tiên). Tier: Ổn định / Mong manh (1–3) / Sụp đổ (≤0). Điểm Quản trị = +1 mở HS-G; +2/−1 Governance & Family; −1 mỗi lần mất Uy tín; −2 nếu Sụp đổ tài chính; −1 nếu PD-D chưa mở HS-E. Tier: ≥3 Đoàn kết · 0–2 Chia rẽ · <0 Mất kiểm soát. → ô 3×3.
A27: Uy tín | B27: Thấp / Trung bình / Cao. Không đổi ô kết cục, đổi cách mô tả. Là điều kiện mở PD-A và PD-F; thay đổi bởi CD-F thiếu điều kiện, TG-C thất bại, đổi thiếu dữ liệu mới.
A28: Lớp điểm /100 (bổ sung) | B28: Investigation, Diagnosis, Treatment, Execution, Reassessment (0–100) và Overall (20/25/20/20/15%) để so sánh người chơi.
A30: 4. Đã chốt theo USER_FLOW bản sửa (không còn là giả định)
A31: • Ngưỡng 'Ổn định tài chính' = ≥4 (Config → fr_stable). Ngưỡng ≥5 trong bản nháp đầu không đạt được (điểm tối đa chỉ +4) — đội đã chốt lại ≥4, có ghi chú ngay trong USER_FLOW Màn 12.
A32: • 6 chẩn đoán CD-A..F đổi tên theo khung '6 tầng vấn đề' (Áp lực Cạnh tranh, Nút thắt Vận hành, Biểu hiện Thanh khoản, Nguyên nhân Cấu trúc, Áp lực Danh mục, Đa yếu tố) — không còn khung đúng/sai ngầm định.
A33: • Màn 10 có đủ 14 diễn biến: 7 gốc + 4 sự kiện phản bác trực tiếp cho CD-A/B/C/E + 3 hệ quả quan sát được cho Employees/Customers/Landlords.
A35: 5. Điểm cần bạn xác nhận (case gốc không nêu)
A36: • Uy tín khởi điểm, quy tắc tăng (+1 chẩn đoán có căn cứ, +1 điều tra hiệu quả) và cách xác định 'refinance thử thành công / có dữ liệu mới' là GIẢ ĐỊNH của file — chỉnh ở Config và S10.
A37: • CD-D 'Nguyên nhân Cấu trúc' được dùng làm MỐC CHẤM ĐIỂM Treatment (không phải tuyên bố '5 chẩn đoán kia sai') — nếu nhóm muốn đổi mốc, sửa Config → true_dx và bảng M3, M4.
A38: • Các nhóm ưu tiên ở Màn 9 không có mã trong case gốc; file đặt GR-1..GR-7.
A39: • Chữ xanh = số liệu nhập; đen = công thức; ô nền vàng ở Scorecard = dropdown lựa chọn.

Sheet DECISION_MATRIX
A1: DECISION MATRIX — tất cả ma trận quyết định trong 1 sheet
A2: Hàng = lựa chọn A, cột = lựa chọn B, ô giao nhau = điểm/kết quả. Ô liên kết tự động tới sheet gốc (sửa số ở sheet M*/S* tương ứng).
A4: M1 · Hồ sơ (Màn 2) × Câu hỏi bổ sung (Màn 3) — giá trị thông tin tăng thêm (cùng khu vực = 1)
A5: Hàng ↓ / Cột → | C5: =M1_File_x_Q!C4 -> Traffic giảm, e-commerce tăng — khách rời bỏ hay đổi kê | D5: =M1_File_x_Q!D4 -> Chương trình vốn nào bị trì hoãn lâu nhất? | E5: =M1_File_x_Q!E4 -> Holiday kém 10% thì thanh khoản ra sao? | F5: =M1_File_x_Q!F4 -> Khoản nợ nào đến hạn sớm nhất? | G5: =M1_File_x_Q!G4 -> Nhóm sản phẩm nào đang hoạt động tốt nhất? | H5: =M1_File_x_Q!H4 -> Ban lãnh đạo có đồng thuận không? | I5: =M1_File_x_Q!I4 -> Có một điều khoản đặc biệt nào giữa Michael và nhà đầu
A6: ID | B6: Lựa chọn | C6: =M1_File_x_Q!C5 -> CH1-A | D6: =M1_File_x_Q!D5 -> CH1-B | E6: =M1_File_x_Q!E5 -> CH1-C | F6: =M1_File_x_Q!F5 -> CH1-D | G6: =M1_File_x_Q!G5 -> CH1-E | H6: =M1_File_x_Q!H5 -> CH1-F | I6: =M1_File_x_Q!I5 -> CH1-G
A7: =M1_File_x_Q!A6 -> HS-A | B7: =M1_File_x_Q!B6 -> Sales & Customer | C7: =M1_File_x_Q!C6 -> 1 | D7: =M1_File_x_Q!D6 -> 2 | E7: =M1_File_x_Q!E6 -> 4 | F7: =M1_File_x_Q!F6 -> 6 | G7: =M1_File_x_Q!G6 -> 2 | H7: =M1_File_x_Q!H6 -> 3 | I7: =M1_File_x_Q!I6 -> 3
A8: =M1_File_x_Q!A7 -> HS-B | B8: =M1_File_x_Q!B7 -> Stores & Investment | C8: =M1_File_x_Q!C7 -> 3 | D8: =M1_File_x_Q!D7 -> 1 | E8: =M1_File_x_Q!E7 -> 4 | F8: =M1_File_x_Q!F7 -> 6 | G8: =M1_File_x_Q!G7 -> 2 | H8: =M1_File_x_Q!H7 -> 3 | I8: =M1_File_x_Q!I7 -> 3
A9: =M1_File_x_Q!A8 -> HS-C | B9: =M1_File_x_Q!B8 -> Liquidity | C9: =M1_File_x_Q!C8 -> 3 | D9: =M1_File_x_Q!D8 -> 2 | E9: =M1_File_x_Q!E8 -> 1 | F9: =M1_File_x_Q!F8 -> 6 | G9: =M1_File_x_Q!G8 -> 2 | H9: =M1_File_x_Q!H8 -> 3 | I9: =M1_File_x_Q!I8 -> 3
A10: =M1_File_x_Q!A9 -> HS-D | B10: =M1_File_x_Q!B9 -> Capital Structure & Leverage History | C10: =M1_File_x_Q!C9 -> 3 | D10: =M1_File_x_Q!D9 -> 2 | E10: =M1_File_x_Q!E9 -> 4 | F10: =M1_File_x_Q!F9 -> 1 | G10: =M1_File_x_Q!G9 -> 2 | H10: =M1_File_x_Q!H9 -> 3 | I10: =M1_File_x_Q!I9 -> 3
A11: =M1_File_x_Q!A10 -> HS-E | B11: =M1_File_x_Q!B10 -> Product & Category Trends | C11: =M1_File_x_Q!C10 -> 3 | D11: =M1_File_x_Q!D10 -> 2 | E11: =M1_File_x_Q!E10 -> 4 | F11: =M1_File_x_Q!F10 -> 6 | G11: =M1_File_x_Q!G10 -> 1 | H11: =M1_File_x_Q!H10 -> 3 | I11: =M1_File_x_Q!I10 -> 3
A12: =M1_File_x_Q!A11 -> HS-F | B12: =M1_File_x_Q!B11 -> Management Track Record | C12: =M1_File_x_Q!C11 -> 3 | D12: =M1_File_x_Q!D11 -> 2 | E12: =M1_File_x_Q!E11 -> 4 | F12: =M1_File_x_Q!F11 -> 6 | G12: =M1_File_x_Q!G11 -> 2 | H12: =M1_File_x_Q!H11 -> 1 | I12: =M1_File_x_Q!I11 -> 3
A13: =M1_File_x_Q!A12 -> HS-G | B13: =M1_File_x_Q!B12 -> Governance & Family | C13: =M1_File_x_Q!C12 -> 3 | D13: =M1_File_x_Q!D12 -> 2 | E13: =M1_File_x_Q!E12 -> 4 | F13: =M1_File_x_Q!F12 -> 6 | G13: =M1_File_x_Q!G12 -> 2 | H13: =M1_File_x_Q!H12 -> 3 | I13: =M1_File_x_Q!I12 -> 1
A16: M2 · Hồ sơ (Màn 2) × Câu hỏi cuối (Màn 5) — điểm thông tin thêm
A17: Hàng ↓ / Cột → | C17: =M2_File_x_FQ!C4 -> Khoản nào khó cắt nhất? | D17: =M2_File_x_FQ!D4 -> Có thêm vốn thì dùng vào đâu? | E17: =M2_File_x_FQ!E4 -> Sao không đóng mạnh cửa hàng? | F17: =M2_File_x_FQ!F4 -> Amazon biến mất thì công ty khỏe chưa? | G17: =M2_File_x_FQ!G4 -> Nếu loại bỏ được phần lớn áp lực nợ, đã giải quyết toàn | H17: =M2_File_x_FQ!H4 -> Lo nhất điều gì trong 12 tháng tới? | I17: =M2_File_x_FQ!I4 -> Nếu EBITDA giảm thêm 5%, điều gì xảy ra ngay lập tức?
A18: ID | B18: Lựa chọn | C18: =M2_File_x_FQ!C5 -> CH2-A | D18: =M2_File_x_FQ!D5 -> CH2-B | E18: =M2_File_x_FQ!E5 -> CH2-C | F18: =M2_File_x_FQ!F5 -> CH2-D | G18: =M2_File_x_FQ!G5 -> CH2-E | H18: =M2_File_x_FQ!H5 -> CH2-F | I18: =M2_File_x_FQ!I5 -> CH2-G
A19: =M2_File_x_FQ!A6 -> HS-A | B19: =M2_File_x_FQ!B6 -> Sales & Customer | C19: =M2_File_x_FQ!C6 -> 0 | D19: =M2_File_x_FQ!D6 -> 2 | E19: =M2_File_x_FQ!E6 -> 2 | F19: =M2_File_x_FQ!F6 -> 5 | G19: =M2_File_x_FQ!G6 -> 2 | H19: =M2_File_x_FQ!H6 -> 0 | I19: =M2_File_x_FQ!I6 -> 0
A20: =M2_File_x_FQ!A7 -> HS-B | B20: =M2_File_x_FQ!B7 -> Stores & Investment | C20: =M2_File_x_FQ!C7 -> 0 | D20: =M2_File_x_FQ!D7 -> 5 | E20: =M2_File_x_FQ!E7 -> 5 | F20: =M2_File_x_FQ!F7 -> 0 | G20: =M2_File_x_FQ!G7 -> 3 | H20: =M2_File_x_FQ!H7 -> 0 | I20: =M2_File_x_FQ!I7 -> 0
A21: =M2_File_x_FQ!A8 -> HS-C | B21: =M2_File_x_FQ!B8 -> Liquidity | C21: =M2_File_x_FQ!C8 -> 0 | D21: =M2_File_x_FQ!D8 -> 2 | E21: =M2_File_x_FQ!E8 -> 0 | F21: =M2_File_x_FQ!F8 -> 0 | G21: =M2_File_x_FQ!G8 -> 0 | H21: =M2_File_x_FQ!H8 -> 5 | I21: =M2_File_x_FQ!I8 -> 3
A22: =M2_File_x_FQ!A9 -> HS-D | B22: =M2_File_x_FQ!B9 -> Capital Structure & Leverage History | C22: =M2_File_x_FQ!C9 -> 5 | D22: =M2_File_x_FQ!D9 -> 0 | E22: =M2_File_x_FQ!E9 -> 0 | F22: =M2_File_x_FQ!F9 -> 3 | G22: =M2_File_x_FQ!G9 -> 6 | H22: =M2_File_x_FQ!H9 -> 5 | I22: =M2_File_x_FQ!I9 -> 4
A23: =M2_File_x_FQ!A10 -> HS-E | B23: =M2_File_x_FQ!B10 -> Product & Category Trends | C23: =M2_File_x_FQ!C10 -> 0 | D23: =M2_File_x_FQ!D10 -> 0 | E23: =M2_File_x_FQ!E10 -> 0 | F23: =M2_File_x_FQ!F10 -> 3 | G23: =M2_File_x_FQ!G10 -> 0 | H23: =M2_File_x_FQ!H10 -> 0 | I23: =M2_File_x_FQ!I10 -> 0
A24: =M2_File_x_FQ!A11 -> HS-F | B24: =M2_File_x_FQ!B11 -> Management Track Record | C24: =M2_File_x_FQ!C11 -> 3 | D24: =M2_File_x_FQ!D11 -> 0 | E24: =M2_File_x_FQ!E11 -> 0 | F24: =M2_File_x_FQ!F11 -> 0 | G24: =M2_File_x_FQ!G11 -> 0 | H24: =M2_File_x_FQ!H11 -> 0 | I24: =M2_File_x_FQ!I11 -> 0
A25: =M2_File_x_FQ!A12 -> HS-G | B25: =M2_File_x_FQ!B12 -> Governance & Family | C25: =M2_File_x_FQ!C12 -> 2 | D25: =M2_File_x_FQ!D12 -> 4 | E25: =M2_File_x_FQ!E12 -> 4 | F25: =M2_File_x_FQ!F12 -> 3 | G25: =M2_File_x_FQ!G12 -> 5 | H25: =M2_File_x_FQ!H12 -> 4 | I25: =M2_File_x_FQ!I12 -> 10
A28: M3 · Chẩn đoán (Màn 6) × Hồ sơ (Màn 2) — bằng chứng ủng hộ
A29: Hàng ↓ / Cột → | C29: =M3_Dx_x_File!C4 -> Sales & Customer | D29: =M3_Dx_x_File!D4 -> Stores & Investment | E29: =M3_Dx_x_File!E4 -> Liquidity | F29: =M3_Dx_x_File!F4 -> Capital Structure & Leverage History | G29: =M3_Dx_x_File!G4 -> Product & Category Trends | H29: =M3_Dx_x_File!H4 -> Management Track Record | I29: =M3_Dx_x_File!I4 -> Governance & Family
A30: ID | B30: Lựa chọn | C30: =M3_Dx_x_File!C5 -> HS-A | D30: =M3_Dx_x_File!D5 -> HS-B | E30: =M3_Dx_x_File!E5 -> HS-C | F30: =M3_Dx_x_File!F5 -> HS-D | G30: =M3_Dx_x_File!G5 -> HS-E | H30: =M3_Dx_x_File!H5 -> HS-F | I30: =M3_Dx_x_File!I5 -> HS-G
A31: =M3_Dx_x_File!A6 -> CD-A | B31: =M3_Dx_x_File!B6 -> Áp lực Cạnh tranh (Competitive Pressure) | C31: =M3_Dx_x_File!C6 -> 25 | D31: =M3_Dx_x_File!D6 -> 4 | E31: =M3_Dx_x_File!E6 -> 0 | F31: =M3_Dx_x_File!F6 -> 2 | G31: =M3_Dx_x_File!G6 -> 8 | H31: =M3_Dx_x_File!H6 -> 6 | I31: =M3_Dx_x_File!I6 -> 0
A32: =M3_Dx_x_File!A7 -> CD-B | B32: =M3_Dx_x_File!B7 -> Nút thắt Vận hành (Operational Bottleneck) | C32: =M3_Dx_x_File!C7 -> 5 | D32: =M3_Dx_x_File!D7 -> 25 | E32: =M3_Dx_x_File!E7 -> 3 | F32: =M3_Dx_x_File!F7 -> 0 | G32: =M3_Dx_x_File!G7 -> 0 | H32: =M3_Dx_x_File!H7 -> 8 | I32: =M3_Dx_x_File!I7 -> 3
A33: =M3_Dx_x_File!A8 -> CD-C | B33: =M3_Dx_x_File!B8 -> Biểu hiện Thanh khoản tức thời (Liquidity Manifestation) | C33: =M3_Dx_x_File!C8 -> 0 | D33: =M3_Dx_x_File!D8 -> 4 | E33: =M3_Dx_x_File!E8 -> 25 | F33: =M3_Dx_x_File!F8 -> 10 | G33: =M3_Dx_x_File!G8 -> 0 | H33: =M3_Dx_x_File!H8 -> 3 | I33: =M3_Dx_x_File!I8 -> 0
A34: =M3_Dx_x_File!A9 -> CD-D | B34: =M3_Dx_x_File!B9 -> Nguyên nhân Cấu trúc (Structural Driver) | C34: =M3_Dx_x_File!C9 -> 2 | D34: =M3_Dx_x_File!D9 -> 0 | E34: =M3_Dx_x_File!E9 -> 10 | F34: =M3_Dx_x_File!F9 -> 25 | G34: =M3_Dx_x_File!G9 -> 0 | H34: =M3_Dx_x_File!H9 -> 8 | I34: =M3_Dx_x_File!I9 -> 6
A35: =M3_Dx_x_File!A10 -> CD-E | B35: =M3_Dx_x_File!B10 -> Áp lực Danh mục Sản phẩm (Category Pressure) | C35: =M3_Dx_x_File!C10 -> 6 | D35: =M3_Dx_x_File!D10 -> 0 | E35: =M3_Dx_x_File!E10 -> 0 | F35: =M3_Dx_x_File!F10 -> 0 | G35: =M3_Dx_x_File!G10 -> 25 | H35: =M3_Dx_x_File!H10 -> 3 | I35: =M3_Dx_x_File!I10 -> 2
A36: =M3_Dx_x_File!A11 -> CD-F | B36: =M3_Dx_x_File!B11 -> Chẩn đoán Đa yếu tố (Multi-Factor Diagnosis) | C36: =M3_Dx_x_File!C11 -> 6 | D36: =M3_Dx_x_File!D11 -> 6 | E36: =M3_Dx_x_File!E11 -> 6 | F36: =M3_Dx_x_File!F11 -> 15 | G36: =M3_Dx_x_File!G11 -> 6 | H36: =M3_Dx_x_File!H11 -> 8 | I36: =M3_Dx_x_File!I11 -> 10
A39: M4 · Chẩn đoán (Màn 6) × Phác đồ (Màn 7) — độ phù hợp 0–100
A40: Hàng ↓ / Cột → | C40: =M4_Dx_x_Tx!C4 -> Invest to Compete | D40: =M4_Dx_x_Tx!D4 -> Deep Cost Cutting | E40: =M4_Dx_x_Tx!E4 -> Debt Restructuring | F40: =M4_Dx_x_Tx!F4 -> Asset Sale | G40: =M4_Dx_x_Tx!G4 -> Bankruptcy Restructuring | H40: =M4_Dx_x_Tx!H4 -> Combined Restructuring
A41: ID | B41: Lựa chọn | C41: =M4_Dx_x_Tx!C5 -> PD-A | D41: =M4_Dx_x_Tx!D5 -> PD-B | E41: =M4_Dx_x_Tx!E5 -> PD-C | F41: =M4_Dx_x_Tx!F5 -> PD-D | G41: =M4_Dx_x_Tx!G5 -> PD-E | H41: =M4_Dx_x_Tx!H5 -> PD-F
A42: =M4_Dx_x_Tx!A6 -> CD-A | B42: =M4_Dx_x_Tx!B6 -> Áp lực Cạnh tranh (Competitive Pressure) | C42: =M4_Dx_x_Tx!C6 -> 90 | D42: =M4_Dx_x_Tx!D6 -> 35 | E42: =M4_Dx_x_Tx!E6 -> 30 | F42: =M4_Dx_x_Tx!F6 -> 25 | G42: =M4_Dx_x_Tx!G6 -> 20 | H42: =M4_Dx_x_Tx!H6 -> 60
A43: =M4_Dx_x_Tx!A7 -> CD-B | B43: =M4_Dx_x_Tx!B7 -> Nút thắt Vận hành (Operational Bottleneck) | C43: =M4_Dx_x_Tx!C7 -> 85 | D43: =M4_Dx_x_Tx!D7 -> 40 | E43: =M4_Dx_x_Tx!E7 -> 30 | F43: =M4_Dx_x_Tx!F7 -> 40 | G43: =M4_Dx_x_Tx!G7 -> 20 | H43: =M4_Dx_x_Tx!H7 -> 60
A44: =M4_Dx_x_Tx!A8 -> CD-C | B44: =M4_Dx_x_Tx!B8 -> Biểu hiện Thanh khoản tức thời (Liquidity Manifestation) | C44: =M4_Dx_x_Tx!C8 -> 30 | D44: =M4_Dx_x_Tx!D8 -> 65 | E44: =M4_Dx_x_Tx!E8 -> 80 | F44: =M4_Dx_x_Tx!F8 -> 85 | G44: =M4_Dx_x_Tx!G8 -> 50 | H44: =M4_Dx_x_Tx!H8 -> 65
A45: =M4_Dx_x_Tx!A9 -> CD-D | B45: =M4_Dx_x_Tx!B9 -> Nguyên nhân Cấu trúc (Structural Driver) | C45: =M4_Dx_x_Tx!C9 -> 20 | D45: =M4_Dx_x_Tx!D9 -> 40 | E45: =M4_Dx_x_Tx!E9 -> 85 | F45: =M4_Dx_x_Tx!F9 -> 55 | G45: =M4_Dx_x_Tx!G9 -> 80 | H45: =M4_Dx_x_Tx!H9 -> 90
A46: =M4_Dx_x_Tx!A10 -> CD-E | B46: =M4_Dx_x_Tx!B10 -> Áp lực Danh mục Sản phẩm (Category Pressure) | C46: =M4_Dx_x_Tx!C10 -> 55 | D46: =M4_Dx_x_Tx!D10 -> 35 | E46: =M4_Dx_x_Tx!E10 -> 30 | F46: =M4_Dx_x_Tx!F10 -> 20 | G46: =M4_Dx_x_Tx!G10 -> 25 | H46: =M4_Dx_x_Tx!H10 -> 50
A47: =M4_Dx_x_Tx!A11 -> CD-F | B47: =M4_Dx_x_Tx!B11 -> Chẩn đoán Đa yếu tố (Multi-Factor Diagnosis) | C47: =M4_Dx_x_Tx!C11 -> 45 | D47: =M4_Dx_x_Tx!D11 -> 40 | E47: =M4_Dx_x_Tx!E11 -> 65 | F47: =M4_Dx_x_Tx!F11 -> 55 | G47: =M4_Dx_x_Tx!G11 -> 70 | H47: =M4_Dx_x_Tx!H11 -> 90
A50: M5 · Phác đồ (Màn 7) × Thời điểm (Màn 8) — điểm thực thi 0–100
A51: Hàng ↓ / Cột → | C51: =M5_Tx_x_Timing!C4 -> Thực hiện ngay | D51: =M5_Tx_x_Timing!D4 -> Sau holiday season | E51: =M5_Tx_x_Timing!E4 -> Thử tái cấp vốn trước khi cam kết kế hoạch | F51: =M5_Tx_x_Timing!F4 -> Chờ 6 tháng
A52: ID | B52: Lựa chọn | C52: =M5_Tx_x_Timing!C5 -> TG-A | D52: =M5_Tx_x_Timing!D5 -> TG-B | E52: =M5_Tx_x_Timing!E5 -> TG-C | F52: =M5_Tx_x_Timing!F5 -> TG-D
A53: =M5_Tx_x_Timing!A6 -> PD-A | B53: =M5_Tx_x_Timing!B6 -> Invest to Compete | C53: =M5_Tx_x_Timing!C6 -> 55 | D53: =M5_Tx_x_Timing!D6 -> 85 | E53: =M5_Tx_x_Timing!E6 -> 60 | F53: =M5_Tx_x_Timing!F6 -> 30
A54: =M5_Tx_x_Timing!A7 -> PD-B | B54: =M5_Tx_x_Timing!B7 -> Deep Cost Cutting | C54: =M5_Tx_x_Timing!C7 -> 80 | D54: =M5_Tx_x_Timing!D7 -> 60 | E54: =M5_Tx_x_Timing!E7 -> 50 | F54: =M5_Tx_x_Timing!F7 -> 25
A55: =M5_Tx_x_Timing!A8 -> PD-C | B55: =M5_Tx_x_Timing!B8 -> Debt Restructuring | C55: =M5_Tx_x_Timing!C8 -> 65 | D55: =M5_Tx_x_Timing!D8 -> 60 | E55: =M5_Tx_x_Timing!E8 -> 90 | F55: =M5_Tx_x_Timing!F8 -> 20
A56: =M5_Tx_x_Timing!A9 -> PD-D | B56: =M5_Tx_x_Timing!B9 -> Asset Sale | C56: =M5_Tx_x_Timing!C9 -> 75 | D56: =M5_Tx_x_Timing!D9 -> 55 | E56: =M5_Tx_x_Timing!E9 -> 55 | F56: =M5_Tx_x_Timing!F9 -> 20
A57: =M5_Tx_x_Timing!A10 -> PD-E | B57: =M5_Tx_x_Timing!B10 -> Bankruptcy Restructuring | C57: =M5_Tx_x_Timing!C10 -> 60 | D57: =M5_Tx_x_Timing!D10 -> 85 | E57: =M5_Tx_x_Timing!E10 -> 35 | F57: =M5_Tx_x_Timing!F10 -> 10
A58: =M5_Tx_x_Timing!A11 -> PD-F | B58: =M5_Tx_x_Timing!B11 -> Combined Restructuring | C58: =M5_Tx_x_Timing!C11 -> 60 | D58: =M5_Tx_x_Timing!D11 -> 80 | E58: =M5_Tx_x_Timing!E11 -> 70 | F58: =M5_Tx_x_Timing!F11 -> 20
A61: M6 · Phác đồ (Màn 7) × Nhóm ưu tiên (Màn 9) — giá trị ưu tiên
A62: Hàng ↓ / Cột → | C62: =M6_Tx_x_Stake!C4 -> Suppliers | D62: =M6_Tx_x_Stake!D4 -> Employees | E62: =M6_Tx_x_Stake!E4 -> Customers | F62: =M6_Tx_x_Stake!F4 -> Creditors | G62: =M6_Tx_x_Stake!G4 -> Landlords | H62: =M6_Tx_x_Stake!H4 -> Holiday Inventory | I62: =M6_Tx_x_Stake!I4 -> Governance & Family
A63: ID | B63: Lựa chọn | C63: =M6_Tx_x_Stake!C5 -> GR-1 | D63: =M6_Tx_x_Stake!D5 -> GR-2 | E63: =M6_Tx_x_Stake!E5 -> GR-3 | F63: =M6_Tx_x_Stake!F5 -> GR-4 | G63: =M6_Tx_x_Stake!G5 -> GR-5 | H63: =M6_Tx_x_Stake!H5 -> GR-6 | I63: =M6_Tx_x_Stake!I5 -> GR-7
A64: =M6_Tx_x_Stake!A6 -> PD-A | B64: =M6_Tx_x_Stake!B6 -> Invest to Compete | C64: =M6_Tx_x_Stake!C6 -> 15 | D64: =M6_Tx_x_Stake!D6 -> 10 | E64: =M6_Tx_x_Stake!E6 -> 25 | F64: =M6_Tx_x_Stake!F6 -> 15 | G64: =M6_Tx_x_Stake!G6 -> 20 | H64: =M6_Tx_x_Stake!H6 -> 25 | I64: =M6_Tx_x_Stake!I6 -> 15
A65: =M6_Tx_x_Stake!A7 -> PD-B | B65: =M6_Tx_x_Stake!B7 -> Deep Cost Cutting | C65: =M6_Tx_x_Stake!C7 -> 15 | D65: =M6_Tx_x_Stake!D7 -> 25 | E65: =M6_Tx_x_Stake!E7 -> 10 | F65: =M6_Tx_x_Stake!F7 -> 15 | G65: =M6_Tx_x_Stake!G7 -> 20 | H65: =M6_Tx_x_Stake!H7 -> 5 | I65: =M6_Tx_x_Stake!I7 -> 10
A66: =M6_Tx_x_Stake!A8 -> PD-C | B66: =M6_Tx_x_Stake!B8 -> Debt Restructuring | C66: =M6_Tx_x_Stake!C8 -> 15 | D66: =M6_Tx_x_Stake!D8 -> 10 | E66: =M6_Tx_x_Stake!E8 -> 10 | F66: =M6_Tx_x_Stake!F8 -> 30 | G66: =M6_Tx_x_Stake!G8 -> 10 | H66: =M6_Tx_x_Stake!H8 -> 15 | I66: =M6_Tx_x_Stake!I8 -> 25
A67: =M6_Tx_x_Stake!A9 -> PD-D | B67: =M6_Tx_x_Stake!B9 -> Asset Sale | C67: =M6_Tx_x_Stake!C9 -> 10 | D67: =M6_Tx_x_Stake!D9 -> 15 | E67: =M6_Tx_x_Stake!E9 -> 10 | F67: =M6_Tx_x_Stake!F9 -> 20 | G67: =M6_Tx_x_Stake!G9 -> 25 | H67: =M6_Tx_x_Stake!H9 -> 15 | I67: =M6_Tx_x_Stake!I9 -> 25
A68: =M6_Tx_x_Stake!A10 -> PD-E | B68: =M6_Tx_x_Stake!B10 -> Bankruptcy Restructuring | C68: =M6_Tx_x_Stake!C10 -> 30 | D68: =M6_Tx_x_Stake!D10 -> 15 | E68: =M6_Tx_x_Stake!E10 -> 20 | F68: =M6_Tx_x_Stake!F10 -> 25 | G68: =M6_Tx_x_Stake!G10 -> 25 | H68: =M6_Tx_x_Stake!H10 -> 15 | I68: =M6_Tx_x_Stake!I10 -> 15
A69: =M6_Tx_x_Stake!A11 -> PD-F | B69: =M6_Tx_x_Stake!B11 -> Combined Restructuring | C69: =M6_Tx_x_Stake!C11 -> 20 | D69: =M6_Tx_x_Stake!D11 -> 15 | E69: =M6_Tx_x_Stake!E11 -> 15 | F69: =M6_Tx_x_Stake!F11 -> 25 | G69: =M6_Tx_x_Stake!G11 -> 15 | H69: =M6_Tx_x_Stake!H11 -> 15 | I69: =M6_Tx_x_Stake!I11 -> 25
A72: M7 · Phác đồ × Thời điểm → điểm Sức khỏe Tài chính cơ bản (TG-D = −1)
A73: Hàng ↓ / Cột → | C73: =S10_Consequence!C4 -> Thực hiện ngay | D73: =S10_Consequence!D4 -> Sau holiday season | E73: =S10_Consequence!E4 -> Thử tái cấp vốn trước khi cam kết kế hoạch | F73: =S10_Consequence!F4 -> Chờ 6 tháng
A74: ID | B74: Lựa chọn | C74: =S10_Consequence!C5 -> TG-A | D74: =S10_Consequence!D5 -> TG-B | E74: =S10_Consequence!E5 -> TG-C | F74: =S10_Consequence!F5 -> TG-D
A75: =S10_Consequence!A6 -> PD-A | B75: =S10_Consequence!B6 -> Invest to Compete | C75: =S10_Consequence!C6 -> 2 | D75: =S10_Consequence!D6 -> 2 | E75: =S10_Consequence!E6 -> 2 | F75: =S10_Consequence!F6 -> 1
A76: =S10_Consequence!A7 -> PD-B | B76: =S10_Consequence!B7 -> Deep Cost Cutting | C76: =S10_Consequence!C7 -> 3 | D76: =S10_Consequence!D7 -> 3 | E76: =S10_Consequence!E7 -> 3 | F76: =S10_Consequence!F7 -> 2
A77: =S10_Consequence!A8 -> PD-C | B77: =S10_Consequence!B8 -> Debt Restructuring | C77: =S10_Consequence!C8 -> 0 | D77: =S10_Consequence!D8 -> 0 | E77: =S10_Consequence!E8 -> 0 | F77: =S10_Consequence!F8 -> -1
A78: =S10_Consequence!A9 -> PD-D | B78: =S10_Consequence!B9 -> Asset Sale | C78: =S10_Consequence!C9 -> 2 | D78: =S10_Consequence!D9 -> 2 | E78: =S10_Consequence!E9 -> 2 | F78: =S10_Consequence!F9 -> 1
A79: =S10_Consequence!A10 -> PD-E | B79: =S10_Consequence!B10 -> Bankruptcy Restructuring | C79: =S10_Consequence!C10 -> 0 | D79: =S10_Consequence!D10 -> 0 | E79: =S10_Consequence!E10 -> 0 | F79: =S10_Consequence!F10 -> -1
A80: =S10_Consequence!A11 -> PD-F | B80: =S10_Consequence!B11 -> Combined Restructuring | C80: =S10_Consequence!C11 -> 4 | D80: =S10_Consequence!D11 -> 4 | E80: =S10_Consequence!E11 -> 4 | F80: =S10_Consequence!F11 -> 3
A83: M8 · Phác đồ × Nhóm → điểm Tài chính KHI nhóm ĐƯỢC ưu tiên
A84: Hàng ↓ / Cột → | C84: =S10_Consequence!C14 -> Suppliers | D84: =S10_Consequence!D14 -> Employees | E84: =S10_Consequence!E14 -> Customers | F84: =S10_Consequence!F14 -> Creditors | G84: =S10_Consequence!G14 -> Landlords | H84: =S10_Consequence!H14 -> Holiday Inventory | I84: =S10_Consequence!I14 -> Governance & Family
A85: ID | B85: Lựa chọn | C85: =S10_Consequence!C15 -> GR-1 | D85: =S10_Consequence!D15 -> GR-2 | E85: =S10_Consequence!E15 -> GR-3 | F85: =S10_Consequence!F15 -> GR-4 | G85: =S10_Consequence!G15 -> GR-5 | H85: =S10_Consequence!H15 -> GR-6 | I85: =S10_Consequence!I15 -> GR-7
A86: =S10_Consequence!A16 -> PD-A | B86: =S10_Consequence!B16 -> Invest to Compete | C86: =S10_Consequence!C16 -> 0 | D86: =S10_Consequence!D16 -> 0 | E86: =S10_Consequence!E16 -> 0 | F86: =S10_Consequence!F16 -> 0 | G86: =S10_Consequence!G16 -> 0 | H86: =S10_Consequence!H16 -> 0 | I86: =S10_Consequence!I16 -> 0
A87: =S10_Consequence!A17 -> PD-B | B87: =S10_Consequence!B17 -> Deep Cost Cutting | C87: =S10_Consequence!C17 -> 0 | D87: =S10_Consequence!D17 -> 0 | E87: =S10_Consequence!E17 -> 0 | F87: =S10_Consequence!F17 -> 0 | G87: =S10_Consequence!G17 -> 0 | H87: =S10_Consequence!H17 -> 0 | I87: =S10_Consequence!I17 -> 0
A88: =S10_Consequence!A18 -> PD-C | B88: =S10_Consequence!B18 -> Debt Restructuring | C88: =S10_Consequence!C18 -> 0 | D88: =S10_Consequence!D18 -> 0 | E88: =S10_Consequence!E18 -> 0 | F88: =S10_Consequence!F18 -> 2 | G88: =S10_Consequence!G18 -> 0 | H88: =S10_Consequence!H18 -> 0 | I88: =S10_Consequence!I18 -> 0
A89: =S10_Consequence!A19 -> PD-D | B89: =S10_Consequence!B19 -> Asset Sale | C89: =S10_Consequence!C19 -> 0 | D89: =S10_Consequence!D19 -> 0 | E89: =S10_Consequence!E19 -> 0 | F89: =S10_Consequence!F19 -> 0 | G89: =S10_Consequence!G19 -> 0 | H89: =S10_Consequence!H19 -> 0 | I89: =S10_Consequence!I19 -> 0
A90: =S10_Consequence!A20 -> PD-E | B90: =S10_Consequence!B20 -> Bankruptcy Restructuring | C90: =S10_Consequence!C20 -> 1 | D90: =S10_Consequence!D20 -> 0 | E90: =S10_Consequence!E20 -> 0 | F90: =S10_Consequence!F20 -> 0 | G90: =S10_Consequence!G20 -> 0 | H90: =S10_Consequence!H20 -> 0 | I90: =S10_Consequence!I20 -> 0
A91: =S10_Consequence!A21 -> PD-F | B91: =S10_Consequence!B21 -> Combined Restructuring | C91: =S10_Consequence!C21 -> 0 | D91: =S10_Consequence!D21 -> 0 | E91: =S10_Consequence!E21 -> 0 | F91: =S10_Consequence!F21 -> 0 | G91: =S10_Consequence!G21 -> 0 | H91: =S10_Consequence!H21 -> 0 | I91: =S10_Consequence!I21 -> 0
A94: M9 · Phác đồ × Nhóm → điểm Tài chính KHI nhóm KHÔNG được ưu tiên
A95: Hàng ↓ / Cột → | C95: =S10_Consequence!C24 -> Suppliers | D95: =S10_Consequence!D24 -> Employees | E95: =S10_Consequence!E24 -> Customers | F95: =S10_Consequence!F24 -> Creditors | G95: =S10_Consequence!G24 -> Landlords | H95: =S10_Consequence!H24 -> Holiday Inventory | I95: =S10_Consequence!I24 -> Governance & Family
A96: ID | B96: Lựa chọn | C96: =S10_Consequence!C25 -> GR-1 | D96: =S10_Consequence!D25 -> GR-2 | E96: =S10_Consequence!E25 -> GR-3 | F96: =S10_Consequence!F25 -> GR-4 | G96: =S10_Consequence!G25 -> GR-5 | H96: =S10_Consequence!H25 -> GR-6 | I96: =S10_Consequence!I25 -> GR-7
A97: =S10_Consequence!A26 -> PD-A | B97: =S10_Consequence!B26 -> Invest to Compete | C97: =S10_Consequence!C26 -> 0 | D97: =S10_Consequence!D26 -> 0 | E97: =S10_Consequence!E26 -> 0 | F97: =S10_Consequence!F26 -> 0 | G97: =S10_Consequence!G26 -> 0 | H97: =S10_Consequence!H26 -> -1 | I97: =S10_Consequence!I26 -> 0
A98: =S10_Consequence!A27 -> PD-B | B98: =S10_Consequence!B27 -> Deep Cost Cutting | C98: =S10_Consequence!C27 -> 0 | D98: =S10_Consequence!D27 -> 0 | E98: =S10_Consequence!E27 -> 0 | F98: =S10_Consequence!F27 -> 0 | G98: =S10_Consequence!G27 -> 0 | H98: =S10_Consequence!H27 -> -1 | I98: =S10_Consequence!I27 -> 0
A99: =S10_Consequence!A28 -> PD-C | B99: =S10_Consequence!B28 -> Debt Restructuring | C99: =S10_Consequence!C28 -> 0 | D99: =S10_Consequence!D28 -> 0 | E99: =S10_Consequence!E28 -> 0 | F99: =S10_Consequence!F28 -> 0 | G99: =S10_Consequence!G28 -> 0 | H99: =S10_Consequence!H28 -> -1 | I99: =S10_Consequence!I28 -> 0
A100: =S10_Consequence!A29 -> PD-D | B100: =S10_Consequence!B29 -> Asset Sale | C100: =S10_Consequence!C29 -> 0 | D100: =S10_Consequence!D29 -> 0 | E100: =S10_Consequence!E29 -> 0 | F100: =S10_Consequence!F29 -> 0 | G100: =S10_Consequence!G29 -> 0 | H100: =S10_Consequence!H29 -> -1 | I100: =S10_Consequence!I29 -> 0
A101: =S10_Consequence!A30 -> PD-E | B101: =S10_Consequence!B30 -> Bankruptcy Restructuring | C101: =S10_Consequence!C30 -> -2 | D101: =S10_Consequence!D30 -> 0 | E101: =S10_Consequence!E30 -> 0 | F101: =S10_Consequence!F30 -> 0 | G101: =S10_Consequence!G30 -> 0 | H101: =S10_Consequence!H30 -> -1 | I101: =S10_Consequence!I30 -> 0
A102: =S10_Consequence!A31 -> PD-F | B102: =S10_Consequence!B31 -> Combined Restructuring | C102: =S10_Consequence!C31 -> 0 | D102: =S10_Consequence!D31 -> 0 | E102: =S10_Consequence!E31 -> 0 | F102: =S10_Consequence!F31 -> 0 | G102: =S10_Consequence!G31 -> 0 | H102: =S10_Consequence!H31 -> -1 | I102: =S10_Consequence!I31 -> 0
A105: M10 · Quyết định Tái khám (Màn 11) × Tình huống — điểm
A106: Quyết định | B106: Mô tả | C106: Strong | D106: Partial | E106: Weak
A107: =S11_Reassess!A6 -> Keep | B107: =S11_Reassess!B6 -> Giữ nguyên chẩn đoán & phác đồ | C107: =S11_Reassess!C6 -> 95 | D107: =S11_Reassess!D6 -> 40 | E107: =S11_Reassess!E6 -> 15
A108: =S11_Reassess!A7 -> Revise Diagnosis | B108: =S11_Reassess!B7 -> Đổi chẩn đoán | C108: =S11_Reassess!C7 -> 40 | D108: =S11_Reassess!D7 -> 25 | E108: =S11_Reassess!E7 -> 70
A109: =S11_Reassess!A8 -> Revise Treatment | B109: =S11_Reassess!B8 -> Đổi phác đồ | C109: =S11_Reassess!C8 -> 55 | D109: =S11_Reassess!D8 -> 95 | E109: =S11_Reassess!E8 -> 35
A110: =S11_Reassess!A9 -> Revise Both | B110: =S11_Reassess!B9 -> Đổi cả hai | C110: =S11_Reassess!C9 -> 30 | D110: =S11_Reassess!D9 -> 60 | E110: =S11_Reassess!E9 -> 95
A113: M11 · Tài chính (hàng) × Quản trị/Gia tộc (cột) → Kết cục cuối (Màn 12)
A114: Tài chính \ Gia tộc | C114: Gia tộc đoàn kết | D114: Gia tộc chia rẽ, chưa vỡ | E114: Mất kiểm soát
A115: =Endings!A6 -> Ổn định tài chính | C115: =Endings!B6 -> "Người kế nghiệp" — David giữ ghế, công ty ổn định, gia đình miễn cưỡng hợp tác. | D115: =Endings!C6 -> "Hưu chiến có điều kiện" — công ty ổn nhưng David nhượng bớt quyền lực/cổ tức để giữ hòa khí. | E115: =Endings!D6 -> "Thắng trận, thua nhà" — công ty khỏe nhưng David bị phế truất hoặc buộc bán rẻ cổ phần cho Houndstooth.
A116: =Endings!A7 -> Ổn định mong manh | C116: =Endings!B7 -> "Cầm cự cùng nhau" — công ty sống nhưng mỏng manh; gia đình đoàn kết vì cùng chung rủi ro. | D116: =Endings!C7 -> "Chia phần trước khi chìm" — công ty nhỏ hơn hẳn; Michael/Richard rút được phần lớn giá trị; David bị ép nhượng bộ. | E116: =Endings!D7 -> "Tự ăn thịt mình" — công ty còn tồn tại về kỹ thuật nhưng gia đình tan đàn xẻ nghé, kiện tụng tiêu tốn vốn còn lại.
A117: =Endings!A8 -> Sụp đổ tài chính | C117: =Endings!B8 -> "Chết trong danh dự" — công ty phá sản/bị tiếp quản nhưng ba anh em cùng chịu trách nhiệm, không đổ lỗi nhau. | D117: =Endings!C8 -> "Quân cờ của quỹ" — Houndstooth hoặc chủ nợ tiếp quản; gia đình đấu đá đến phút cuối. | E117: =Endings!D8 -> "Sụp đổ toàn diện" — tòa án tiếp quản tài sản, ba anh em kiện nhau ngay trong phiên tòa phá sản.

Sheet Comparison
A1: MEDIFIN Case #01 — Score Comparison (Counselor Case Report)
A2: Kết quả song song của mọi lượt chơi trong Scorecard. Điểm /100 + kết cục 3 trục theo USER_FLOW gốc.
A4: Metric | B4: Weight / Max | C4: =Scorecard!C4 -> P1 · Ideal Path | D4: =Scorecard!D4 -> P2 · Debt-First (thiếu HS-G) | E4: =Scorecard!E4 -> P3 · Competitive Trap | F4: =Scorecard!F4 -> P4 · Cost-Cut + Chờ 6 tháng | G4: =Scorecard!G4 -> P5 · Sandbox (sửa thoải mái)
A5: Profile summary | C5: =Scorecard!C5 -> Nợ + Quản trị + Thanh khoản → CD-D → PD-F sau holiday | D5: =Scorecard!D5 -> Đúng gốc nợ, refinance thử, không mở HS-G | E5: =Scorecard!E5 -> Lặp khu vực đã mở → CD-A → đầu tư cạnh tranh, bỏ Governance | F5: =Scorecard!F5 -> CD-C → PD-B → TG-D; tái khám đổi chẩn đoán có dữ liệu mới | G5: =Scorecard!G5 -> CD-F → Phá sản → sau holiday; thử đổi bất kỳ ô nào
A6: Input status | C6: =Scorecard!C41 -> OK | D6: =Scorecard!D41 -> OK | E6: =Scorecard!E41 -> OK | F6: =Scorecard!F41 -> OK | G6: =Scorecard!G41 -> OK
A7: ★ OVERALL COUNSELOR SCORE /100 | B7: 100 | C7: =Scorecard!C146 -> 94.535714 | D7: =Scorecard!D146 -> 91.858811 | E7: =Scorecard!E146 -> 53.047863 | F7: =Scorecard!F146 -> 65.692623 | G7: =Scorecard!G146 -> 84.197336
A8: Xếp loại | C8: =Scorecard!C147 -> Excellent | D8: =Scorecard!D147 -> Excellent | E8: =Scorecard!E147 -> Developing | F8: =Scorecard!F147 -> Developing | G8: =Scorecard!G147 -> Proficient
A9: Xếp hạng (so với các cột khác) | C9: =RANK(C7,$C$7:$G$7) -> 1 | D9: =RANK(D7,$C$7:$G$7) -> 2 | E9: =RANK(E7,$C$7:$G$7) -> 5 | F9: =RANK(F7,$C$7:$G$7) -> 4 | G9: =RANK(G7,$C$7:$G$7) -> 3
A10: Uy tín cuối | C10: =Scorecard!C131 -> Cao | D10: =Scorecard!D131 -> Cao | E10: =Scorecard!E131 -> Trung bình | F10: =Scorecard!F131 -> Cao | G10: =Scorecard!G131 -> Cao
A11: Tier Tài chính | C11: =Scorecard!C135 -> Ổn định tài chính | D11: =Scorecard!D135 -> Ổn định mong manh | E11: =Scorecard!E135 -> Ổn định mong manh | F11: =Scorecard!F135 -> Ổn định mong manh | G11: =Scorecard!G135 -> Sụp đổ tài chính
A12: Tier Quản trị / Gia tộc | C12: =Scorecard!C142 -> Gia tộc đoàn kết | D12: =Scorecard!D142 -> Gia tộc chia rẽ, chưa vỡ | E12: =Scorecard!E142 -> Mất kiểm soát | F12: =Scorecard!F142 -> Mất kiểm soát | G12: =Scorecard!G142 -> Gia tộc chia rẽ, chưa vỡ
A13: ★ KẾT CỤC CUỐI | C13: =Scorecard!C143 -> "Người kế nghiệp" — David giữ ghế, công ty ổn định, gia đình miễn cưỡng hợp tác. | D13: =Scorecard!D143 -> "Chia phần trước khi chìm" — công ty nhỏ hơn hẳn; Michael/Richard rút được phần lớn giá trị; David bị ép nhượng bộ. | E13: =Scorecard!E143 -> "Tự ăn thịt mình" — công ty còn tồn tại về kỹ thuật nhưng gia đình tan đàn xẻ nghé, kiện tụng tiêu tốn vốn còn lại. | F13: =Scorecard!F143 -> "Tự ăn thịt mình" — công ty còn tồn tại về kỹ thuật nhưng gia đình tan đàn xẻ nghé, kiện tụng tiêu tốn vốn còn lại. | G13: =Scorecard!G143 -> "Quân cờ của quỹ" — Houndstooth hoặc chủ nợ tiếp quản; gia đình đấu đá đến phút cuối.
A14: ▶ Chi tiết 5 thành phần tạo nên Overall (bấm [+] để mở)
A15: Investigation /100 | B15: =Config!$B$41 -> 0.2 | C15: =Scorecard!C75 -> 100 | D15: =Scorecard!D75 -> 83.606557 | E15: =Scorecard!E75 -> 50.819672 | F15: =Scorecard!F75 -> 67.213115 | G15: =Scorecard!G75 -> 77.04918
A16: Diagnosis /100 | B16: =Config!$B$42 -> 0.25 | C16: =Scorecard!C79 -> 100 | D16: =Scorecard!D79 -> 100 | E16: =Scorecard!E79 -> 65 | F16: =Scorecard!F79 -> 77 | G16: =Scorecard!G79 -> 90
A17: Treatment /100 | B17: =Config!$B$43 -> 0.2 | C17: =Scorecard!C93 -> 90 | D17: =Scorecard!D93 -> 85 | E17: =Scorecard!E93 -> 48 | F17: =Scorecard!F93 -> 50 | G17: =Scorecard!G93 -> 76
A18: Execution Planning /100 | B18: =Config!$B$44 -> 0.2 | C18: =Scorecard!C99 -> 86.428571 | D18: =Scorecard!D99 -> 95 | E18: =Scorecard!E99 -> 70.357143 | F18: =Scorecard!F99 -> 62.5 | G18: =Scorecard!G99 -> 86.25
A19: Reassessment /100 | B19: =Config!$B$45 -> 0.15 | C19: =Scorecard!C128 -> 95 | D19: =Scorecard!D128 -> 94.25 | E19: =Scorecard!E128 -> 19.75 | F19: =Scorecard!F128 -> 70 | G19: =Scorecard!G128 -> 92.25
A20: Điểm thô Sức khỏe Tài chính (trước khi quy tier) | C20: =Scorecard!C134 -> 4 | D20: =Scorecard!D134 -> 2 | E20: =Scorecard!E134 -> 2 | F20: =Scorecard!F134 -> 1 | G20: =Scorecard!G134 -> 0
A21: Điểm thô Ổn định Quản trị (trước khi quy tier) | C21: =Scorecard!C141 -> 3 | D21: =Scorecard!D141 -> 2 | E21: =Scorecard!E141 -> -1 | F21: =Scorecard!F141 -> -1 | G21: =Scorecard!G141 -> 0
A22: ▶ Lựa chọn của người chơi ở từng màn (bấm [+] để mở)
A23: Hồ sơ đã xem (Màn 2) | C23: =Scorecard!C148 -> HS-D, HS-G, HS-C | D23: =Scorecard!D148 -> HS-D, HS-C, HS-A | E23: =Scorecard!E148 -> HS-A, HS-E, HS-B | F23: =Scorecard!F148 -> HS-C, HS-F, HS-B | G23: =Scorecard!G148 -> HS-D, HS-A, HS-E
A24: Câu hỏi CH1 / CH2 (Màn 3, 5) | C24: =Scorecard!C149 -> CH1-A, CH1-F | CH2-G | D24: =Scorecard!D149 -> CH1-G, CH1-F | CH2-E | E24: =Scorecard!E149 -> CH1-A, CH1-E | CH2-D | F24: =Scorecard!F149 -> CH1-D, CH1-G | CH2-F | G24: =Scorecard!G149 -> CH1-C, CH1-G | CH2-E
A25: Chẩn đoán đầu → sau tái khám (Màn 6, 11) | C25: =Scorecard!C150 -> CD-D | D25: =Scorecard!D150 -> CD-D | E25: =Scorecard!E150 -> CD-A | F25: =Scorecard!F150 -> CD-C → CD-D | G25: =Scorecard!G150 -> CD-F
A26: Phác đồ đầu → sau tái khám (Màn 7, 11) | C26: =Scorecard!C151 -> PD-F | D26: =Scorecard!D151 -> PD-C | E26: =Scorecard!E151 -> PD-A | F26: =Scorecard!F151 -> PD-B | G26: =Scorecard!G151 -> PD-E
A27: Thời điểm (Màn 8) | C27: =Scorecard!C52 -> TG-B | D27: =Scorecard!D52 -> TG-C | E27: =Scorecard!E52 -> TG-A | F27: =Scorecard!F52 -> TG-D | G27: =Scorecard!G52 -> TG-B
A28: Nhóm ưu tiên (Màn 9) | C28: =Scorecard!C152 -> GR-4, GR-7, GR-6 | D28: =Scorecard!D152 -> GR-4, GR-7, GR-6 | E28: =Scorecard!E152 -> GR-3, GR-6, GR-2 | F28: =Scorecard!F152 -> GR-2, GR-1, GR-5 | G28: =Scorecard!G152 -> GR-1, GR-4, GR-7
A29: ▶ FEEDBACK (Result → Reason → Meaning → Action → Limit) — bấm [+] để mở
A30: Investigation | C30: =Scorecard!C155 -> RESULT: 100/100 (High) → REASON: Bạn phủ được các khu vực then chốt (nợ 2015, thanh khoản, quản trị) và dùng câu hỏi bổ sung vào khu vực chưa mở. → MEANING: Chẩn đoán của bạn dựa trên dữ kiện thay vì suy đoán. → ACTION: Tiếp tục dùng câu hỏi để thu hẹp khoảng trống thông tin, không lặp lại khu vực đã có hồ sơ. → LIMIT: Chỉ được mở 3/7 hồ sơ nên luôn còn khu vực chưa thấy — đó là thiết kế. | D30: =Scorecard!D155 -> RESULT: 84/100 (High) → REASON: Bạn phủ được các khu vực then chốt (nợ 2015, thanh khoản, quản trị) và dùng câu hỏi bổ sung vào khu vực chưa mở. → MEANING: Chẩn đoán của bạn dựa trên dữ kiện thay vì suy đoán. → ACTION: Tiếp tục dùng câu hỏi để thu hẹp khoảng trống thông tin, không lặp lại khu vực đã có hồ sơ. → LIMIT: Chỉ được mở 3/7 hồ sơ nên luôn còn khu vực chưa thấy — đó là thiết kế. | E30: =Scorecard!E155 -> RESULT: 51/100 (Mid) → REASON: Bạn có một phần bằng chứng cốt lõi nhưng bỏ sót khu vực quan trọng hoặc lặp câu hỏi ở khu vực đã mở. → MEANING: Chẩn đoán có thể chỉ được ủng hộ một phần. → ACTION: Chọn hồ sơ bao phủ nợ/thanh khoản/quản trị; dùng 2 câu hỏi cho khu vực còn trống. → LIMIT: Điểm dựa trên thiết kế case; các đường điều tra khác vẫn có thể hợp lệ. | F30: =Scorecard!F155 -> RESULT: 67/100 (Mid) → REASON: Bạn có một phần bằng chứng cốt lõi nhưng bỏ sót khu vực quan trọng hoặc lặp câu hỏi ở khu vực đã mở. → MEANING: Chẩn đoán có thể chỉ được ủng hộ một phần. → ACTION: Chọn hồ sơ bao phủ nợ/thanh khoản/quản trị; dùng 2 câu hỏi cho khu vực còn trống. → LIMIT: Điểm dựa trên thiết kế case; các đường điều tra khác vẫn có thể hợp lệ. | G30: =Scorecard!G155 -> RESULT: 77/100 (Mid) → REASON: Bạn có một phần bằng chứng cốt lõi nhưng bỏ sót khu vực quan trọng hoặc lặp câu hỏi ở khu vực đã mở. → MEANING: Chẩn đoán có thể chỉ được ủng hộ một phần. → ACTION: Chọn hồ sơ bao phủ nợ/thanh khoản/quản trị; dùng 2 câu hỏi cho khu vực còn trống. → LIMIT: Điểm dựa trên thiết kế case; các đường điều tra khác vẫn có thể hợp lệ.
A31: Diagnosis | C31: =Scorecard!C157 -> RESULT: 100/100 (High) → REASON: Chẩn đoán của bạn chạm tới tầng cấu trúc sâu nhất (Nguyên nhân Cấu trúc / Đa yếu tố có đủ điều kiện) và có bằng chứng ủng hộ. → MEANING: Bạn phân biệt được nguyên nhân với triệu chứng, không dừng ở tầng bề mặt. → ACTION: Luôn hỏi: vấn đề này xảy ra trước hay là hệ quả? → LIMIT: 6 chẩn đoán là 6 TẦNG của cùng vấn đề, không phải đúng/sai; điểm cao hơn vì chạm tầng sâu, không vì 'đoán trúng đáp án'. | D31: =Scorecard!D157 -> RESULT: 100/100 (High) → REASON: Chẩn đoán của bạn chạm tới tầng cấu trúc sâu nhất (Nguyên nhân Cấu trúc / Đa yếu tố có đủ điều kiện) và có bằng chứng ủng hộ. → MEANING: Bạn phân biệt được nguyên nhân với triệu chứng, không dừng ở tầng bề mặt. → ACTION: Luôn hỏi: vấn đề này xảy ra trước hay là hệ quả? → LIMIT: 6 chẩn đoán là 6 TẦNG của cùng vấn đề, không phải đúng/sai; điểm cao hơn vì chạm tầng sâu, không vì 'đoán trúng đáp án'. | E31: =Scorecard!E157 -> RESULT: 65/100 (Mid) → REASON: Chẩn đoán chỉ ra một vấn đề có thật nhưng là hệ quả/triệu chứng hoặc thiếu bằng chứng. → MEANING: Phác đồ nhắm vào triệu chứng có thể không chữa được bệnh. → ACTION: Truy ngược về giao dịch 2015 và cấu trúc nợ. → LIMIT: CD-F cần HS-D và ≥1 hồ sơ liên quan, nếu không bị phạt Uy tín. | F31: =Scorecard!F157 -> RESULT: 77/100 (Mid) → REASON: Chẩn đoán chỉ ra một vấn đề có thật nhưng là hệ quả/triệu chứng hoặc thiếu bằng chứng. → MEANING: Phác đồ nhắm vào triệu chứng có thể không chữa được bệnh. → ACTION: Truy ngược về giao dịch 2015 và cấu trúc nợ. → LIMIT: CD-F cần HS-D và ≥1 hồ sơ liên quan, nếu không bị phạt Uy tín. | G31: =Scorecard!G157 -> RESULT: 90/100 (High) → REASON: Chẩn đoán của bạn chạm tới tầng cấu trúc sâu nhất (Nguyên nhân Cấu trúc / Đa yếu tố có đủ điều kiện) và có bằng chứng ủng hộ. → MEANING: Bạn phân biệt được nguyên nhân với triệu chứng, không dừng ở tầng bề mặt. → ACTION: Luôn hỏi: vấn đề này xảy ra trước hay là hệ quả? → LIMIT: 6 chẩn đoán là 6 TẦNG của cùng vấn đề, không phải đúng/sai; điểm cao hơn vì chạm tầng sâu, không vì 'đoán trúng đáp án'.
A32: Treatment | C32: =Scorecard!C159 -> RESULT: 90/100 (High) → REASON: Phác đồ (sau khi qua điều kiện Uy tín) khớp gốc rễ và chẩn đoán của bạn. → MEANING: Kế hoạch xử lý đúng chỗ thanh khoản/nợ bị kẹt. → ACTION: Thử xem thời điểm và nhóm ưu tiên thay đổi hậu quả thế nào. → LIMIT: Không phác đồ nào thắng mọi trục; hậu quả còn phụ thuộc thực thi. | D32: =Scorecard!D159 -> RESULT: 85/100 (High) → REASON: Phác đồ (sau khi qua điều kiện Uy tín) khớp gốc rễ và chẩn đoán của bạn. → MEANING: Kế hoạch xử lý đúng chỗ thanh khoản/nợ bị kẹt. → ACTION: Thử xem thời điểm và nhóm ưu tiên thay đổi hậu quả thế nào. → LIMIT: Không phác đồ nào thắng mọi trục; hậu quả còn phụ thuộc thực thi. | E32: =Scorecard!E159 -> RESULT: 48/100 (Low) → REASON: Phác đồ không khớp vấn đề thật. → MEANING: Có thể tiêu tốn cash/thời gian công ty không có. → ACTION: Đọc lại chẩn đoán và hỏi phác đồ nào tác động đúng nguyên nhân đó. → LIMIT: Độ khớp được chấm theo thiết kế case, không theo lý thuyết chung. | F32: =Scorecard!F159 -> RESULT: 50/100 (Mid) → REASON: Phác đồ giải quyết một phần vấn đề hoặc bị hạ cấp do thiếu Uy tín. → MEANING: Có thể mua thời gian nhưng chưa gỡ nguyên nhân. → ACTION: Cân nhắc phác đồ kết hợp nếu đủ Uy tín. → LIMIT: PD-A cần Uy tín ≥ TB, PD-F cần Uy tín Cao. | G32: =Scorecard!G159 -> RESULT: 76/100 (Mid) → REASON: Phác đồ giải quyết một phần vấn đề hoặc bị hạ cấp do thiếu Uy tín. → MEANING: Có thể mua thời gian nhưng chưa gỡ nguyên nhân. → ACTION: Cân nhắc phác đồ kết hợp nếu đủ Uy tín. → LIMIT: PD-A cần Uy tín ≥ TB, PD-F cần Uy tín Cao.
A33: Execution Planning | C33: =Scorecard!C161 -> RESULT: 86/100 (High) → REASON: Thời điểm và nhóm ưu tiên phù hợp với phác đồ. → MEANING: Kế hoạch vừa đúng vừa triển khai được. → ACTION: Tiếp tục nối phác đồ với đúng nhóm phải thuyết phục. → LIMIT: Phản ứng của Michael/chủ nợ thực tế có thể khó đoán hơn mô hình. | D33: =Scorecard!D161 -> RESULT: 95/100 (High) → REASON: Thời điểm và nhóm ưu tiên phù hợp với phác đồ. → MEANING: Kế hoạch vừa đúng vừa triển khai được. → ACTION: Tiếp tục nối phác đồ với đúng nhóm phải thuyết phục. → LIMIT: Phản ứng của Michael/chủ nợ thực tế có thể khó đoán hơn mô hình. | E33: =Scorecard!E161 -> RESULT: 70/100 (Mid) → REASON: Thời điểm hoặc nhóm ưu tiên chỉ hỗ trợ một phần phác đồ. → MEANING: Phác đồ tốt vẫn có thể yếu đi vì sai thứ tự. → ACTION: Tự hỏi ai phải đồng ý để phác đồ chạy, và khi nào. → LIMIT: Chỉ chọn 3/7 nhóm — đánh đổi là chủ đích. | F33: =Scorecard!F161 -> RESULT: 63/100 (Mid) → REASON: Thời điểm hoặc nhóm ưu tiên chỉ hỗ trợ một phần phác đồ. → MEANING: Phác đồ tốt vẫn có thể yếu đi vì sai thứ tự. → ACTION: Tự hỏi ai phải đồng ý để phác đồ chạy, và khi nào. → LIMIT: Chỉ chọn 3/7 nhóm — đánh đổi là chủ đích. | G33: =Scorecard!G161 -> RESULT: 86/100 (High) → REASON: Thời điểm và nhóm ưu tiên phù hợp với phác đồ. → MEANING: Kế hoạch vừa đúng vừa triển khai được. → ACTION: Tiếp tục nối phác đồ với đúng nhóm phải thuyết phục. → LIMIT: Phản ứng của Michael/chủ nợ thực tế có thể khó đoán hơn mô hình.
A34: Reassessment | C34: =Scorecard!C163 -> RESULT: 95/100 (High) → REASON: Bạn giữ hoặc đổi phán đoán đúng với dữ liệu mới từ Màn 10. → MEANING: Linh hoạt nghề nghiệp mà không phản ứng thái quá. → ACTION: Luôn kiểm tra dữ liệu mới xác nhận hay mâu thuẫn chẩn đoán. → LIMIT: Đổi có dữ liệu mới thì không mất Uy tín; đổi không có thì −1. | D34: =Scorecard!D163 -> RESULT: 94/100 (High) → REASON: Bạn giữ hoặc đổi phán đoán đúng với dữ liệu mới từ Màn 10. → MEANING: Linh hoạt nghề nghiệp mà không phản ứng thái quá. → ACTION: Luôn kiểm tra dữ liệu mới xác nhận hay mâu thuẫn chẩn đoán. → LIMIT: Đổi có dữ liệu mới thì không mất Uy tín; đổi không có thì −1. | E34: =Scorecard!E163 -> RESULT: 20/100 (Low) → REASON: Tái khám không khớp dữ liệu mới hoặc bị trừ Uy tín vì đổi thiếu căn cứ. → MEANING: Bỏ qua hoặc phản ứng thái quá làm giảm độ tin cậy. → ACTION: Quyết định chẩn đoán sai hay chỉ phác đồ sai trước khi đổi. → LIMIT: Có thể chơi lại để thử đường tái khám khác. | F34: =Scorecard!F163 -> RESULT: 70/100 (Mid) → REASON: Tái khám chỉ khớp một phần với dữ liệu mới. → MEANING: Có thể giữ phán đoán yếu hoặc đổi phán đoán tốt. → ACTION: Hỏi: sự kiện nào ở Màn 10 thật sự mâu thuẫn chẩn đoán? → LIMIT: Một số đổi là phán đoán chủ quan; điểm từng phần là chủ đích. | G34: =Scorecard!G163 -> RESULT: 92/100 (High) → REASON: Bạn giữ hoặc đổi phán đoán đúng với dữ liệu mới từ Màn 10. → MEANING: Linh hoạt nghề nghiệp mà không phản ứng thái quá. → ACTION: Luôn kiểm tra dữ liệu mới xác nhận hay mâu thuẫn chẩn đoán. → LIMIT: Đổi có dữ liệu mới thì không mất Uy tín; đổi không có thì −1.

Sheet Scorecard
A1: Scorecard — nhập lựa chọn của người chơi, đọc toàn bộ điểm
A2: Mỗi cột = một người chơi / lượt chơi. Đổi các dropdown vàng; mọi mục bên dưới tự tính lại. P1–P4 là lượt chơi mẫu để so sánh.
A4: Item | B4: Rule / source | C4: P1 · Ideal Path | D4: P2 · Debt-First (thiếu HS-G) | E4: P3 · Competitive Trap | F4: P4 · Cost-Cut + Chờ 6 tháng | G4: P5 · Sandbox (sửa thoải mái)
A5: Profile summary | C5: Nợ + Quản trị + Thanh khoản → CD-D → PD-F sau holiday | D5: Đúng gốc nợ, refinance thử, không mở HS-G | E5: Lặp khu vực đã mở → CD-A → đầu tư cạnh tranh, bỏ Governance | F5: CD-C → PD-B → TG-D; tái khám đổi chẩn đoán có dữ liệu mới | G5: CD-F → Phá sản → sau holiday; thử đổi bất kỳ ô nào
A6: A. PLAYER INPUTS (dropdowns)
A7: Màn 2 · Hồ sơ 1 | B7: S2_Files | C7: HS-D - Capital Structure & Leverage History | D7: HS-D - Capital Structure & Leverage History | E7: HS-A - Sales & Customer | F7: HS-C - Liquidity | G7: HS-D - Capital Structure & Leverage History
A8: Màn 2 · Hồ sơ 2 | B8: S2_Files | C8: HS-G - Governance & Family | D8: HS-C - Liquidity | E8: HS-E - Product & Category Trends | F8: HS-F - Management Track Record | G8: HS-A - Sales & Customer
A9: Màn 2 · Hồ sơ 3 | B9: S2_Files | C9: HS-C - Liquidity | D9: HS-A - Sales & Customer | E9: HS-B - Stores & Investment | F9: HS-B - Stores & Investment | G9: HS-E - Product & Category Trends
A10: Màn 3 · Câu hỏi bổ sung 1 | B10: S3_Questions | C10: CH1-A - Traffic giảm, e-commerce tăng — khách rời bỏ hay đổi kênh? | D10: CH1-G - Có một điều khoản đặc biệt nào giữa Michael và nhà đầu tư bên ngoài không? | E10: CH1-A - Traffic giảm, e-commerce tăng — khách rời bỏ hay đổi kênh? | F10: CH1-D - Khoản nợ nào đến hạn sớm nhất? | G10: CH1-C - Holiday kém 10% thì thanh khoản ra sao?
A11: Màn 3 · Câu hỏi bổ sung 2 | B11: S3_Questions | C11: CH1-F - Ban lãnh đạo có đồng thuận không? | D11: CH1-F - Ban lãnh đạo có đồng thuận không? | E11: CH1-E - Nhóm sản phẩm nào đang hoạt động tốt nhất? | F11: CH1-G - Có một điều khoản đặc biệt nào giữa Michael và nhà đầu tư bên ngoài không? | G11: CH1-G - Có một điều khoản đặc biệt nào giữa Michael và nhà đầu tư bên ngoài không?
A12: Màn 5 · Câu hỏi cuối | B12: S5_FinalQ | C12: CH2-G - Nếu EBITDA giảm thêm 5%, điều gì xảy ra ngay lập tức? | D12: CH2-E - Nếu loại bỏ được phần lớn áp lực nợ, đã giải quyết toàn bộ vấn đề chưa? | E12: CH2-D - Amazon biến mất thì công ty khỏe chưa? | F12: CH2-F - Lo nhất điều gì trong 12 tháng tới? | G12: CH2-E - Nếu loại bỏ được phần lớn áp lực nợ, đã giải quyết toàn bộ vấn đề chưa?
A13: Màn 6 · Chẩn đoán | B13: S6_Diagnosis | C13: CD-D - Nguyên nhân Cấu trúc (Structural Driver) | D13: CD-D - Nguyên nhân Cấu trúc (Structural Driver) | E13: CD-A - Áp lực Cạnh tranh (Competitive Pressure) | F13: CD-C - Biểu hiện Thanh khoản tức thời (Liquidity Manifestation) | G13: CD-F - Chẩn đoán Đa yếu tố (Multi-Factor Diagnosis)
A14: Màn 7 · Phác đồ | B14: S7_Treatment | C14: PD-F - Combined Restructuring | D14: PD-C - Debt Restructuring | E14: PD-A - Invest to Compete | F14: PD-B - Deep Cost Cutting | G14: PD-E - Bankruptcy Restructuring
A15: Màn 8 · Thời điểm | B15: S8_Timing | C15: TG-B - Sau holiday season | D15: TG-C - Thử tái cấp vốn trước khi cam kết kế hoạch | E15: TG-A - Thực hiện ngay | F15: TG-D - Chờ 6 tháng | G15: TG-B - Sau holiday season
A16: Màn 9 · Nhóm ưu tiên 1 | B16: S9_Stakeholders | C16: GR-4 - Creditors | D16: GR-4 - Creditors | E16: GR-3 - Customers | F16: GR-2 - Employees | G16: GR-1 - Suppliers
A17: Màn 9 · Nhóm ưu tiên 2 | B17: S9_Stakeholders | C17: GR-7 - Governance & Family | D17: GR-7 - Governance & Family | E17: GR-6 - Holiday Inventory | F17: GR-1 - Suppliers | G17: GR-4 - Creditors
A18: Màn 9 · Nhóm ưu tiên 3 | B18: S9_Stakeholders | C18: GR-6 - Holiday Inventory | D18: GR-6 - Holiday Inventory | E18: GR-2 - Employees | F18: GR-5 - Landlords | G18: GR-7 - Governance & Family
A19: Màn 11 · Quyết định tái khám | B19: S11_Reassess | C19: Keep | D19: Keep | E19: Keep | F19: Revise Diagnosis | G19: Keep
A20: Màn 11 · Chẩn đoán mới (nếu đổi) | B20: S6_Diagnosis | F20: CD-D - Nguyên nhân Cấu trúc (Structural Driver)
A21: Màn 11 · Phác đồ mới (nếu đổi) | B21: S7_Treatment
A22: TÓM TẮT KẾT QUẢ — chỉ cần đọc phần này (chi tiết công thức gấp lại bên dưới)
A23: Trạng thái nhập liệu | C23: =C41 -> OK | D23: =D41 -> OK | E23: =E41 -> OK | F23: =F41 -> OK | G23: =G41 -> OK
A24: Màn 2 · Điểm Hồ sơ đã chọn (đơn vị thô, không phải /100) | B24: tra S2_Files | C24: =C71 -> 40 | D24: =D71 -> 33 | E24: =E71 -> 19 | F24: =F71 -> 23 | G24: =G71 -> 28
A25: Màn 3 · Điểm Câu hỏi bổ sung (đơn vị thô) | B25: tra M1 | C25: =C72+C73 -> 6 | D25: =D72+D73 -> 6 | E25: =E72+E73 -> 2 | F25: =F72+F73 -> 9 | G25: =G72+G73 -> 7
A26: Màn 5 · Điểm Câu hỏi cuối (đơn vị thô) | B26: tra S5+M2 | C26: =C74 -> 15 | D26: =D74 -> 12 | E26: =E74 -> 10 | F26: =F74 -> 9 | G26: =G74 -> 12
A27: → Investigation QUY VỀ /100 (3 dòng trên gộp lại, chia cho mức tối đa có thể đạt) | C27: =C75 -> 100 | D27: =D75 -> 83.606557 | E27: =E75 -> 50.819672 | F27: =F75 -> 67.213115 | G27: =G75 -> 77.04918
A28: Màn 6 · Diagnosis /100 | B28: primary+evidence, tự nhiên ra /100 | C28: =C79 -> 100 | D28: =D79 -> 100 | E28: =E79 -> 65 | F28: =F79 -> 77 | G28: =G79 -> 90
A29: Màn 7 · Treatment /100 | B29: tra M4 (đã là thang 0–100 sẵn) | C29: =C93 -> 90 | D29: =D93 -> 85 | E29: =E93 -> 48 | F29: =F93 -> 50 | G29: =G93 -> 76
A30: Màn 8–9 · Execution /100 | B30: M5 và M6 đều quy về /100 trước khi gộp | C30: =C99 -> 86.428571 | D30: =D99 -> 95 | E30: =E99 -> 70.357143 | F30: =F99 -> 62.5 | G30: =G99 -> 86.25
A31: Màn 11 · Reassessment /100 | C31: =C128 -> 95 | D31: =D128 -> 94.25 | E31: =E128 -> 19.75 | F31: =F128 -> 70 | G31: =G128 -> 92.25
A32: ★ TỔNG ĐIỂM COUNSELOR /100 (=20%×Inv +25%×Dia +20%×Tre +20%×Exe +15%×Rea — 5 số trên CỘNG CÓ TRỌNG SỐ, KHÔNG cộng điểm thô ở M2/M3/M5) | B32: Config | C32: =C146 -> 94.535714 | D32: =D146 -> 91.858811 | E32: =E146 -> 53.047863 | F32: =F146 -> 65.692623 | G32: =G146 -> 84.197336
A33: Xếp loại | C33: =C147 -> Excellent | D33: =D147 -> Excellent | E33: =E147 -> Developing | F33: =F147 -> Developing | G33: =G147 -> Proficient
A34: ─── 3 trục kết cục (điểm THÔ riêng, KHÔNG liên quan tới /100 ở trên) ───
A35: Uy tín cuối | C35: =C131 -> Cao | D35: =D131 -> Cao | E35: =E131 -> Trung bình | F35: =F131 -> Cao | G35: =G131 -> Cao
A36: Sức khỏe Tài chính (điểm thô + tier) | C36: =TEXT(C134,"0")&" → "&C135 -> 4 → Ổn định tài chính | D36: =TEXT(D134,"0")&" → "&D135 -> 2 → Ổn định mong manh | E36: =TEXT(E134,"0")&" → "&E135 -> 2 → Ổn định mong manh | F36: =TEXT(F134,"0")&" → "&F135 -> 1 → Ổn định mong manh | G36: =TEXT(G134,"0")&" → "&G135 -> 0 → Sụp đổ tài chính
A37: Ổn định Quản trị (điểm thô + tier) | C37: =TEXT(C141,"0")&" → "&C142 -> 3 → Gia tộc đoàn kết | D37: =TEXT(D141,"0")&" → "&D142 -> 2 → Gia tộc chia rẽ, chưa vỡ | E37: =TEXT(E141,"0")&" → "&E142 -> -1 → Mất kiểm soát | F37: =TEXT(F141,"0")&" → "&F142 -> -1 → Mất kiểm soát | G37: =TEXT(G141,"0")&" → "&G142 -> 0 → Gia tộc chia rẽ, chưa vỡ
A38: ★ KẾT CỤC CUỐI CÙNG | B38: tra ma trận 3×3 Endings | C38: =C143 -> "Người kế nghiệp" — David giữ ghế, công ty ổn định, gia đình miễn cưỡng hợp tác. | D38: =D143 -> "Chia phần trước khi chìm" — công ty nhỏ hơn hẳn; Michael/Richard rút được phần lớn giá trị; David bị ép nhượng bộ. | E38: =E143 -> "Tự ăn thịt mình" — công ty còn tồn tại về kỹ thuật nhưng gia đình tan đàn xẻ nghé, kiện tụng tiêu tốn vốn còn lại. | F38: =F143 -> "Tự ăn thịt mình" — công ty còn tồn tại về kỹ thuật nhưng gia đình tan đàn xẻ nghé, kiện tụng tiêu tốn vốn còn lại. | G38: =G143 -> "Quân cờ của quỹ" — Houndstooth hoặc chủ nợ tiếp quản; gia đình đấu đá đến phút cuối.
A39: ▶ CHI TIẾT CÔNG THỨC BÊN DƯỚI (bấm nút [+] ở lề trái để mở — chỉ cần khi muốn kiểm tra lại cách tính)
A40: B. VALIDATION (thông báo lỗi & cảnh báo)
A41: Input status | B41: OK = flow tiếp tục được | C41: =IF(OR(COUNTA(C7:C9)<>3,C7=C8,C7=C9,C8=C9),"Select exactly 3 Diagnostic Files to continue.",IF(OR(COUNTA(C10:C11)<>2,C10=C11),"Select exactly 2 Follow-Up Questions to continue.",IF(C12="","Select one final question before continuing.",IF(C13="","Select a Primary Diagnosis before submitting your diagnosis.",IF(C14="","Select a treatment strategy to continue.",IF(C15="","Select an implementation timing.",IF(OR(COUNTA(C16:C18)<>3,C16=C17,C16=C18,C17=C18),"Select exactly 3 stakeholder priorities.",IF(OR(C19="",AND(OR(C19="Revise Diagnosis",C19="Revise Both"),C20=""),AND(OR(C19="Revise Treatment",C19="Revise Both"),C21="")),"Complete your revised decision before closing the case.","OK")))))))) -> OK | D41: =IF(OR(COUNTA(D7:D9)<>3,D7=D8,D7=D9,D8=D9),"Select exactly 3 Diagnostic Files to continue.",IF(OR(COUNTA(D10:D11)<>2,D10=D11),"Select exactly 2 Follow-Up Questions to continue.",IF(D12="","Select one final question before continuing.",IF(D13="","Select a Primary Diagnosis before submitting your diagnosis.",IF(D14="","Select a treatment strategy to continue.",IF(D15="","Select an implementation timing.",IF(OR(COUNTA(D16:D18)<>3,D16=D17,D16=D18,D17=D18),"Select exactly 3 stakeholder priorities.",IF(OR(D19="",AND(OR(D19="Revise Diagnosis",D19="Revise Both"),D20=""),AND(OR(D19="Revise Treatment",D19="Revise Both"),D21="")),"Complete your revised decision before closing the case.","OK")))))))) -> OK | E41: =IF(OR(COUNTA(E7:E9)<>3,E7=E8,E7=E9,E8=E9),"Select exactly 3 Diagnostic Files to continue.",IF(OR(COUNTA(E10:E11)<>2,E10=E11),"Select exactly 2 Follow-Up Questions to continue.",IF(E12="","Select one final question before continuing.",IF(E13="","Select a Primary Diagnosis before submitting your diagnosis.",IF(E14="","Select a treatment strategy to continue.",IF(E15="","Select an implementation timing.",IF(OR(COUNTA(E16:E18)<>3,E16=E17,E16=E18,E17=E18),"Select exactly 3 stakeholder priorities.",IF(OR(E19="",AND(OR(E19="Revise Diagnosis",E19="Revise Both"),E20=""),AND(OR(E19="Revise Treatment",E19="Revise Both"),E21="")),"Complete your revised decision before closing the case.","OK")))))))) -> OK | F41: =IF(OR(COUNTA(F7:F9)<>3,F7=F8,F7=F9,F8=F9),"Select exactly 3 Diagnostic Files to continue.",IF(OR(COUNTA(F10:F11)<>2,F10=F11),"Select exactly 2 Follow-Up Questions to continue.",IF(F12="","Select one final question before continuing.",IF(F13="","Select a Primary Diagnosis before submitting your diagnosis.",IF(F14="","Select a treatment strategy to continue.",IF(F15="","Select an implementation timing.",IF(OR(COUNTA(F16:F18)<>3,F16=F17,F16=F18,F17=F18),"Select exactly 3 stakeholder priorities.",IF(OR(F19="",AND(OR(F19="Revise Diagnosis",F19="Revise Both"),F20=""),AND(OR(F19="Revise Treatment",F19="Revise Both"),F21="")),"Complete your revised decision before closing the case.","OK")))))))) -> OK | G41: =IF(OR(COUNTA(G7:G9)<>3,G7=G8,G7=G9,G8=G9),"Select exactly 3 Diagnostic Files to continue.",IF(OR(COUNTA(G10:G11)<>2,G10=G11),"Select exactly 2 Follow-Up Questions to continue.",IF(G12="","Select one final question before continuing.",IF(G13="","Select a Primary Diagnosis before submitting your diagnosis.",IF(G14="","Select a treatment strategy to continue.",IF(G15="","Select an implementation timing.",IF(OR(COUNTA(G16:G18)<>3,G16=G17,G16=G18,G17=G18),"Select exactly 3 stakeholder priorities.",IF(OR(G19="",AND(OR(G19="Revise Diagnosis",G19="Revise Both"),G20=""),AND(OR(G19="Revise Treatment",G19="Revise Both"),G21="")),"Complete your revised decision before closing the case.","OK")))))))) -> OK
A42: Cảnh báo hệ thống (Màn 6 / Màn 7) | B42: theo USER_FLOW bản sửa | C42: =IF(C69=1,"Chẩn đoán hỗn hợp cần nhiều bằng chứng hơn bạn có — hội đồng có thể coi đây là né tránh trách nhiệm. Uy tín −1. ","")&IF(C87=1,IF(C51="PD-A","Hội đồng chưa đủ tin tưởng để duyệt kế hoạch đầu tư — bạn buộc phải triển khai phương án cắt giảm chi phí.","Hội đồng chưa đủ tin tưởng để duyệt một kế hoạch tái cấu trúc nhiều mặt trận cùng lúc — bạn buộc phải thu hẹp lại thành cắt giảm chi phí."),"") | D42: =IF(D69=1,"Chẩn đoán hỗn hợp cần nhiều bằng chứng hơn bạn có — hội đồng có thể coi đây là né tránh trách nhiệm. Uy tín −1. ","")&IF(D87=1,IF(D51="PD-A","Hội đồng chưa đủ tin tưởng để duyệt kế hoạch đầu tư — bạn buộc phải triển khai phương án cắt giảm chi phí.","Hội đồng chưa đủ tin tưởng để duyệt một kế hoạch tái cấu trúc nhiều mặt trận cùng lúc — bạn buộc phải thu hẹp lại thành cắt giảm chi phí."),"") | E42: =IF(E69=1,"Chẩn đoán hỗn hợp cần nhiều bằng chứng hơn bạn có — hội đồng có thể coi đây là né tránh trách nhiệm. Uy tín −1. ","")&IF(E87=1,IF(E51="PD-A","Hội đồng chưa đủ tin tưởng để duyệt kế hoạch đầu tư — bạn buộc phải triển khai phương án cắt giảm chi phí.","Hội đồng chưa đủ tin tưởng để duyệt một kế hoạch tái cấu trúc nhiều mặt trận cùng lúc — bạn buộc phải thu hẹp lại thành cắt giảm chi phí."),"") | F42: =IF(F69=1,"Chẩn đoán hỗn hợp cần nhiều bằng chứng hơn bạn có — hội đồng có thể coi đây là né tránh trách nhiệm. Uy tín −1. ","")&IF(F87=1,IF(F51="PD-A","Hội đồng chưa đủ tin tưởng để duyệt kế hoạch đầu tư — bạn buộc phải triển khai phương án cắt giảm chi phí.","Hội đồng chưa đủ tin tưởng để duyệt một kế hoạch tái cấu trúc nhiều mặt trận cùng lúc — bạn buộc phải thu hẹp lại thành cắt giảm chi phí."),"") | G42: =IF(G69=1,"Chẩn đoán hỗn hợp cần nhiều bằng chứng hơn bạn có — hội đồng có thể coi đây là né tránh trách nhiệm. Uy tín −1. ","")&IF(G87=1,IF(G51="PD-A","Hội đồng chưa đủ tin tưởng để duyệt kế hoạch đầu tư — bạn buộc phải triển khai phương án cắt giảm chi phí.","Hội đồng chưa đủ tin tưởng để duyệt một kế hoạch tái cấu trúc nhiều mặt trận cùng lúc — bạn buộc phải thu hẹp lại thành cắt giảm chi phí."),"")
A43: C. DECODED IDs (helper)
A44: ID · F1 | C44: =IFERROR(LEFT(C7,FIND(" ",C7)-1),"") -> HS-D | D44: =IFERROR(LEFT(D7,FIND(" ",D7)-1),"") -> HS-D | E44: =IFERROR(LEFT(E7,FIND(" ",E7)-1),"") -> HS-A | F44: =IFERROR(LEFT(F7,FIND(" ",F7)-1),"") -> HS-C | G44: =IFERROR(LEFT(G7,FIND(" ",G7)-1),"") -> HS-D
A45: ID · F2 | C45: =IFERROR(LEFT(C8,FIND(" ",C8)-1),"") -> HS-G | D45: =IFERROR(LEFT(D8,FIND(" ",D8)-1),"") -> HS-C | E45: =IFERROR(LEFT(E8,FIND(" ",E8)-1),"") -> HS-E | F45: =IFERROR(LEFT(F8,FIND(" ",F8)-1),"") -> HS-F | G45: =IFERROR(LEFT(G8,FIND(" ",G8)-1),"") -> HS-A
A46: ID · F3 | C46: =IFERROR(LEFT(C9,FIND(" ",C9)-1),"") -> HS-C | D46: =IFERROR(LEFT(D9,FIND(" ",D9)-1),"") -> HS-A | E46: =IFERROR(LEFT(E9,FIND(" ",E9)-1),"") -> HS-B | F46: =IFERROR(LEFT(F9,FIND(" ",F9)-1),"") -> HS-B | G46: =IFERROR(LEFT(G9,FIND(" ",G9)-1),"") -> HS-E
A47: ID · Q1 | C47: =IFERROR(LEFT(C10,FIND(" ",C10)-1),"") -> CH1-A | D47: =IFERROR(LEFT(D10,FIND(" ",D10)-1),"") -> CH1-G | E47: =IFERROR(LEFT(E10,FIND(" ",E10)-1),"") -> CH1-A | F47: =IFERROR(LEFT(F10,FIND(" ",F10)-1),"") -> CH1-D | G47: =IFERROR(LEFT(G10,FIND(" ",G10)-1),"") -> CH1-C
A48: ID · Q2 | C48: =IFERROR(LEFT(C11,FIND(" ",C11)-1),"") -> CH1-F | D48: =IFERROR(LEFT(D11,FIND(" ",D11)-1),"") -> CH1-F | E48: =IFERROR(LEFT(E11,FIND(" ",E11)-1),"") -> CH1-E | F48: =IFERROR(LEFT(F11,FIND(" ",F11)-1),"") -> CH1-G | G48: =IFERROR(LEFT(G11,FIND(" ",G11)-1),"") -> CH1-G
A49: ID · FQ | C49: =IFERROR(LEFT(C12,FIND(" ",C12)-1),"") -> CH2-G | D49: =IFERROR(LEFT(D12,FIND(" ",D12)-1),"") -> CH2-E | E49: =IFERROR(LEFT(E12,FIND(" ",E12)-1),"") -> CH2-D | F49: =IFERROR(LEFT(F12,FIND(" ",F12)-1),"") -> CH2-F | G49: =IFERROR(LEFT(G12,FIND(" ",G12)-1),"") -> CH2-E
A50: ID · DX | C50: =IFERROR(LEFT(C13,FIND(" ",C13)-1),"") -> CD-D | D50: =IFERROR(LEFT(D13,FIND(" ",D13)-1),"") -> CD-D | E50: =IFERROR(LEFT(E13,FIND(" ",E13)-1),"") -> CD-A | F50: =IFERROR(LEFT(F13,FIND(" ",F13)-1),"") -> CD-C | G50: =IFERROR(LEFT(G13,FIND(" ",G13)-1),"") -> CD-F
A51: ID · T | C51: =IFERROR(LEFT(C14,FIND(" ",C14)-1),"") -> PD-F | D51: =IFERROR(LEFT(D14,FIND(" ",D14)-1),"") -> PD-C | E51: =IFERROR(LEFT(E14,FIND(" ",E14)-1),"") -> PD-A | F51: =IFERROR(LEFT(F14,FIND(" ",F14)-1),"") -> PD-B | G51: =IFERROR(LEFT(G14,FIND(" ",G14)-1),"") -> PD-E
A52: ID · TM | C52: =IFERROR(LEFT(C15,FIND(" ",C15)-1),"") -> TG-B | D52: =IFERROR(LEFT(D15,FIND(" ",D15)-1),"") -> TG-C | E52: =IFERROR(LEFT(E15,FIND(" ",E15)-1),"") -> TG-A | F52: =IFERROR(LEFT(F15,FIND(" ",F15)-1),"") -> TG-D | G52: =IFERROR(LEFT(G15,FIND(" ",G15)-1),"") -> TG-B
A53: ID · S1 | C53: =IFERROR(LEFT(C16,FIND(" ",C16)-1),"") -> GR-4 | D53: =IFERROR(LEFT(D16,FIND(" ",D16)-1),"") -> GR-4 | E53: =IFERROR(LEFT(E16,FIND(" ",E16)-1),"") -> GR-3 | F53: =IFERROR(LEFT(F16,FIND(" ",F16)-1),"") -> GR-2 | G53: =IFERROR(LEFT(G16,FIND(" ",G16)-1),"") -> GR-1
A54: ID · S2 | C54: =IFERROR(LEFT(C17,FIND(" ",C17)-1),"") -> GR-7 | D54: =IFERROR(LEFT(D17,FIND(" ",D17)-1),"") -> GR-7 | E54: =IFERROR(LEFT(E17,FIND(" ",E17)-1),"") -> GR-6 | F54: =IFERROR(LEFT(F17,FIND(" ",F17)-1),"") -> GR-1 | G54: =IFERROR(LEFT(G17,FIND(" ",G17)-1),"") -> GR-4
A55: ID · S3 | C55: =IFERROR(LEFT(C18,FIND(" ",C18)-1),"") -> GR-6 | D55: =IFERROR(LEFT(D18,FIND(" ",D18)-1),"") -> GR-6 | E55: =IFERROR(LEFT(E18,FIND(" ",E18)-1),"") -> GR-2 | F55: =IFERROR(LEFT(F18,FIND(" ",F18)-1),"") -> GR-5 | G55: =IFERROR(LEFT(G18,FIND(" ",G18)-1),"") -> GR-7
A56: ID · RDX | C56: =IFERROR(LEFT(C20,FIND(" ",C20)-1),"") | D56: =IFERROR(LEFT(D20,FIND(" ",D20)-1),"") | E56: =IFERROR(LEFT(E20,FIND(" ",E20)-1),"") | F56: =IFERROR(LEFT(F20,FIND(" ",F20)-1),"") -> CD-D | G56: =IFERROR(LEFT(G20,FIND(" ",G20)-1),"")
A57: ID · RT | C57: =IFERROR(LEFT(C21,FIND(" ",C21)-1),"") | D57: =IFERROR(LEFT(D21,FIND(" ",D21)-1),"") | E57: =IFERROR(LEFT(E21,FIND(" ",E21)-1),"") | F57: =IFERROR(LEFT(F21,FIND(" ",F21)-1),"") | G57: =IFERROR(LEFT(G21,FIND(" ",G21)-1),"")
A58: D. FLAGS
A59: Nhóm GR-1 (Suppliers) được ưu tiên? (1/0) | C59: =IF(COUNTIF(C53:C55,"GR-1")>0,1,0) -> 0 | D59: =IF(COUNTIF(D53:D55,"GR-1")>0,1,0) -> 0 | E59: =IF(COUNTIF(E53:E55,"GR-1")>0,1,0) -> 0 | F59: =IF(COUNTIF(F53:F55,"GR-1")>0,1,0) -> 1 | G59: =IF(COUNTIF(G53:G55,"GR-1")>0,1,0) -> 1
A60: Nhóm GR-2 (Employees) được ưu tiên? (1/0) | C60: =IF(COUNTIF(C53:C55,"GR-2")>0,1,0) -> 0 | D60: =IF(COUNTIF(D53:D55,"GR-2")>0,1,0) -> 0 | E60: =IF(COUNTIF(E53:E55,"GR-2")>0,1,0) -> 1 | F60: =IF(COUNTIF(F53:F55,"GR-2")>0,1,0) -> 1 | G60: =IF(COUNTIF(G53:G55,"GR-2")>0,1,0) -> 0
A61: Nhóm GR-3 (Customers) được ưu tiên? (1/0) | C61: =IF(COUNTIF(C53:C55,"GR-3")>0,1,0) -> 0 | D61: =IF(COUNTIF(D53:D55,"GR-3")>0,1,0) -> 0 | E61: =IF(COUNTIF(E53:E55,"GR-3")>0,1,0) -> 1 | F61: =IF(COUNTIF(F53:F55,"GR-3")>0,1,0) -> 0 | G61: =IF(COUNTIF(G53:G55,"GR-3")>0,1,0) -> 0
A62: Nhóm GR-4 (Creditors) được ưu tiên? (1/0) | C62: =IF(COUNTIF(C53:C55,"GR-4")>0,1,0) -> 1 | D62: =IF(COUNTIF(D53:D55,"GR-4")>0,1,0) -> 1 | E62: =IF(COUNTIF(E53:E55,"GR-4")>0,1,0) -> 0 | F62: =IF(COUNTIF(F53:F55,"GR-4")>0,1,0) -> 0 | G62: =IF(COUNTIF(G53:G55,"GR-4")>0,1,0) -> 1
A63: Nhóm GR-5 (Landlords) được ưu tiên? (1/0) | C63: =IF(COUNTIF(C53:C55,"GR-5")>0,1,0) -> 0 | D63: =IF(COUNTIF(D53:D55,"GR-5")>0,1,0) -> 0 | E63: =IF(COUNTIF(E53:E55,"GR-5")>0,1,0) -> 0 | F63: =IF(COUNTIF(F53:F55,"GR-5")>0,1,0) -> 1 | G63: =IF(COUNTIF(G53:G55,"GR-5")>0,1,0) -> 0
A64: Nhóm GR-6 (Holiday Inventory) được ưu tiên? (1/0) | C64: =IF(COUNTIF(C53:C55,"GR-6")>0,1,0) -> 1 | D64: =IF(COUNTIF(D53:D55,"GR-6")>0,1,0) -> 1 | E64: =IF(COUNTIF(E53:E55,"GR-6")>0,1,0) -> 1 | F64: =IF(COUNTIF(F53:F55,"GR-6")>0,1,0) -> 0 | G64: =IF(COUNTIF(G53:G55,"GR-6")>0,1,0) -> 0
A65: Nhóm GR-7 (Governance & Family) được ưu tiên? (1/0) | C65: =IF(COUNTIF(C53:C55,"GR-7")>0,1,0) -> 1 | D65: =IF(COUNTIF(D53:D55,"GR-7")>0,1,0) -> 1 | E65: =IF(COUNTIF(E53:E55,"GR-7")>0,1,0) -> 0 | F65: =IF(COUNTIF(F53:F55,"GR-7")>0,1,0) -> 0 | G65: =IF(COUNTIF(G53:G55,"GR-7")>0,1,0) -> 1
A66: Đã mở HS-G? (1/0) | C66: =IF(COUNTIF(C44:C46,"HS-G")>0,1,0) -> 1 | D66: =IF(COUNTIF(D44:D46,"HS-G")>0,1,0) -> 0 | E66: =IF(COUNTIF(E44:E46,"HS-G")>0,1,0) -> 0 | F66: =IF(COUNTIF(F44:F46,"HS-G")>0,1,0) -> 0 | G66: =IF(COUNTIF(G44:G46,"HS-G")>0,1,0) -> 0
A67: Đã mở HS-E? (1/0) | C67: =IF(COUNTIF(C44:C46,"HS-E")>0,1,0) -> 0 | D67: =IF(COUNTIF(D44:D46,"HS-E")>0,1,0) -> 0 | E67: =IF(COUNTIF(E44:E46,"HS-E")>0,1,0) -> 1 | F67: =IF(COUNTIF(F44:F46,"HS-E")>0,1,0) -> 0 | G67: =IF(COUNTIF(G44:G46,"HS-E")>0,1,0) -> 1
A68: Đủ điều kiện CD-F? (HS-D + ≥1 trong A/B/E/F) | C68: =IF(AND(COUNTIF(C44:C46,"HS-D")>0,COUNTIF(C44:C46,"HS-A")+COUNTIF(C44:C46,"HS-B")+COUNTIF(C44:C46,"HS-E")+COUNTIF(C44:C46,"HS-F")>0),1,0) -> 0 | D68: =IF(AND(COUNTIF(D44:D46,"HS-D")>0,COUNTIF(D44:D46,"HS-A")+COUNTIF(D44:D46,"HS-B")+COUNTIF(D44:D46,"HS-E")+COUNTIF(D44:D46,"HS-F")>0),1,0) -> 1 | E68: =IF(AND(COUNTIF(E44:E46,"HS-D")>0,COUNTIF(E44:E46,"HS-A")+COUNTIF(E44:E46,"HS-B")+COUNTIF(E44:E46,"HS-E")+COUNTIF(E44:E46,"HS-F")>0),1,0) -> 0 | F68: =IF(AND(COUNTIF(F44:F46,"HS-D")>0,COUNTIF(F44:F46,"HS-A")+COUNTIF(F44:F46,"HS-B")+COUNTIF(F44:F46,"HS-E")+COUNTIF(F44:F46,"HS-F")>0),1,0) -> 0 | G68: =IF(AND(COUNTIF(G44:G46,"HS-D")>0,COUNTIF(G44:G46,"HS-A")+COUNTIF(G44:G46,"HS-B")+COUNTIF(G44:G46,"HS-E")+COUNTIF(G44:G46,"HS-F")>0),1,0) -> 1
A69: Chọn CD-F nhưng thiếu điều kiện? (1/0) | C69: =IF(AND(C50="CD-F",C68=0),1,0) -> 0 | D69: =IF(AND(D50="CD-F",D68=0),1,0) -> 0 | E69: =IF(AND(E50="CD-F",E68=0),1,0) -> 0 | F69: =IF(AND(F50="CD-F",F68=0),1,0) -> 0 | G69: =IF(AND(G50="CD-F",G68=0),1,0) -> 0
A70: E. INVESTIGATION (Màn 2–5)
A71: Điểm hồ sơ (tối đa 40) | B71: Σ S2_Files | C71: =IFERROR(INDEX(S2_Files!$E$5:$E$11,MATCH(C44,S2_Files!$A$5:$A$11,0)),0)+IFERROR(INDEX(S2_Files!$E$5:$E$11,MATCH(C45,S2_Files!$A$5:$A$11,0)),0)+IFERROR(INDEX(S2_Files!$E$5:$E$11,MATCH(C46,S2_Files!$A$5:$A$11,0)),0) -> 40 | D71: =IFERROR(INDEX(S2_Files!$E$5:$E$11,MATCH(D44,S2_Files!$A$5:$A$11,0)),0)+IFERROR(INDEX(S2_Files!$E$5:$E$11,MATCH(D45,S2_Files!$A$5:$A$11,0)),0)+IFERROR(INDEX(S2_Files!$E$5:$E$11,MATCH(D46,S2_Files!$A$5:$A$11,0)),0) -> 33 | E71: =IFERROR(INDEX(S2_Files!$E$5:$E$11,MATCH(E44,S2_Files!$A$5:$A$11,0)),0)+IFERROR(INDEX(S2_Files!$E$5:$E$11,MATCH(E45,S2_Files!$A$5:$A$11,0)),0)+IFERROR(INDEX(S2_Files!$E$5:$E$11,MATCH(E46,S2_Files!$A$5:$A$11,0)),0) -> 19 | F71: =IFERROR(INDEX(S2_Files!$E$5:$E$11,MATCH(F44,S2_Files!$A$5:$A$11,0)),0)+IFERROR(INDEX(S2_Files!$E$5:$E$11,MATCH(F45,S2_Files!$A$5:$A$11,0)),0)+IFERROR(INDEX(S2_Files!$E$5:$E$11,MATCH(F46,S2_Files!$A$5:$A$11,0)),0) -> 23 | G71: =IFERROR(INDEX(S2_Files!$E$5:$E$11,MATCH(G44,S2_Files!$A$5:$A$11,0)),0)+IFERROR(INDEX(S2_Files!$E$5:$E$11,MATCH(G45,S2_Files!$A$5:$A$11,0)),0)+IFERROR(INDEX(S2_Files!$E$5:$E$11,MATCH(G46,S2_Files!$A$5:$A$11,0)),0) -> 28
A72: Câu hỏi 1: giá trị tăng thêm (M1, MIN qua 3 hồ sơ) | B72: M1 | C72: =MIN(IFERROR(INDEX(M1_File_x_Q!$C$6:$I$12,MATCH(C44,M1_File_x_Q!$A$6:$A$12,0),MATCH(C47,M1_File_x_Q!$C$5:$I$5,0)),0),IFERROR(INDEX(M1_File_x_Q!$C$6:$I$12,MATCH(C45,M1_File_x_Q!$A$6:$A$12,0),MATCH(C47,M1_File_x_Q!$C$5:$I$5,0)),0),IFERROR(INDEX(M1_File_x_Q!$C$6:$I$12,MATCH(C46,M1_File_x_Q!$A$6:$A$12,0),MATCH(C47,M1_File_x_Q!$C$5:$I$5,0)),0)) -> 3 | D72: =MIN(IFERROR(INDEX(M1_File_x_Q!$C$6:$I$12,MATCH(D44,M1_File_x_Q!$A$6:$A$12,0),MATCH(D47,M1_File_x_Q!$C$5:$I$5,0)),0),IFERROR(INDEX(M1_File_x_Q!$C$6:$I$12,MATCH(D45,M1_File_x_Q!$A$6:$A$12,0),MATCH(D47,M1_File_x_Q!$C$5:$I$5,0)),0),IFERROR(INDEX(M1_File_x_Q!$C$6:$I$12,MATCH(D46,M1_File_x_Q!$A$6:$A$12,0),MATCH(D47,M1_File_x_Q!$C$5:$I$5,0)),0)) -> 3 | E72: =MIN(IFERROR(INDEX(M1_File_x_Q!$C$6:$I$12,MATCH(E44,M1_File_x_Q!$A$6:$A$12,0),MATCH(E47,M1_File_x_Q!$C$5:$I$5,0)),0),IFERROR(INDEX(M1_File_x_Q!$C$6:$I$12,MATCH(E45,M1_File_x_Q!$A$6:$A$12,0),MATCH(E47,M1_File_x_Q!$C$5:$I$5,0)),0),IFERROR(INDEX(M1_File_x_Q!$C$6:$I$12,MATCH(E46,M1_File_x_Q!$A$6:$A$12,0),MATCH(E47,M1_File_x_Q!$C$5:$I$5,0)),0)) -> 1 | F72: =MIN(IFERROR(INDEX(M1_File_x_Q!$C$6:$I$12,MATCH(F44,M1_File_x_Q!$A$6:$A$12,0),MATCH(F47,M1_File_x_Q!$C$5:$I$5,0)),0),IFERROR(INDEX(M1_File_x_Q!$C$6:$I$12,MATCH(F45,M1_File_x_Q!$A$6:$A$12,0),MATCH(F47,M1_File_x_Q!$C$5:$I$5,0)),0),IFERROR(INDEX(M1_File_x_Q!$C$6:$I$12,MATCH(F46,M1_File_x_Q!$A$6:$A$12,0),MATCH(F47,M1_File_x_Q!$C$5:$I$5,0)),0)) -> 6 | G72: =MIN(IFERROR(INDEX(M1_File_x_Q!$C$6:$I$12,MATCH(G44,M1_File_x_Q!$A$6:$A$12,0),MATCH(G47,M1_File_x_Q!$C$5:$I$5,0)),0),IFERROR(INDEX(M1_File_x_Q!$C$6:$I$12,MATCH(G45,M1_File_x_Q!$A$6:$A$12,0),MATCH(G47,M1_File_x_Q!$C$5:$I$5,0)),0),IFERROR(INDEX(M1_File_x_Q!$C$6:$I$12,MATCH(G46,M1_File_x_Q!$A$6:$A$12,0),MATCH(G47,M1_File_x_Q!$C$5:$I$5,0)),0)) -> 4
A73: Câu hỏi 2: giá trị tăng thêm (M1, MIN qua 3 hồ sơ) | B73: M1 | C73: =MIN(IFERROR(INDEX(M1_File_x_Q!$C$6:$I$12,MATCH(C44,M1_File_x_Q!$A$6:$A$12,0),MATCH(C48,M1_File_x_Q!$C$5:$I$5,0)),0),IFERROR(INDEX(M1_File_x_Q!$C$6:$I$12,MATCH(C45,M1_File_x_Q!$A$6:$A$12,0),MATCH(C48,M1_File_x_Q!$C$5:$I$5,0)),0),IFERROR(INDEX(M1_File_x_Q!$C$6:$I$12,MATCH(C46,M1_File_x_Q!$A$6:$A$12,0),MATCH(C48,M1_File_x_Q!$C$5:$I$5,0)),0)) -> 3 | D73: =MIN(IFERROR(INDEX(M1_File_x_Q!$C$6:$I$12,MATCH(D44,M1_File_x_Q!$A$6:$A$12,0),MATCH(D48,M1_File_x_Q!$C$5:$I$5,0)),0),IFERROR(INDEX(M1_File_x_Q!$C$6:$I$12,MATCH(D45,M1_File_x_Q!$A$6:$A$12,0),MATCH(D48,M1_File_x_Q!$C$5:$I$5,0)),0),IFERROR(INDEX(M1_File_x_Q!$C$6:$I$12,MATCH(D46,M1_File_x_Q!$A$6:$A$12,0),MATCH(D48,M1_File_x_Q!$C$5:$I$5,0)),0)) -> 3 | E73: =MIN(IFERROR(INDEX(M1_File_x_Q!$C$6:$I$12,MATCH(E44,M1_File_x_Q!$A$6:$A$12,0),MATCH(E48,M1_File_x_Q!$C$5:$I$5,0)),0),IFERROR(INDEX(M1_File_x_Q!$C$6:$I$12,MATCH(E45,M1_File_x_Q!$A$6:$A$12,0),MATCH(E48,M1_File_x_Q!$C$5:$I$5,0)),0),IFERROR(INDEX(M1_File_x_Q!$C$6:$I$12,MATCH(E46,M1_File_x_Q!$A$6:$A$12,0),MATCH(E48,M1_File_x_Q!$C$5:$I$5,0)),0)) -> 1 | F73: =MIN(IFERROR(INDEX(M1_File_x_Q!$C$6:$I$12,MATCH(F44,M1_File_x_Q!$A$6:$A$12,0),MATCH(F48,M1_File_x_Q!$C$5:$I$5,0)),0),IFERROR(INDEX(M1_File_x_Q!$C$6:$I$12,MATCH(F45,M1_File_x_Q!$A$6:$A$12,0),MATCH(F48,M1_File_x_Q!$C$5:$I$5,0)),0),IFERROR(INDEX(M1_File_x_Q!$C$6:$I$12,MATCH(F46,M1_File_x_Q!$A$6:$A$12,0),MATCH(F48,M1_File_x_Q!$C$5:$I$5,0)),0)) -> 3 | G73: =MIN(IFERROR(INDEX(M1_File_x_Q!$C$6:$I$12,MATCH(G44,M1_File_x_Q!$A$6:$A$12,0),MATCH(G48,M1_File_x_Q!$C$5:$I$5,0)),0),IFERROR(INDEX(M1_File_x_Q!$C$6:$I$12,MATCH(G45,M1_File_x_Q!$A$6:$A$12,0),MATCH(G48,M1_File_x_Q!$C$5:$I$5,0)),0),IFERROR(INDEX(M1_File_x_Q!$C$6:$I$12,MATCH(G46,M1_File_x_Q!$A$6:$A$12,0),MATCH(G48,M1_File_x_Q!$C$5:$I$5,0)),0)) -> 3
A74: Câu hỏi cuối: cơ bản + M2 (chặn fq_cap) | B74: S5 + M2 | C74: =MIN(Config!$B$6,IFERROR(INDEX(S5_FinalQ!$E$5:$E$11,MATCH(C49,S5_FinalQ!$A$5:$A$11,0)),0)+IFERROR(INDEX(M2_File_x_FQ!$C$6:$I$12,MATCH(C44,M2_File_x_FQ!$A$6:$A$12,0),MATCH(C49,M2_File_x_FQ!$C$5:$I$5,0)),0)+IFERROR(INDEX(M2_File_x_FQ!$C$6:$I$12,MATCH(C45,M2_File_x_FQ!$A$6:$A$12,0),MATCH(C49,M2_File_x_FQ!$C$5:$I$5,0)),0)+IFERROR(INDEX(M2_File_x_FQ!$C$6:$I$12,MATCH(C46,M2_File_x_FQ!$A$6:$A$12,0),MATCH(C49,M2_File_x_FQ!$C$5:$I$5,0)),0)) -> 15 | D74: =MIN(Config!$B$6,IFERROR(INDEX(S5_FinalQ!$E$5:$E$11,MATCH(D49,S5_FinalQ!$A$5:$A$11,0)),0)+IFERROR(INDEX(M2_File_x_FQ!$C$6:$I$12,MATCH(D44,M2_File_x_FQ!$A$6:$A$12,0),MATCH(D49,M2_File_x_FQ!$C$5:$I$5,0)),0)+IFERROR(INDEX(M2_File_x_FQ!$C$6:$I$12,MATCH(D45,M2_File_x_FQ!$A$6:$A$12,0),MATCH(D49,M2_File_x_FQ!$C$5:$I$5,0)),0)+IFERROR(INDEX(M2_File_x_FQ!$C$6:$I$12,MATCH(D46,M2_File_x_FQ!$A$6:$A$12,0),MATCH(D49,M2_File_x_FQ!$C$5:$I$5,0)),0)) -> 12 | E74: =MIN(Config!$B$6,IFERROR(INDEX(S5_FinalQ!$E$5:$E$11,MATCH(E49,S5_FinalQ!$A$5:$A$11,0)),0)+IFERROR(INDEX(M2_File_x_FQ!$C$6:$I$12,MATCH(E44,M2_File_x_FQ!$A$6:$A$12,0),MATCH(E49,M2_File_x_FQ!$C$5:$I$5,0)),0)+IFERROR(INDEX(M2_File_x_FQ!$C$6:$I$12,MATCH(E45,M2_File_x_FQ!$A$6:$A$12,0),MATCH(E49,M2_File_x_FQ!$C$5:$I$5,0)),0)+IFERROR(INDEX(M2_File_x_FQ!$C$6:$I$12,MATCH(E46,M2_File_x_FQ!$A$6:$A$12,0),MATCH(E49,M2_File_x_FQ!$C$5:$I$5,0)),0)) -> 10 | F74: =MIN(Config!$B$6,IFERROR(INDEX(S5_FinalQ!$E$5:$E$11,MATCH(F49,S5_FinalQ!$A$5:$A$11,0)),0)+IFERROR(INDEX(M2_File_x_FQ!$C$6:$I$12,MATCH(F44,M2_File_x_FQ!$A$6:$A$12,0),MATCH(F49,M2_File_x_FQ!$C$5:$I$5,0)),0)+IFERROR(INDEX(M2_File_x_FQ!$C$6:$I$12,MATCH(F45,M2_File_x_FQ!$A$6:$A$12,0),MATCH(F49,M2_File_x_FQ!$C$5:$I$5,0)),0)+IFERROR(INDEX(M2_File_x_FQ!$C$6:$I$12,MATCH(F46,M2_File_x_FQ!$A$6:$A$12,0),MATCH(F49,M2_File_x_FQ!$C$5:$I$5,0)),0)) -> 9 | G74: =MIN(Config!$B$6,IFERROR(INDEX(S5_FinalQ!$E$5:$E$11,MATCH(G49,S5_FinalQ!$A$5:$A$11,0)),0)+IFERROR(INDEX(M2_File_x_FQ!$C$6:$I$12,MATCH(G44,M2_File_x_FQ!$A$6:$A$12,0),MATCH(G49,M2_File_x_FQ!$C$5:$I$5,0)),0)+IFERROR(INDEX(M2_File_x_FQ!$C$6:$I$12,MATCH(G45,M2_File_x_FQ!$A$6:$A$12,0),MATCH(G49,M2_File_x_FQ!$C$5:$I$5,0)),0)+IFERROR(INDEX(M2_File_x_FQ!$C$6:$I$12,MATCH(G46,M2_File_x_FQ!$A$6:$A$12,0),MATCH(G49,M2_File_x_FQ!$C$5:$I$5,0)),0)) -> 12
A75: INVESTIGATION SCORE /100 | B75: tổng ÷ điểm tối đa (Config) | C75: =MAX(0,MIN(100,(C71+C72+C73+C74)/Config!$B$7*100)) -> 100 | D75: =MAX(0,MIN(100,(D71+D72+D73+D74)/Config!$B$7*100)) -> 83.606557 | E75: =MAX(0,MIN(100,(E71+E72+E73+E74)/Config!$B$7*100)) -> 50.819672 | F75: =MAX(0,MIN(100,(F71+F72+F73+F74)/Config!$B$7*100)) -> 67.213115 | G75: =MAX(0,MIN(100,(G71+G72+G73+G74)/Config!$B$7*100)) -> 77.04918
A76: F. DIAGNOSIS (Màn 6)
A77: Primary Diagnosis pts (tối đa 60; CD-F thiếu ĐK × hệ số) | B77: S6_Diagnosis | C77: =IFERROR(INDEX(S6_Diagnosis!$E$5:$E$10,MATCH(C50,S6_Diagnosis!$A$5:$A$10,0)),0)*IF(C69=1,Config!$B$10,1) -> 60 | D77: =IFERROR(INDEX(S6_Diagnosis!$E$5:$E$10,MATCH(D50,S6_Diagnosis!$A$5:$A$10,0)),0)*IF(D69=1,Config!$B$10,1) -> 60 | E77: =IFERROR(INDEX(S6_Diagnosis!$E$5:$E$10,MATCH(E50,S6_Diagnosis!$A$5:$A$10,0)),0)*IF(E69=1,Config!$B$10,1) -> 25 | F77: =IFERROR(INDEX(S6_Diagnosis!$E$5:$E$10,MATCH(F50,S6_Diagnosis!$A$5:$A$10,0)),0)*IF(F69=1,Config!$B$10,1) -> 40 | G77: =IFERROR(INDEX(S6_Diagnosis!$E$5:$E$10,MATCH(G50,S6_Diagnosis!$A$5:$A$10,0)),0)*IF(G69=1,Config!$B$10,1) -> 55
A78: Evidence support (M3: hồ sơ + 50% × CH1) | B78: chặn dxsup_cap | C78: =MAX(0,MIN(Config!$B$8,IFERROR(INDEX(M3_Dx_x_File!$C$6:$I$11,MATCH(C50,M3_Dx_x_File!$A$6:$A$11,0),MATCH(C44,M3_Dx_x_File!$C$5:$I$5,0)),0)+IFERROR(INDEX(M3_Dx_x_File!$C$6:$I$11,MATCH(C50,M3_Dx_x_File!$A$6:$A$11,0),MATCH(C45,M3_Dx_x_File!$C$5:$I$5,0)),0)+IFERROR(INDEX(M3_Dx_x_File!$C$6:$I$11,MATCH(C50,M3_Dx_x_File!$A$6:$A$11,0),MATCH(C46,M3_Dx_x_File!$C$5:$I$5,0)),0)+Config!$B$9*(IFERROR(INDEX(M3_Dx_x_File!$C$6:$I$11,MATCH(C50,M3_Dx_x_File!$A$6:$A$11,0),MATCH("HS-"&RIGHT(C47,1),M3_Dx_x_File!$C$5:$I$5,0)),0)+IFERROR(INDEX(M3_Dx_x_File!$C$6:$I$11,MATCH(C50,M3_Dx_x_File!$A$6:$A$11,0),MATCH("HS-"&RIGHT(C48,1),M3_Dx_x_File!$C$5:$I$5,0)),0)))) -> 40 | D78: =MAX(0,MIN(Config!$B$8,IFERROR(INDEX(M3_Dx_x_File!$C$6:$I$11,MATCH(D50,M3_Dx_x_File!$A$6:$A$11,0),MATCH(D44,M3_Dx_x_File!$C$5:$I$5,0)),0)+IFERROR(INDEX(M3_Dx_x_File!$C$6:$I$11,MATCH(D50,M3_Dx_x_File!$A$6:$A$11,0),MATCH(D45,M3_Dx_x_File!$C$5:$I$5,0)),0)+IFERROR(INDEX(M3_Dx_x_File!$C$6:$I$11,MATCH(D50,M3_Dx_x_File!$A$6:$A$11,0),MATCH(D46,M3_Dx_x_File!$C$5:$I$5,0)),0)+Config!$B$9*(IFERROR(INDEX(M3_Dx_x_File!$C$6:$I$11,MATCH(D50,M3_Dx_x_File!$A$6:$A$11,0),MATCH("HS-"&RIGHT(D47,1),M3_Dx_x_File!$C$5:$I$5,0)),0)+IFERROR(INDEX(M3_Dx_x_File!$C$6:$I$11,MATCH(D50,M3_Dx_x_File!$A$6:$A$11,0),MATCH("HS-"&RIGHT(D48,1),M3_Dx_x_File!$C$5:$I$5,0)),0)))) -> 40 | E78: =MAX(0,MIN(Config!$B$8,IFERROR(INDEX(M3_Dx_x_File!$C$6:$I$11,MATCH(E50,M3_Dx_x_File!$A$6:$A$11,0),MATCH(E44,M3_Dx_x_File!$C$5:$I$5,0)),0)+IFERROR(INDEX(M3_Dx_x_File!$C$6:$I$11,MATCH(E50,M3_Dx_x_File!$A$6:$A$11,0),MATCH(E45,M3_Dx_x_File!$C$5:$I$5,0)),0)+IFERROR(INDEX(M3_Dx_x_File!$C$6:$I$11,MATCH(E50,M3_Dx_x_File!$A$6:$A$11,0),MATCH(E46,M3_Dx_x_File!$C$5:$I$5,0)),0)+Config!$B$9*(IFERROR(INDEX(M3_Dx_x_File!$C$6:$I$11,MATCH(E50,M3_Dx_x_File!$A$6:$A$11,0),MATCH("HS-"&RIGHT(E47,1),M3_Dx_x_File!$C$5:$I$5,0)),0)+IFERROR(INDEX(M3_Dx_x_File!$C$6:$I$11,MATCH(E50,M3_Dx_x_File!$A$6:$A$11,0),MATCH("HS-"&RIGHT(E48,1),M3_Dx_x_File!$C$5:$I$5,0)),0)))) -> 40 | F78: =MAX(0,MIN(Config!$B$8,IFERROR(INDEX(M3_Dx_x_File!$C$6:$I$11,MATCH(F50,M3_Dx_x_File!$A$6:$A$11,0),MATCH(F44,M3_Dx_x_File!$C$5:$I$5,0)),0)+IFERROR(INDEX(M3_Dx_x_File!$C$6:$I$11,MATCH(F50,M3_Dx_x_File!$A$6:$A$11,0),MATCH(F45,M3_Dx_x_File!$C$5:$I$5,0)),0)+IFERROR(INDEX(M3_Dx_x_File!$C$6:$I$11,MATCH(F50,M3_Dx_x_File!$A$6:$A$11,0),MATCH(F46,M3_Dx_x_File!$C$5:$I$5,0)),0)+Config!$B$9*(IFERROR(INDEX(M3_Dx_x_File!$C$6:$I$11,MATCH(F50,M3_Dx_x_File!$A$6:$A$11,0),MATCH("HS-"&RIGHT(F47,1),M3_Dx_x_File!$C$5:$I$5,0)),0)+IFERROR(INDEX(M3_Dx_x_File!$C$6:$I$11,MATCH(F50,M3_Dx_x_File!$A$6:$A$11,0),MATCH("HS-"&RIGHT(F48,1),M3_Dx_x_File!$C$5:$I$5,0)),0)))) -> 37 | G78: =MAX(0,MIN(Config!$B$8,IFERROR(INDEX(M3_Dx_x_File!$C$6:$I$11,MATCH(G50,M3_Dx_x_File!$A$6:$A$11,0),MATCH(G44,M3_Dx_x_File!$C$5:$I$5,0)),0)+IFERROR(INDEX(M3_Dx_x_File!$C$6:$I$11,MATCH(G50,M3_Dx_x_File!$A$6:$A$11,0),MATCH(G45,M3_Dx_x_File!$C$5:$I$5,0)),0)+IFERROR(INDEX(M3_Dx_x_File!$C$6:$I$11,MATCH(G50,M3_Dx_x_File!$A$6:$A$11,0),MATCH(G46,M3_Dx_x_File!$C$5:$I$5,0)),0)+Config!$B$9*(IFERROR(INDEX(M3_Dx_x_File!$C$6:$I$11,MATCH(G50,M3_Dx_x_File!$A$6:$A$11,0),MATCH("HS-"&RIGHT(G47,1),M3_Dx_x_File!$C$5:$I$5,0)),0)+IFERROR(INDEX(M3_Dx_x_File!$C$6:$I$11,MATCH(G50,M3_Dx_x_File!$A$6:$A$11,0),MATCH("HS-"&RIGHT(G48,1),M3_Dx_x_File!$C$5:$I$5,0)),0)))) -> 35
A79: DIAGNOSIS SCORE /100 | B79: 60 + 40 | C79: =C77+C78 -> 100 | D79: =D77+D78 -> 100 | E79: =E77+E78 -> 65 | F79: =F77+F78 -> 77 | G79: =G77+G78 -> 90
A80: G. UY TÍN & ĐIỀU KIỆN PHÁC ĐỒ (Màn 6–8)
A81: Uy tín: chẩn đoán có căn cứ (+1 / −1) | B81: Config | C81: =IF(C50="CD-F",IF(C68=1,Config!$B$14,Config!$B$15),IF(OR(COUNTIF(C44:C46,"HS-"&RIGHT(C50,1))>0,COUNTIF(C47:C48,"CH1-"&RIGHT(C50,1))>0),Config!$B$14,Config!$B$15)) -> 1 | D81: =IF(D50="CD-F",IF(D68=1,Config!$B$14,Config!$B$15),IF(OR(COUNTIF(D44:D46,"HS-"&RIGHT(D50,1))>0,COUNTIF(D47:D48,"CH1-"&RIGHT(D50,1))>0),Config!$B$14,Config!$B$15)) -> 1 | E81: =IF(E50="CD-F",IF(E68=1,Config!$B$14,Config!$B$15),IF(OR(COUNTIF(E44:E46,"HS-"&RIGHT(E50,1))>0,COUNTIF(E47:E48,"CH1-"&RIGHT(E50,1))>0),Config!$B$14,Config!$B$15)) -> 1 | F81: =IF(F50="CD-F",IF(F68=1,Config!$B$14,Config!$B$15),IF(OR(COUNTIF(F44:F46,"HS-"&RIGHT(F50,1))>0,COUNTIF(F47:F48,"CH1-"&RIGHT(F50,1))>0),Config!$B$14,Config!$B$15)) -> 1 | G81: =IF(G50="CD-F",IF(G68=1,Config!$B$14,Config!$B$15),IF(OR(COUNTIF(G44:G46,"HS-"&RIGHT(G50,1))>0,COUNTIF(G47:G48,"CH1-"&RIGHT(G50,1))>0),Config!$B$14,Config!$B$15)) -> 1
A82: Uy tín: CD-F thiếu điều kiện | B82: Config | C82: =IF(C69=1,Config!$B$17,0) -> 0 | D82: =IF(D69=1,Config!$B$17,0) -> 0 | E82: =IF(E69=1,Config!$B$17,0) -> 0 | F82: =IF(F69=1,Config!$B$17,0) -> 0 | G82: =IF(G69=1,Config!$B$17,0) -> 0
A83: Uy tín: điều tra hiệu quả (2 CH1 ở khu vực chưa mở) | B83: Config | C83: =IF(AND(COUNTIF(C44:C46,"HS-"&RIGHT(C47,1))=0,COUNTIF(C44:C46,"HS-"&RIGHT(C48,1))=0),Config!$B$16,0) -> 1 | D83: =IF(AND(COUNTIF(D44:D46,"HS-"&RIGHT(D47,1))=0,COUNTIF(D44:D46,"HS-"&RIGHT(D48,1))=0),Config!$B$16,0) -> 1 | E83: =IF(AND(COUNTIF(E44:E46,"HS-"&RIGHT(E47,1))=0,COUNTIF(E44:E46,"HS-"&RIGHT(E48,1))=0),Config!$B$16,0) -> 0 | F83: =IF(AND(COUNTIF(F44:F46,"HS-"&RIGHT(F47,1))=0,COUNTIF(F44:F46,"HS-"&RIGHT(F48,1))=0),Config!$B$16,0) -> 1 | G83: =IF(AND(COUNTIF(G44:G46,"HS-"&RIGHT(G47,1))=0,COUNTIF(G44:G46,"HS-"&RIGHT(G48,1))=0),Config!$B$16,0) -> 1
A84: Uy tín tại Màn 7 (điểm) | B84: khởi điểm + các mục trên | C84: =Config!$B$11+C81+C82+C83 -> 4 | D84: =Config!$B$11+D81+D82+D83 -> 4 | E84: =Config!$B$11+E81+E82+E83 -> 3 | F84: =Config!$B$11+F81+F82+F83 -> 4 | G84: =Config!$B$11+G81+G82+G83 -> 4
A85: Uy tín tại Màn 7 (tier) | B85: Config | C85: =IF(C84>=Config!$B$13,"Cao",IF(C84>=Config!$B$12,"Trung bình","Thấp")) -> Cao | D85: =IF(D84>=Config!$B$13,"Cao",IF(D84>=Config!$B$12,"Trung bình","Thấp")) -> Cao | E85: =IF(E84>=Config!$B$13,"Cao",IF(E84>=Config!$B$12,"Trung bình","Thấp")) -> Trung bình | F85: =IF(F84>=Config!$B$13,"Cao",IF(F84>=Config!$B$12,"Trung bình","Thấp")) -> Cao | G85: =IF(G84>=Config!$B$13,"Cao",IF(G84>=Config!$B$12,"Trung bình","Thấp")) -> Cao
A86: Phác đồ HIỆU LỰC sau kiểm tra Uy tín | B86: PD-A cần ≥TB; PD-F cần Cao | C86: =IF(C51="PD-A",IF(C84>=Config!$B$12,"PD-A","PD-B"),IF(C51="PD-F",IF(C84>=Config!$B$13,"PD-F","PD-B"),C51)) -> PD-F | D86: =IF(D51="PD-A",IF(D84>=Config!$B$12,"PD-A","PD-B"),IF(D51="PD-F",IF(D84>=Config!$B$13,"PD-F","PD-B"),D51)) -> PD-C | E86: =IF(E51="PD-A",IF(E84>=Config!$B$12,"PD-A","PD-B"),IF(E51="PD-F",IF(E84>=Config!$B$13,"PD-F","PD-B"),E51)) -> PD-A | F86: =IF(F51="PD-A",IF(F84>=Config!$B$12,"PD-A","PD-B"),IF(F51="PD-F",IF(F84>=Config!$B$13,"PD-F","PD-B"),F51)) -> PD-B | G86: =IF(G51="PD-A",IF(G84>=Config!$B$12,"PD-A","PD-B"),IF(G51="PD-F",IF(G84>=Config!$B$13,"PD-F","PD-B"),G51)) -> PD-E
A87: Bị hạ xuống PD-B? (1/0) | C87: =IF(AND(C51<>"",C86<>C51),1,0) -> 0 | D87: =IF(AND(D51<>"",D86<>D51),1,0) -> 0 | E87: =IF(AND(E51<>"",E86<>E51),1,0) -> 0 | F87: =IF(AND(F51<>"",F86<>F51),1,0) -> 0 | G87: =IF(AND(G51<>"",G86<>G51),1,0) -> 0
A88: TG-C refinance thử THẤT BẠI? (1/0) | B88: TG-C + không ưu tiên Creditors | C88: =IF(AND(C52="TG-C",C62=0),1,0) -> 0 | D88: =IF(AND(D52="TG-C",D62=0),1,0) -> 0 | E88: =IF(AND(E52="TG-C",E62=0),1,0) -> 0 | F88: =IF(AND(F52="TG-C",F62=0),1,0) -> 0 | G88: =IF(AND(G52="TG-C",G62=0),1,0) -> 0
A89: Uy tín sau Màn 8 (điểm) | C89: =C84+C88*Config!$B$18 -> 4 | D89: =D84+D88*Config!$B$18 -> 4 | E89: =E84+E88*Config!$B$18 -> 3 | F89: =F84+F88*Config!$B$18 -> 4 | G89: =G84+G88*Config!$B$18 -> 4
A90: H. TREATMENT (Màn 7)
A91: Độ phù hợp vs NGUYÊN NHÂN GỐC (M4) | B91: row = Config true Dx | C91: =IFERROR(INDEX(M4_Dx_x_Tx!$C$6:$H$11,MATCH(Config!$B$4,M4_Dx_x_Tx!$A$6:$A$11,0),MATCH(C86,M4_Dx_x_Tx!$C$5:$H$5,0)),0) -> 90 | D91: =IFERROR(INDEX(M4_Dx_x_Tx!$C$6:$H$11,MATCH(Config!$B$4,M4_Dx_x_Tx!$A$6:$A$11,0),MATCH(D86,M4_Dx_x_Tx!$C$5:$H$5,0)),0) -> 85 | E91: =IFERROR(INDEX(M4_Dx_x_Tx!$C$6:$H$11,MATCH(Config!$B$4,M4_Dx_x_Tx!$A$6:$A$11,0),MATCH(E86,M4_Dx_x_Tx!$C$5:$H$5,0)),0) -> 20 | F91: =IFERROR(INDEX(M4_Dx_x_Tx!$C$6:$H$11,MATCH(Config!$B$4,M4_Dx_x_Tx!$A$6:$A$11,0),MATCH(F86,M4_Dx_x_Tx!$C$5:$H$5,0)),0) -> 40 | G91: =IFERROR(INDEX(M4_Dx_x_Tx!$C$6:$H$11,MATCH(Config!$B$4,M4_Dx_x_Tx!$A$6:$A$11,0),MATCH(G86,M4_Dx_x_Tx!$C$5:$H$5,0)),0) -> 80
A92: Độ phù hợp vs chẩn đoán của người chơi (M4) | B92: row = Dx của bạn | C92: =IFERROR(INDEX(M4_Dx_x_Tx!$C$6:$H$11,MATCH(C50,M4_Dx_x_Tx!$A$6:$A$11,0),MATCH(C86,M4_Dx_x_Tx!$C$5:$H$5,0)),0) -> 90 | D92: =IFERROR(INDEX(M4_Dx_x_Tx!$C$6:$H$11,MATCH(D50,M4_Dx_x_Tx!$A$6:$A$11,0),MATCH(D86,M4_Dx_x_Tx!$C$5:$H$5,0)),0) -> 85 | E92: =IFERROR(INDEX(M4_Dx_x_Tx!$C$6:$H$11,MATCH(E50,M4_Dx_x_Tx!$A$6:$A$11,0),MATCH(E86,M4_Dx_x_Tx!$C$5:$H$5,0)),0) -> 90 | F92: =IFERROR(INDEX(M4_Dx_x_Tx!$C$6:$H$11,MATCH(F50,M4_Dx_x_Tx!$A$6:$A$11,0),MATCH(F86,M4_Dx_x_Tx!$C$5:$H$5,0)),0) -> 65 | G92: =IFERROR(INDEX(M4_Dx_x_Tx!$C$6:$H$11,MATCH(G50,M4_Dx_x_Tx!$A$6:$A$11,0),MATCH(G86,M4_Dx_x_Tx!$C$5:$H$5,0)),0) -> 70
A93: TREATMENT SCORE /100 | B93: 60% gốc + 40% tự chẩn đoán | C93: =Config!$B$20*C91+Config!$B$21*C92 -> 90 | D93: =Config!$B$20*D91+Config!$B$21*D92 -> 85 | E93: =Config!$B$20*E91+Config!$B$21*E92 -> 48 | F93: =Config!$B$20*F91+Config!$B$21*F92 -> 50 | G93: =Config!$B$20*G91+Config!$B$21*G92 -> 76
A94: I. EXECUTION PLANNING (Màn 8–9)
A95: Điểm thời điểm (M5) | B95: PD hiệu lực × Thời điểm | C95: =IFERROR(INDEX(M5_Tx_x_Timing!$C$6:$F$11,MATCH(C86,M5_Tx_x_Timing!$A$6:$A$11,0),MATCH(C52,M5_Tx_x_Timing!$C$5:$F$5,0)),0) -> 80 | D95: =IFERROR(INDEX(M5_Tx_x_Timing!$C$6:$F$11,MATCH(D86,M5_Tx_x_Timing!$A$6:$A$11,0),MATCH(D52,M5_Tx_x_Timing!$C$5:$F$5,0)),0) -> 90 | E95: =IFERROR(INDEX(M5_Tx_x_Timing!$C$6:$F$11,MATCH(E86,M5_Tx_x_Timing!$A$6:$A$11,0),MATCH(E52,M5_Tx_x_Timing!$C$5:$F$5,0)),0) -> 55 | F95: =IFERROR(INDEX(M5_Tx_x_Timing!$C$6:$F$11,MATCH(F86,M5_Tx_x_Timing!$A$6:$A$11,0),MATCH(F52,M5_Tx_x_Timing!$C$5:$F$5,0)),0) -> 25 | G95: =IFERROR(INDEX(M5_Tx_x_Timing!$C$6:$F$11,MATCH(G86,M5_Tx_x_Timing!$A$6:$A$11,0),MATCH(G52,M5_Tx_x_Timing!$C$5:$F$5,0)),0) -> 85
A96: Điểm thô 3 nhóm ưu tiên (M6) | B96: M6 | C96: =IFERROR(INDEX(M6_Tx_x_Stake!$C$6:$I$11,MATCH(C86,M6_Tx_x_Stake!$A$6:$A$11,0),MATCH(C53,M6_Tx_x_Stake!$C$5:$I$5,0)),0)+IFERROR(INDEX(M6_Tx_x_Stake!$C$6:$I$11,MATCH(C86,M6_Tx_x_Stake!$A$6:$A$11,0),MATCH(C54,M6_Tx_x_Stake!$C$5:$I$5,0)),0)+IFERROR(INDEX(M6_Tx_x_Stake!$C$6:$I$11,MATCH(C86,M6_Tx_x_Stake!$A$6:$A$11,0),MATCH(C55,M6_Tx_x_Stake!$C$5:$I$5,0)),0) -> 65 | D96: =IFERROR(INDEX(M6_Tx_x_Stake!$C$6:$I$11,MATCH(D86,M6_Tx_x_Stake!$A$6:$A$11,0),MATCH(D53,M6_Tx_x_Stake!$C$5:$I$5,0)),0)+IFERROR(INDEX(M6_Tx_x_Stake!$C$6:$I$11,MATCH(D86,M6_Tx_x_Stake!$A$6:$A$11,0),MATCH(D54,M6_Tx_x_Stake!$C$5:$I$5,0)),0)+IFERROR(INDEX(M6_Tx_x_Stake!$C$6:$I$11,MATCH(D86,M6_Tx_x_Stake!$A$6:$A$11,0),MATCH(D55,M6_Tx_x_Stake!$C$5:$I$5,0)),0) -> 70 | E96: =IFERROR(INDEX(M6_Tx_x_Stake!$C$6:$I$11,MATCH(E86,M6_Tx_x_Stake!$A$6:$A$11,0),MATCH(E53,M6_Tx_x_Stake!$C$5:$I$5,0)),0)+IFERROR(INDEX(M6_Tx_x_Stake!$C$6:$I$11,MATCH(E86,M6_Tx_x_Stake!$A$6:$A$11,0),MATCH(E54,M6_Tx_x_Stake!$C$5:$I$5,0)),0)+IFERROR(INDEX(M6_Tx_x_Stake!$C$6:$I$11,MATCH(E86,M6_Tx_x_Stake!$A$6:$A$11,0),MATCH(E55,M6_Tx_x_Stake!$C$5:$I$5,0)),0) -> 60 | F96: =IFERROR(INDEX(M6_Tx_x_Stake!$C$6:$I$11,MATCH(F86,M6_Tx_x_Stake!$A$6:$A$11,0),MATCH(F53,M6_Tx_x_Stake!$C$5:$I$5,0)),0)+IFERROR(INDEX(M6_Tx_x_Stake!$C$6:$I$11,MATCH(F86,M6_Tx_x_Stake!$A$6:$A$11,0),MATCH(F54,M6_Tx_x_Stake!$C$5:$I$5,0)),0)+IFERROR(INDEX(M6_Tx_x_Stake!$C$6:$I$11,MATCH(F86,M6_Tx_x_Stake!$A$6:$A$11,0),MATCH(F55,M6_Tx_x_Stake!$C$5:$I$5,0)),0) -> 60 | G96: =IFERROR(INDEX(M6_Tx_x_Stake!$C$6:$I$11,MATCH(G86,M6_Tx_x_Stake!$A$6:$A$11,0),MATCH(G53,M6_Tx_x_Stake!$C$5:$I$5,0)),0)+IFERROR(INDEX(M6_Tx_x_Stake!$C$6:$I$11,MATCH(G86,M6_Tx_x_Stake!$A$6:$A$11,0),MATCH(G54,M6_Tx_x_Stake!$C$5:$I$5,0)),0)+IFERROR(INDEX(M6_Tx_x_Stake!$C$6:$I$11,MATCH(G86,M6_Tx_x_Stake!$A$6:$A$11,0),MATCH(G55,M6_Tx_x_Stake!$C$5:$I$5,0)),0) -> 70
A97: Top-3 tốt nhất của phác đồ | B97: M6 cột J | C97: =IFERROR(INDEX(M6_Tx_x_Stake!$J$6:$J$11,MATCH(C86,M6_Tx_x_Stake!$A$6:$A$11,0)),0) -> 70 | D97: =IFERROR(INDEX(M6_Tx_x_Stake!$J$6:$J$11,MATCH(D86,M6_Tx_x_Stake!$A$6:$A$11,0)),0) -> 70 | E97: =IFERROR(INDEX(M6_Tx_x_Stake!$J$6:$J$11,MATCH(E86,M6_Tx_x_Stake!$A$6:$A$11,0)),0) -> 70 | F97: =IFERROR(INDEX(M6_Tx_x_Stake!$J$6:$J$11,MATCH(F86,M6_Tx_x_Stake!$A$6:$A$11,0)),0) -> 60 | G97: =IFERROR(INDEX(M6_Tx_x_Stake!$J$6:$J$11,MATCH(G86,M6_Tx_x_Stake!$A$6:$A$11,0)),0) -> 80
A98: Stakeholder score | B98: thô ÷ tốt nhất × 100 | C98: =IF(C97=0,0,MAX(0,MIN(100,C96/C97*100))) -> 92.857143 | D98: =IF(D97=0,0,MAX(0,MIN(100,D96/D97*100))) -> 100 | E98: =IF(E97=0,0,MAX(0,MIN(100,E96/E97*100))) -> 85.714286 | F98: =IF(F97=0,0,MAX(0,MIN(100,F96/F97*100))) -> 100 | G98: =IF(G97=0,0,MAX(0,MIN(100,G96/G97*100))) -> 87.5
A99: EXECUTION SCORE /100 | B99: 50% thời điểm + 50% nhóm | C99: =Config!$B$22*C95+Config!$B$23*C98 -> 86.428571 | D99: =Config!$B$22*D95+Config!$B$23*D98 -> 95 | E99: =Config!$B$22*E95+Config!$B$23*E98 -> 70.357143 | F99: =Config!$B$22*F95+Config!$B$23*F98 -> 62.5 | G99: =Config!$B$22*G95+Config!$B$23*G98 -> 86.25
A100: J. DIỄN BIẾN MÀN 10 (1 = xảy ra)
A101: E1 · Store Update: đóng thêm cửa hàng ngoài kế hoạch | B101: PD hiệu lực = PD-B + TG-A + KHÔNG ưu tiê | C101: =IF(AND(C86="PD-B",C52="TG-A",C60=0),1,0) -> 0 | D101: =IF(AND(D86="PD-B",D52="TG-A",D60=0),1,0) -> 0 | E101: =IF(AND(E86="PD-B",E52="TG-A",E60=0),1,0) -> 0 | F101: =IF(AND(F86="PD-B",F52="TG-A",F60=0),1,0) -> 0 | G101: =IF(AND(G86="PD-B",G52="TG-A",G60=0),1,0) -> 0
...

Sheet Case_Facts
A1: Case #01 — Toy Kingdom Inc. (mô phỏng Toys "R" Us): tổng quan & bí mật nền
A2: Nội dung lấy từ USER_FLOW_GỐC. Mục 'GIẢ ĐỊNH THIẾT KẾ' là phần bổ sung để chấm điểm.
A4: Nhóm | B4: Trường | C4: Nội dung
A5: Tổng quan | B5: Công ty | C5: Toy Kingdom Inc. (mô phỏng Toys "R" Us, Inc.)
A6: Tổng quan | B6: Ngành / quy mô | C6: Specialty retail — đồ chơi & sản phẩm trẻ em; ~1.700 cửa hàng toàn cầu.
A7: Tổng quan | B7: Doanh thu FY2026 | C7: $11.540 tỷ
A8: Tổng quan | B8: Sở hữu | C8: Gia đình Anderson 78% (David — CEO, Michael — em trai, Richard — chú); quỹ đầu tư tư nhân 22%.
A9: Tổng quan | B9: Kết quả FY2026 | C9: Adjusted EBITDA $792m; Operating Earnings $460m; Net Loss attributable −$36m.
A10: Tổng quan | B10: Lý do khám | C10: Kinh doanh có dấu hiệu cải thiện nhưng thiếu nguồn lực tái đầu tư, áp lực tài chính tăng, ban lãnh đạo gia đình chia rẽ.
A11: Màn 1 | B11: David (CEO) | C11: "Sales tiếp tục giảm… Một số chỉ số tốt lên nhưng công ty vẫn ngày càng khó xoay xở." Không biết vấn đề nằm ở thị trường, cấu trúc tài chính hay ban lãnh đạo.
A12: Bí mật nền | B12: Thỏa thuận Michael–Houndstooth | C12: Nếu Adjusted EBITDA giảm thêm 5% so với FY2026, Houndstooth có quyền mua ưu tiên cổ phần gia đình với giá thấp. Chỉ xác nhận đầy đủ khi mở HS-G.
A13: Bí mật nền | B13: Richard | C13: Muốn thanh lý tài sản quốc tế để chia tiền mặt ngay.
A14: Trục theo dõi | B14: Uy tín | C14: Thấp / Trung bình / Cao — không đổi ô kết cục, đổi cách mô tả người chơi; là điều kiện mở PD-A (≥ TB) và PD-F (Cao).
A15: Trục theo dõi | B15: Sức khỏe Tài chính | C15: Điểm → Ổn định / Mong manh / Sụp đổ.
... A20: GIẢ ĐỊNH THIẾT KẾ | B20: Lớp điểm /100 | C20: Investigation, Diagnosis, Treatment, Execution, Reassessment và Overall là lớp chấm điểm bổ sung để so sánh; kết cục cuối vẫn theo 3 trục của USER_FLOW gốc.

Sheet Financials
A1: Màn 4 — Báo cáo tài chính đầy đủ (triệu USD)
A2: Số liệu từ USER_FLOW gốc (xanh = dữ liệu; đen = công thức). Chỉ số đòn bẩy là phần tính thêm.
A4: Chỉ tiêu | B4: FY2024 | C4: FY2025 | D4: FY2026 | E4: FY26 vs FY25 | F4: Tín hiệu
A5: CONSOLIDATED INCOME STATEMENT
A6: Net Sales | B6: 12361 | C6: 11802 | D6: 11540 | E6: =D6-C6 -> -262 | F6: Doanh thu giảm 2.2%
A7: Cost of Sales | B7: 7931 | C7: 7576 | D7: 7432 | E7: =D7-C7 -> -144
A8: Gross Margin | B8: =B6-B7 -> 4430 | C8: =C6-C7 -> 4226 | D8: =D6-D7 -> 4108 | E8: =D8-C8 -> -118
A9: SG&A | B9: 3915 | C9: 3593 | D9: 3480 | E9: =D9-C9 -> -113
A10: Depreciation & Amortization | B10: 377 | C10: 343 | D10: 317 | E10: =D10-C10 -> -26
A11: Other Income, net | B11: 53 | C11: 88 | D11: 149 | E11: =D11-C11 -> 61 | F11: Tăng bất thường (bảo hiểm nhân thọ, tranh chấp)
A12: Operating Earnings | B12: =B8-B9-B10+B11 -> 191 | C12: =C8-C9-C10+C11 -> 378 | D12: =D8-D9-D10+D11 -> 460 | E12: =D12-C12 -> 82
A13: Interest Expense | B13: 451 | C13: 429 | D13: 457 | E13: =D13-C13 -> 28 | F13: Lãi vay ≈ Operating Earnings
A14: Interest Income | B14: 4 | C14: 3 | D14: 2 | E14: =D14-C14 -> -1
A15: Earnings / (Loss) Before Tax | B15: =B12-B13+B14 -> -256 | C15: =C12-C13+C14 -> -48 | D15: =D12-D13+D14 -> 5 | E15: =D15-C15 -> 53
A16: Income Tax Expense | B16: 32 | C16: 76 | D16: 34 | E16: =D16-C16 -> -42
A17: Net Loss | B17: =B15-B16 -> -288 | C17: =C15-C16 -> -124 | D17: =D15-D16 -> -29 | E17: =D17-C17 -> 95
A18: Noncontrolling Interest | B18: 4 | C18: 6 | D18: 7 | E18: =D18-C18 -> 1
A19: Net Loss attributable to Toys "R" Us | B19: =B17-B18 -> -292 | C19: =C17-C18 -> -130 | D19: =D17-D18 -> -36 | E19: =D19-C19 -> 94 | F19: Lỗ thu hẹp nhưng vẫn lỗ
A20: OPERATING METRICS
A21: Adjusted EBITDA | B21: 642 | C21: 800 | D21: 792 | E21: =D21-C21 -> -8 | F21: Giảm 1.0% — đã dùng 1/5 biên trigger Houndstooth
A22: Consolidated SSS | B22: 0 | C22: 0.009 | D22: -0.014
A23: Gross Margin % | B23: =B8/B6 -> 0.35838524 | C23: =C8/C6 -> 0.3580749 | D23: =D8/D6 -> 0.3559792
A24: SG&A / Sales | B24: =B9/B6 -> 0.31672195 | C24: =C9/C6 -> 0.30443993 | D24: =D9/D6 -> 0.30155979
A25: Net Sales growth | C25: =C6/B6-1 -> -0.045222878 | D25: =D6/C6-1 -> -0.022199627
A26: BALANCE SHEET SNAPSHOT — FY2026
A27: Cash & Cash Equivalents | D27: 566
A28: Receivables | D28: 255
A29: Inventory | D29: 2476
A30: Total Current Assets | D30: 3389
A31: Property & Equipment | D31: 3067
A32: Total Indebtedness | D32: 4800 | F32: ~$4.8bn
A33: Secured Indebtedness | D33: 3400 | F33: ~$3.4bn
A34: Stockholders' Equity (deficit) | D34: -1300 | F34: ~$1.3bn deficit
A35: LEVERAGE INDICATORS — FY2026 (tính thêm)
A36: Debt / Adj. EBITDA (x) | D36: =D32/D21 -> 6.0606061 | F36: Đòn bẩy rất cao
A37: Secured debt / Adj. EBITDA (x) | D37: =D33/D21 -> 4.2929293
A38: Net debt / Adj. EBITDA (x) | D38: =(D32-D27)/D21 -> 5.3459596
A39: Adj. EBITDA / Interest expense (x) | D39: =D21/D13 -> 1.7330416 | F39: Bao phủ lãi mỏng
A40: Operating Earnings / Interest (x) | D40: =D12/D13 -> 1.0065646 | F40: ≈ 1.0x
A41: Cash / Total debt | D41: =D27/D32 -> 0.11791667
A42: Inventory / Current assets | D42: =D29/D30 -> 0.730599
A43: Houndstooth trigger: Adj. EBITDA thấp hơn (−5%) | D43: =D21*0.95 -> 752.4 | F43: Giả định ngưỡng từ Bí mật nền
A44: OPERATING CASH FLOW TRƯỚC GIAO DỊCH 2015 (HS-D)
A45: Operating Cash Flow 2012 | D45: 575
A46: Operating Cash Flow 2013 | D46: 801
A47: Operating Cash Flow 2014 | D47: 746

Sheet Config
A1: Config — tham số toàn cục (chữ xanh = chỉnh được)
A2: Đổi giá trị ở đây, mọi điểm ở Scorecard / Comparison tự tính lại.
A3: Parameter | B3: Value | C3: Note
A4: Chẩn đoán ở TẦNG CẤU TRÚC sâu nhất, dùng làm mốc chấm Treatment (ID) | B4: CD-D | C4: HS-D ghi 'Gốc rễ: giao dịch 2015'. Đây là mốc CHẤM ĐIỂM, không phải tuyên bố '6 chẩn đoán kia sai' (USER_FLOW bản sửa, Màn 6).
A5: Điểm câu hỏi bổ sung khi khu vực ĐÃ mở hồ sơ | B5: 1 | C5: USER_FLOW: chỉ củng cố thêm chi tiết nhỏ.
A6: Trần điểm câu hỏi cuối | B6: 15
A7: Điểm thông tin tối đa đạt được (chuẩn hóa Investigation) | B7: 61 | C7: Tính bằng vét cạn: 3 hồ sơ + 2 CH1 + 1 CH2 tốt nhất. Tính lại nếu đổi điểm.
A8: Trần Evidence support (Diagnosis) | B8: 40
A9: Hệ số bằng chứng từ câu hỏi CH1 (so với hồ sơ đầy đủ) | B9: 0.5
A10: Hệ số điểm CD-F khi THIẾU điều kiện | B10: 0.5 | C10: Kèm Uy tín −1 (USER_FLOW Màn 6).
A11: Uy tín khởi điểm (điểm) | B11: 2 | C11: GIẢ ĐỊNH: case gốc không nêu điểm khởi đầu. 2 = Trung bình.
A12: Uy tín: Trung bình khi ≥ | B12: 2 | C12: Thấp: <2 · Trung bình: 2–3 · Cao: ≥4.
A13: Uy tín: Cao khi ≥ | B13: 4 | C13: PD-F cần Cao; PD-A cần ≥ Trung bình.
A14: Uy tín: chẩn đoán CÓ căn cứ | B14: 1 | C14: GIẢ ĐỊNH (case gốc: 'tăng/giảm theo lựa chọn có/không đủ căn cứ').
A15: Uy tín: chẩn đoán KHÔNG có căn cứ | B15: -1 | C15: Căn cứ = đã mở HS-x hoặc hỏi CH1-x của chính chẩn đoán (CD-F: đủ điều kiện).
A16: Uy tín: điều tra hiệu quả (2 CH1 vào 2 khu vực chưa mở) | B16: 1 | C16: GIẢ ĐỊNH — thưởng cho việc không lãng phí 'cơ hội duy nhất'.
A17: Uy tín: chọn CD-F thiếu điều kiện | B17: -1 | C17: Theo USER_FLOW Màn 6.
A18: Uy tín: TG-C refinance thử thất bại | B18: -1 | C18: Theo USER_FLOW Màn 8. Thất bại = KHÔNG ưu tiên Creditors (GIẢ ĐỊNH).
A19: Uy tín: mỗi lần đổi chẩn đoán/phác đồ thiếu dữ liệu mới | B19: -1 | C19: Theo USER_FLOW Màn 11.
A20: Treatment: trọng số độ phù hợp với nguyên nhân gốc | B20: 0.6
A21: Treatment: trọng số độ phù hợp với chẩn đoán của người chơi | B21: 0.4
A22: Execution: trọng số thời điểm | B22: 0.5
A23: Execution: trọng số nhóm ưu tiên | B23: 0.5
A24: Độ phù hợp để tính là kế hoạch MẠNH (Reassessment) | B24: 80
A25: Reassessment: trọng số quyết định | B25: 0.7
A26: Reassessment: trọng số chất lượng phán đoán cuối | B26: 0.3
A27: Reassessment: phạt (điểm /100) mỗi lần đổi thiếu căn cứ | B27: 10
A28: Tài chính: Ổn định khi điểm ≥ | B28: 4 | C28: Đã CHỐT CHÍNH THỨC theo USER_FLOW bản sửa (Màn 12): ngưỡng ≥5 gốc không đạt được với thang điểm (tối đa +4) nên đội quyết định đổi thành ≥4 — không còn là giả định.
A29: Tài chính: Mong manh khi điểm ≥ | B29: 1 | C29: USER_FLOW: 1–4 mong manh; ≤0 sụp đổ.
A30: Quản trị: Đoàn kết khi điểm ≥ | B30: 3 | C30: USER_FLOW: ≥3.
A31: Quản trị: Chia rẽ chưa vỡ khi điểm ≥ | B31: 0 | C31: USER_FLOW: 0–2; <0 mất kiểm soát.
A32: Quản trị: đã mở HS-G | B32: 1
A33: Quản trị: mỗi lần mất Uy tín ở Màn 11 | B33: -1
A34: Quản trị: Tài chính rơi vào Sụp đổ | B34: -2
A35: Quản trị: chọn PD-D mà chưa mở HS-E | B35: -1
A36: Feedback band: High ≥ | B36: 80
A37: Feedback band: Mid ≥ | B37: 50
A39: Trọng số Counselor Score (tổng phải = 100%)
A40: Dimension | B40: Weight | C40: Cách tính (tối đa 100)
A41: Investigation | B41: 0.2 | C41: (Hồ sơ + CH1 + CH2 + synergy) ÷ điểm thông tin tối đa × 100
A42: Diagnosis | B42: 0.25 | C42: Primary (tối đa 60) + Evidence support M3 (tối đa 40)
A43: Treatment | B43: 0.2 | C43: M4: 60% vs nguyên nhân gốc + 40% vs chẩn đoán của bạn
A44: Execution | B44: 0.2 | C44: 50% thời điểm M5 + 50% nhóm ưu tiên M6
A45: Reassessment | B45: 0.15 | C45: 70% quyết định + 30% chất lượng phán đoán cuối − phạt đổi thiếu căn cứ
A46: Total (check = 100%) | B46: =SUM(B41:B45) -> 1
A48: Grade (Overall Counselor Score)
A49: Min score | B49: Grade | C49: Meaning
A50: 85 | B50: Excellent | C50: Sẵn sàng tư vấn độc lập.
A51: 70 | B51: Proficient | C51: Phán đoán vững, còn khoảng trống nhỏ.
A52: 50 | B52: Developing | C52: Hiểu luồng; cần nối bằng chứng với quyết định chặt hơn.
A53: 0 | B53: Needs Review | C53: Nên chơi lại.

Sheet Lists
A1: Lists — nguồn dropdown (tự sinh, không sửa)
A3: Files | B3: Questions | C3: Final Q | D3: Diagnosis | E3: Treatment | F3: Timing | G3: Stakeholder | H3: Reassess decision
A4: =S2_Files!A5&" - "&S2_Files!B5 -> HS-A - Sales & Customer | B4: =S3_Questions!A5&" - "&S3_Questions!B5 -> CH1-A - Traffic giảm, e-commerce tăng — khách rời bỏ hay đổi kênh? | C4: =S5_FinalQ!A5&" - "&S5_FinalQ!B5 -> CH2-A - Khoản nào khó cắt nhất? | D4: =S6_Diagnosis!A5&" - "&S6_Diagnosis!B5 -> CD-A - Áp lực Cạnh tranh (Competitive Pressure) | E4: =S7_Treatment!A5&" - "&S7_Treatment!B5 -> PD-A - Invest to Compete | F4: =S8_Timing!A5&" - "&S8_Timing!B5 -> TG-A - Thực hiện ngay | G4: =S9_Stakeholders!A5&" - "&S9_Stakeholders!B5 -> GR-1 - Suppliers | H4: Keep
A5: =S2_Files!A6&" - "&S2_Files!B6 -> HS-B - Stores & Investment | B5: =S3_Questions!A6&" - "&S3_Questions!B6 -> CH1-B - Chương trình vốn nào bị trì hoãn lâu nhất? | C5: =S5_FinalQ!A6&" - "&S5_FinalQ!B6 -> CH2-B - Có thêm vốn thì dùng vào đâu? | D5: =S6_Diagnosis!A6&" - "&S6_Diagnosis!B6 -> CD-B - Nút thắt Vận hành (Operational Bottleneck) | E5: =S7_Treatment!A6&" - "&S7_Treatment!B6 -> PD-B - Deep Cost Cutting | F5: =S8_Timing!A6&" - "&S8_Timing!B6 -> TG-B - Sau holiday season | G5: =S9_Stakeholders!A6&" - "&S9_Stakeholders!B6 -> GR-2 - Employees | H5: Revise Diagnosis
A6: =S2_Files!A7&" - "&S2_Files!B7 -> HS-C - Liquidity | B6: =S3_Questions!A7&" - "&S3_Questions!B7 -> CH1-C - Holiday kém 10% thì thanh khoản ra sao? | C6: =S5_FinalQ!A7&" - "&S5_FinalQ!B7 -> CH2-C - Sao không đóng mạnh cửa hàng? | D6: =S6_Diagnosis!A7&" - "&S6_Diagnosis!B7 -> CD-C - Biểu hiện Thanh khoản tức thời (Liquidity Manifestation) | E6: =S7_Treatment!A7&" - "&S7_Treatment!B7 -> PD-C - Debt Restructuring | F6: =S8_Timing!A7&" - "&S8_Timing!B7 -> TG-C - Thử tái cấp vốn trước khi cam kết kế hoạch | G6: =S9_Stakeholders!A7&" - "&S9_Stakeholders!B7 -> GR-3 - Customers | H6: Revise Treatment
A7: =S2_Files!A8&" - "&S2_Files!B8 -> HS-D - Capital Structure & Leverage History | B7: =S3_Questions!A8&" - "&S3_Questions!B8 -> CH1-D - Khoản nợ nào đến hạn sớm nhất? | C7: =S5_FinalQ!A8&" - "&S5_FinalQ!B8 -> CH2-D - Amazon biến mất thì công ty khỏe chưa? | D7: =S6_Diagnosis!A8&" - "&S6_Diagnosis!B8 -> CD-D - Nguyên nhân Cấu trúc (Structural Driver) | E7: =S7_Treatment!A8&" - "&S7_Treatment!B8 -> PD-D - Asset Sale | F7: =S8_Timing!A8&" - "&S8_Timing!B8 -> TG-D - Chờ 6 tháng | G7: =S9_Stakeholders!A8&" - "&S9_Stakeholders!B8 -> GR-4 - Creditors | H7: Revise Both
A8: =S2_Files!A9&" - "&S2_Files!B9 -> HS-E - Product & Category Trends | B8: =S3_Questions!A9&" - "&S3_Questions!B9 -> CH1-E - Nhóm sản phẩm nào đang hoạt động tốt nhất? | C8: =S5_FinalQ!A9&" - "&S5_FinalQ!B9 -> CH2-E - Nếu loại bỏ được phần lớn áp lực nợ, đã giải quyết toàn bộ vấn đề chưa? | D8: =S6_Diagnosis!A9&" - "&S6_Diagnosis!B9 -> CD-E - Áp lực Danh mục Sản phẩm (Category Pressure) | E8: =S7_Treatment!A9&" - "&S7_Treatment!B9 -> PD-E - Bankruptcy Restructuring | G8: =S9_Stakeholders!A9&" - "&S9_Stakeholders!B9 -> GR-5 - Landlords
A9: =S2_Files!A10&" - "&S2_Files!B10 -> HS-F - Management Track Record | B9: =S3_Questions!A10&" - "&S3_Questions!B10 -> CH1-F - Ban lãnh đạo có đồng thuận không? | C9: =S5_FinalQ!A10&" - "&S5_FinalQ!B10 -> CH2-F - Lo nhất điều gì trong 12 tháng tới? | D9: =S6_Diagnosis!A10&" - "&S6_Diagnosis!B10 -> CD-F - Chẩn đoán Đa yếu tố (Multi-Factor Diagnosis) | E9: =S7_Treatment!A10&" - "&S7_Treatment!B10 -> PD-F - Combined Restructuring | G9: =S9_Stakeholders!A10&" - "&S9_Stakeholders!B10 -> GR-6 - Holiday Inventory
A10: =S2_Files!A11&" - "&S2_Files!B11 -> HS-G - Governance & Family | B10: =S3_Questions!A11&" - "&S3_Questions!B11 -> CH1-G - Có một điều khoản đặc biệt nào giữa Michael và nhà đầu tư bên ngoài không? | C10: =S5_FinalQ!A11&" - "&S5_FinalQ!B11 -> CH2-G - Nếu EBITDA giảm thêm 5%, điều gì xảy ra ngay lập tức? | G10: =S9_Stakeholders!A11&" - "&S9_Stakeholders!B11 -> GR-7 - Governance & Family

Sheet S2_Files
A1: Screen 2 — Hồ sơ chẩn đoán (chọn đúng 3 trong 7; 4 hồ sơ còn lại đóng vĩnh viễn)
A2: Points = giá trị thông tin khi mở đầy đủ (best 3 = HS-D + HS-G + HS-C = 40).
A4: ID | B4: Option (player sees) | C4: What it reveals | D4: Category | E4: Full-file pts | F4: Design note
A5: HS-A | B5: Sales & Customer | C5: SSS consolidated −1.4% (Domestic −1.3%, Intl −1.6%); Net sales $11.802bn → $11.540bn (−2.2%); e-commerce +11%. | D5: Supporting | E5: 8 | F5: Traffic yếu nhưng không phải kênh nào cũng giảm.
A6: HS-B | B6: Stores & Investment | C6: 6 chương trình đang tranh vốn hữu hạn: renovation, mobile & web, omnichannel, supply chain, customer experience, holiday inventory. | D6: Supporting | E6: 6 | F6: Áp lực CapEx dồn nén.
A7: HS-C | B7: Liquidity | C7: Cash $566m; Receivables $255m; Inventory $2.476bn; Current assets $3.389bn; PP&E $3.067bn. Cash cuối kỳ không phản ánh toàn bộ liquidity. | D7: Core | E7: 10 | F7: Thanh khoản / covenant.
A8: HS-D | B8: Capital Structure & Leverage History | C8: Total debt ~$4.8bn (secured ~$3.4bn); LBO 2015 $6.6bn; OCF trước 2015: $575m / $801m / $746m. 'Leverage cao nhưng đã tồn tại nhiều năm'. | D8: Core (gốc rễ) | E8: 15 | F8: Historical Financing Event — 2015.
A9: HS-E | B9: Product & Category Trends | C9: Toy ex-entertainment: Domestic +2.5% SSS, Consolidated +1.1%; entertainment/licensing yếu, phụ thuộc lịch phát hành bên ngoài. | D9: Supporting | E9: 5 | F9: Đồ chơi truyền thống vẫn có nhu cầu thật.
A10: HS-F | B10: Management Track Record | C10: 4 sáng kiến 3 năm qua: renovation pilot, cắt SG&A vòng 1, digital & app, tái cấu trúc một phần nợ quốc tế — mỗi thứ chỉ xử lý một phần. | D10: Supporting | E10: 7 | F10: Chưa sáng kiến nào đủ lớn.
A11: HS-G | B11: Governance & Family | C11: Cổ phần Anderson 78%; thỏa thuận Michael–Houndstooth (quyền mua ưu tiên nếu Adj. EBITDA giảm thêm 5%); Richard chào bán tài sản quốc tế; thư luật sư của Michael. | D11: Core (bí mật nền) | E11: 15 | F11: Chỉ HS-G xác nhận đầy đủ bí mật nền.

Sheet S3_Questions
A1: Screen 3 — Câu hỏi bổ sung (chọn đúng 2 trong 7)
A2: Points = giá trị BỀ MẶT nếu khu vực CHƯA mở hồ sơ đầy đủ. Nếu khu vực đã mở hồ sơ, câu hỏi chỉ củng cố chi tiết nhỏ (=1, xem M1 và Config).
A4: ID | B4: Option (player sees) | C4: What it reveals | D4: Area | E4: Surface pts | F4: Design note
A5: CH1-A | B5: Traffic giảm, e-commerce tăng — khách rời bỏ hay đổi kênh? | C5: Phần lớn đổi kênh; biên online thấp hơn store. Tin đồn tái cấu trúc gia đình khiến một phần khách chuyển sang đối thủ. | D5: Khu vực HS-A | E5: 3 | F5: Bề mặt của HS-A.
A6: CH1-B | B6: Chương trình vốn nào bị trì hoãn lâu nhất? | C6: Store renovation — gác 3 năm liên tiếp; Richard nhiều lần bỏ phiếu trì hoãn vì đang đàm phán bán tài sản riêng. | D6: Khu vực HS-B | E6: 2 | F6: Bề mặt của HS-B.
A7: CH1-C | B7: Holiday kém 10% thì thanh khoản ra sao? | C7: Vẫn đủ cash hoạt động, nhưng biên an toàn covenant mỏng đi đáng kể. | D7: Khu vực HS-C | E7: 4 | F7: Bề mặt của HS-C.
A8: CH1-D | B8: Khoản nợ nào đến hạn sớm nhất? | C8: Một phần secured notes đáo hạn trong 18 tháng; EBITDA trigger của Houndstooth có thể phát sinh sớm hơn. | D8: Khu vực HS-D | E8: 6 | F8: Bề mặt của HS-D (hé lộ Houndstooth).
A9: CH1-E | B9: Nhóm sản phẩm nào đang hoạt động tốt nhất? | C9: Đồ chơi truyền thống nhưng quy mô nhỏ; Richard đang âm thầm rao bán mảng này. | D9: Khu vực HS-E | E9: 2 | F9: Bề mặt của HS-E.
A10: CH1-F | B10: Ban lãnh đạo có đồng thuận không? | C10: Không — Michael đã mời riêng luật sư chuyên 'chuyển giao quyền lực'. | D10: Khu vực HS-F/G | E10: 3 | F10: Bề mặt của HS-F.
A11: CH1-G | B11: Có một điều khoản đặc biệt nào giữa Michael và nhà đầu tư bên ngoài không? | C11: Có một thỏa thuận có điều kiện có thể ảnh hưởng đến quyền sở hữu của gia đình, nhưng chi tiết cụ thể (điều kiện kích hoạt, đối tác) chưa rõ — cần xem hồ sơ đầy đủ. | D11: Khu vực HS-G | E11: 3 | F11: Bề mặt của HS-G — ĐÃ GIẢM 6→3đ và bớt chi tiết (bản sửa USER_FLOW) để việc mở HS-G vẫn có giá trị.

Sheet S5_FinalQ
A1: Screen 5 — Câu hỏi cuối (chọn đúng 1 trong 7)
A2: Points = điểm phản tư cơ bản; cộng thêm điểm từ M2 nếu hồ sơ liên quan đã mở; tổng bị chặn ở Config (fq_cap).
A4: ID | B4: Option (player sees) | C4: What it reveals | D4: Category | E4: Base pts | F4: Design note
A5: CH2-A | B5: Khoản nào khó cắt nhất? | C5: Nghĩa vụ tài chính có thể refinance nhưng không biến mất; Michael thúc cắt marketing mạnh hơn CFO khuyến nghị. | D5: Phản tư | E5: 3 | F5: Nghiêng về chi phí/nợ.
A6: CH2-B | B6: Có thêm vốn thì dùng vào đâu? | C6: Digital, fulfillment, renovation. Nếu Houndstooth thắng, phần lớn đầu tư này dừng ngay. | D6: Phản tư | E6: 3 | F6: Nghiêng về đầu tư cạnh tranh.
A7: CH2-C | B7: Sao không đóng mạnh cửa hàng? | C7: Một số nên đóng nhưng cắt sâu làm nhỏ sales base; nhiều hợp đồng thuê do Richard đứng tên cá nhân. | D7: Phản tư | E7: 3 | F7: Nghiêng về mạng lưới cửa hàng.
A8: CH2-D | B8: Amazon biến mất thì công ty khỏe chưa? | C8: Không — áp lực nội bộ (gia đình, nợ) vẫn còn nguyên. | D8: Phản tư | E8: 2 | F8: Loại giả thuyết cạnh tranh.
A9: CH2-E | B9: Nếu loại bỏ được phần lớn áp lực nợ, đã giải quyết toàn bộ vấn đề chưa? | C9: Không — vẫn phải xử lý store base và cạnh tranh; hết nợ thì Michael/Richard chuyển sang đấu tố quyền kiểm soát. | D9: Phản tư | E9: 4 | F9: Nghiêng về giả thuyết hỗn hợp.
A10: CH2-F | B10: Lo nhất điều gì trong 12 tháng tới? | C10: Liquidity & refinancing. David: Michael sẽ dùng khoản lỗ để thuyết phục cổ đông nhỏ lẻ rằng tôi hết năng lực. | D10: Phản tư | E10: 4 | F10: Thanh khoản + quản trị.
A11: CH2-G | B11: Nếu EBITDA giảm thêm 5%, điều gì xảy ra ngay lập tức? | C11: Điều khoản Houndstooth kích hoạt tự động — không cần họp hội đồng (đầy đủ nếu đã mở HS-G). | D11: Phản tư | E11: 4 | F11: Giá trị cao nhất khi đã mở HS-G.

Sheet M1_File_x_Q
A1: Matrix M1 — Hồ sơ (Màn 2) × Câu hỏi bổ sung (Màn 3): giá trị thông tin tăng thêm
A2: Cùng khu vực (HS-X × CH1-X) = chỉ củng cố chi tiết nhỏ (=1). Khác khu vực = điểm bề mặt của câu hỏi (S3). Với mỗi câu hỏi, hệ thống lấy MIN qua 3 hồ sơ đã mở → nếu khu vực đã mở thì chỉ còn =1.
A4: Hồ sơ ↓ / Câu hỏi → | C4: Traffic giảm, e-commerce tăng — khách rời bỏ hay đổi kê | D4: Chương trình vốn nào bị trì hoãn lâu nhất? | E4: Holiday kém 10% thì thanh khoản ra sao? | F4: Khoản nợ nào đến hạn sớm nhất? | G4: Nhóm sản phẩm nào đang hoạt động tốt nhất? | H4: Ban lãnh đạo có đồng thuận không? | I4: Có một điều khoản đặc biệt nào giữa Michael và nhà đầu
A5: ID | B5: Option | C5: CH1-A | D5: CH1-B | E5: CH1-C | F5: CH1-D | G5: CH1-E | H5: CH1-F | I5: CH1-G
A6: HS-A | B6: Sales & Customer | C6: =IF(RIGHT($A6,1)=RIGHT(C$5,1),Config!$B$5,INDEX(S3_Questions!$E$5:$E$11,MATCH(C$5,S3_Questions!$A$5:$A$11,0))) -> 1 | D6: =IF(RIGHT($A6,1)=RIGHT(D$5,1),Config!$B$5,INDEX(S3_Questions!$E$5:$E$11,MATCH(D$5,S3_Questions!$A$5:$A$11,0))) -> 2 | E6: =IF(RIGHT($A6,1)=RIGHT(E$5,1),Config!$B$5,INDEX(S3_Questions!$E$5:$E$11,MATCH(E$5,S3_Questions!$A$5:$A$11,0))) -> 4 | F6: =IF(RIGHT($A6,1)=RIGHT(F$5,1),Config!$B$5,INDEX(S3_Questions!$E$5:$E$11,MATCH(F$5,S3_Questions!$A$5:$A$11,0))) -> 6 | G6: =IF(RIGHT($A6,1)=RIGHT(G$5,1),Config!$B$5,INDEX(S3_Questions!$E$5:$E$11,MATCH(G$5,S3_Questions!$A$5:$A$11,0))) -> 2 | H6: =IF(RIGHT($A6,1)=RIGHT(H$5,1),Config!$B$5,INDEX(S3_Questions!$E$5:$E$11,MATCH(H$5,S3_Questions!$A$5:$A$11,0))) -> 3 | I6: =IF(RIGHT($A6,1)=RIGHT(I$5,1),Config!$B$5,INDEX(S3_Questions!$E$5:$E$11,MATCH(I$5,S3_Questions!$A$5:$A$11,0))) -> 3
A7: HS-B | B7: Stores & Investment | C7: =IF(RIGHT($A7,1)=RIGHT(C$5,1),Config!$B$5,INDEX(S3_Questions!$E$5:$E$11,MATCH(C$5,S3_Questions!$A$5:$A$11,0))) -> 3 | D7: =IF(RIGHT($A7,1)=RIGHT(D$5,1),Config!$B$5,INDEX(S3_Questions!$E$5:$E$11,MATCH(D$5,S3_Questions!$A$5:$A$11,0))) -> 1 | E7: =IF(RIGHT($A7,1)=RIGHT(E$5,1),Config!$B$5,INDEX(S3_Questions!$E$5:$E$11,MATCH(E$5,S3_Questions!$A$5:$A$11,0))) -> 4 | F7: =IF(RIGHT($A7,1)=RIGHT(F$5,1),Config!$B$5,INDEX(S3_Questions!$E$5:$E$11,MATCH(F$5,S3_Questions!$A$5:$A$11,0))) -> 6 | G7: =IF(RIGHT($A7,1)=RIGHT(G$5,1),Config!$B$5,INDEX(S3_Questions!$E$5:$E$11,MATCH(G$5,S3_Questions!$A$5:$A$11,0))) -> 2 | H7: =IF(RIGHT($A7,1)=RIGHT(H$5,1),Config!$B$5,INDEX(S3_Questions!$E$5:$E$11,MATCH(H$5,S3_Questions!$A$5:$A$11,0))) -> 3 | I7: =IF(RIGHT($A7,1)=RIGHT(I$5,1),Config!$B$5,INDEX(S3_Questions!$E$5:$E$11,MATCH(I$5,S3_Questions!$A$5:$A$11,0))) -> 3
A8: HS-C | B8: Liquidity | C8: =IF(RIGHT($A8,1)=RIGHT(C$5,1),Config!$B$5,INDEX(S3_Questions!$E$5:$E$11,MATCH(C$5,S3_Questions!$A$5:$A$11,0))) -> 3 | D8: =IF(RIGHT($A8,1)=RIGHT(D$5,1),Config!$B$5,INDEX(S3_Questions!$E$5:$E$11,MATCH(D$5,S3_Questions!$A$5:$A$11,0))) -> 2 | E8: =IF(RIGHT($A8,1)=RIGHT(E$5,1),Config!$B$5,INDEX(S3_Questions!$E$5:$E$11,MATCH(E$5,S3_Questions!$A$5:$A$11,0))) -> 1 | F8: =IF(RIGHT($A8,1)=RIGHT(F$5,1),Config!$B$5,INDEX(S3_Questions!$E$5:$E$11,MATCH(F$5,S3_Questions!$A$5:$A$11,0))) -> 6 | G8: =IF(RIGHT($A8,1)=RIGHT(G$5,1),Config!$B$5,INDEX(S3_Questions!$E$5:$E$11,MATCH(G$5,S3_Questions!$A$5:$A$11,0))) -> 2 | H8: =IF(RIGHT($A8,1)=RIGHT(H$5,1),Config!$B$5,INDEX(S3_Questions!$E$5:$E$11,MATCH(H$5,S3_Questions!$A$5:$A$11,0))) -> 3 | I8: =IF(RIGHT($A8,1)=RIGHT(I$5,1),Config!$B$5,INDEX(S3_Questions!$E$5:$E$11,MATCH(I$5,S3_Questions!$A$5:$A$11,0))) -> 3
A9: HS-D | B9: Capital Structure & Leverage History | C9: =IF(RIGHT($A9,1)=RIGHT(C$5,1),Config!$B$5,INDEX(S3_Questions!$E$5:$E$11,MATCH(C$5,S3_Questions!$A$5:$A$11,0))) -> 3 | D9: =IF(RIGHT($A9,1)=RIGHT(D$5,1),Config!$B$5,INDEX(S3_Questions!$E$5:$E$11,MATCH(D$5,S3_Questions!$A$5:$A$11,0))) -> 2 | E9: =IF(RIGHT($A9,1)=RIGHT(E$5,1),Config!$B$5,INDEX(S3_Questions!$E$5:$E$11,MATCH(E$5,S3_Questions!$A$5:$A$11,0))) -> 4 | F9: =IF(RIGHT($A9,1)=RIGHT(F$5,1),Config!$B$5,INDEX(S3_Questions!$E$5:$E$11,MATCH(F$5,S3_Questions!$A$5:$A$11,0))) -> 1 | G9: =IF(RIGHT($A9,1)=RIGHT(G$5,1),Config!$B$5,INDEX(S3_Questions!$E$5:$E$11,MATCH(G$5,S3_Questions!$A$5:$A$11,0))) -> 2 | H9: =IF(RIGHT($A9,1)=RIGHT(H$5,1),Config!$B$5,INDEX(S3_Questions!$E$5:$E$11,MATCH(H$5,S3_Questions!$A$5:$A$11,0))) -> 3 | I9: =IF(RIGHT($A9,1)=RIGHT(I$5,1),Config!$B$5,INDEX(S3_Questions!$E$5:$E$11,MATCH(I$5,S3_Questions!$A$5:$A$11,0))) -> 3
A10: HS-E | B10: Product & Category Trends | C10: =IF(RIGHT($A10,1)=RIGHT(C$5,1),Config!$B$5,INDEX(S3_Questions!$E$5:$E$11,MATCH(C$5,S3_Questions!$A$5:$A$11,0))) -> 3 | D10: =IF(RIGHT($A10,1)=RIGHT(D$5,1),Config!$B$5,INDEX(S3_Questions!$E$5:$E$11,MATCH(D$5,S3_Questions!$A$5:$A$11,0))) -> 2 | E10: =IF(RIGHT($A10,1)=RIGHT(E$5,1),Config!$B$5,INDEX(S3_Questions!$E$5:$E$11,MATCH(E$5,S3_Questions!$A$5:$A$11,0))) -> 4 | F10: =IF(RIGHT($A10,1)=RIGHT(F$5,1),Config!$B$5,INDEX(S3_Questions!$E$5:$E$11,MATCH(F$5,S3_Questions!$A$5:$A$11,0))) -> 6 | G10: =IF(RIGHT($A10,1)=RIGHT(G$5,1),Config!$B$5,INDEX(S3_Questions!$E$5:$E$11,MATCH(G$5,S3_Questions!$A$5:$A$11,0))) -> 1 | H10: =IF(RIGHT($A10,1)=RIGHT(H$5,1),Config!$B$5,INDEX(S3_Questions!$E$5:$E$11,MATCH(H$5,S3_Questions!$A$5:$A$11,0))) -> 3 | I10: =IF(RIGHT($A10,1)=RIGHT(I$5,1),Config!$B$5,INDEX(S3_Questions!$E$5:$E$11,MATCH(I$5,S3_Questions!$A$5:$A$11,0))) -> 3
A11: HS-F | B11: Management Track Record | C11: =IF(RIGHT($A11,1)=RIGHT(C$5,1),Config!$B$5,INDEX(S3_Questions!$E$5:$E$11,MATCH(C$5,S3_Questions!$A$5:$A$11,0))) -> 3 | D11: =IF(RIGHT($A11,1)=RIGHT(D$5,1),Config!$B$5,INDEX(S3_Questions!$E$5:$E$11,MATCH(D$5,S3_Questions!$A$5:$A$11,0))) -> 2 | E11: =IF(RIGHT($A11,1)=RIGHT(E$5,1),Config!$B$5,INDEX(S3_Questions!$E$5:$E$11,MATCH(E$5,S3_Questions!$A$5:$A$11,0))) -> 4 | F11: =IF(RIGHT($A11,1)=RIGHT(F$5,1),Config!$B$5,INDEX(S3_Questions!$E$5:$E$11,MATCH(F$5,S3_Questions!$A$5:$A$11,0))) -> 6 | G11: =IF(RIGHT($A11,1)=RIGHT(G$5,1),Config!$B$5,INDEX(S3_Questions!$E$5:$E$11,MATCH(G$5,S3_Questions!$A$5:$A$11,0))) -> 2 | H11: =IF(RIGHT($A11,1)=RIGHT(H$5,1),Config!$B$5,INDEX(S3_Questions!$E$5:$E$11,MATCH(H$5,S3_Questions!$A$5:$A$11,0))) -> 1 | I11: =IF(RIGHT($A11,1)=RIGHT(I$5,1),Config!$B$5,INDEX(S3_Questions!$E$5:$E$11,MATCH(I$5,S3_Questions!$A$5:$A$11,0))) -> 3
A12: HS-G | B12: Governance & Family | C12: =IF(RIGHT($A12,1)=RIGHT(C$5,1),Config!$B$5,INDEX(S3_Questions!$E$5:$E$11,MATCH(C$5,S3_Questions!$A$5:$A$11,0))) -> 3 | D12: =IF(RIGHT($A12,1)=RIGHT(D$5,1),Config!$B$5,INDEX(S3_Questions!$E$5:$E$11,MATCH(D$5,S3_Questions!$A$5:$A$11,0))) -> 2 | E12: =IF(RIGHT($A12,1)=RIGHT(E$5,1),Config!$B$5,INDEX(S3_Questions!$E$5:$E$11,MATCH(E$5,S3_Questions!$A$5:$A$11,0))) -> 4 | F12: =IF(RIGHT($A12,1)=RIGHT(F$5,1),Config!$B$5,INDEX(S3_Questions!$E$5:$E$11,MATCH(F$5,S3_Questions!$A$5:$A$11,0))) -> 6 | G12: =IF(RIGHT($A12,1)=RIGHT(G$5,1),Config!$B$5,INDEX(S3_Questions!$E$5:$E$11,MATCH(G$5,S3_Questions!$A$5:$A$11,0))) -> 2 | H12: =IF(RIGHT($A12,1)=RIGHT(H$5,1),Config!$B$5,INDEX(S3_Questions!$E$5:$E$11,MATCH(H$5,S3_Questions!$A$5:$A$11,0))) -> 3 | I12: =IF(RIGHT($A12,1)=RIGHT(I$5,1),Config!$B$5,INDEX(S3_Questions!$E$5:$E$11,MATCH(I$5,S3_Questions!$A$5:$A$11,0))) -> 1

Sheet M2_File_x_FQ
A1: Matrix M2 — Hồ sơ (Màn 2) × Câu hỏi cuối (Màn 5): điểm thông tin thêm khi có hồ sơ liên quan
A2: Câu hỏi cuối mang tính phản tư: hiểu đầy đủ hơn khi đã mở hồ sơ liên quan (vd CH2-G cần HS-G). Cộng 3 hồ sơ đã mở + điểm cơ bản, tối đa fq_cap (Config).
A4: Hồ sơ ↓ / Câu hỏi cuối → | C4: Khoản nào khó cắt nhất? | D4: Có thêm vốn thì dùng vào đâu? | E4: Sao không đóng mạnh cửa hàng? | F4: Amazon biến mất thì công ty khỏe chưa? | G4: Nếu loại bỏ được phần lớn áp lực nợ, đã giải quyết toàn | H4: Lo nhất điều gì trong 12 tháng tới? | I4: Nếu EBITDA giảm thêm 5%, điều gì xảy ra ngay lập tức?
A5: ID | B5: Option | C5: CH2-A | D5: CH2-B | E5: CH2-C | F5: CH2-D | G5: CH2-E | H5: CH2-F | I5: CH2-G
A6: HS-A | B6: Sales & Customer | C6: 0 | D6: 2 | E6: 2 | F6: 5 | G6: 2 | H6: 0 | I6: 0
A7: HS-B | B7: Stores & Investment | C7: 0 | D7: 5 | E7: 5 | F7: 0 | G7: 3 | H7: 0 | I7: 0
A8: HS-C | B8: Liquidity | C8: 0 | D8: 2 | E8: 0 | F8: 0 | G8: 0 | H8: 5 | I8: 3
A9: HS-D | B9: Capital Structure & Leverage History | C9: 5 | D9: 0 | E9: 0 | F9: 3 | G9: 6 | H9: 5 | I9: 4
A10: HS-E | B10: Product & Category Trends | C10: 0 | D10: 0 | E10: 0 | F10: 3 | G10: 0 | H10: 0 | I10: 0
A11: HS-F | B11: Management Track Record | C11: 3 | D11: 0 | E11: 0 | F11: 0 | G11: 0 | H11: 0 | I11: 0
A12: HS-G | B12: Governance & Family | C12: 2 | D12: 4 | E12: 4 | F12: 3 | G12: 5 | H12: 4 | I12: 10

Sheet S6_Diagnosis
A1: Screen 6 — Chẩn đoán (chọn đúng 1 trong 6)
A2: 6 tên gọi thể hiện 6 TẦNG khác nhau của cùng một vấn đề (từ bề mặt đến cấu trúc), KHÔNG phải một đáp án đúng/sai — người chơi không bị game ngầm coi là "chọn sai" dù chọn tầng nào. "Nguyên nhân Cấu trúc" (CD-D) nằm ở tầng sâu nhất và có bằng chứng bao trùm nhất trong thiết kế điểm (dùng làm mốc chấm Treatment), nhưng vẫn là 1 trong 6 lựa chọn hợp lệ ngang hàng. Primary pts (tối đa 60) = độ khớp với mốc đó. Evidence support (tối đa 40) lấy từ M3.
A4: ID | B4: Chẩn đoán | C4: Bản chất (chấm điểm) | D4: Bằng chứng ủng hộ mạnh nhất | E4: Primary pts | F4: Điều kiện / hệ quả Uy tín
A5: CD-A | B5: Áp lực Cạnh tranh (Competitive Pressure) | C5: Tầng bề mặt — triệu chứng | D5: HS-A, CH1-A: SSS −1.4% nhưng e-com +11% — đổi kênh, không sụp cầu | E5: 25 | F5: Không có điều kiện
A6: CD-B | B6: Nút thắt Vận hành (Operational Bottleneck) | C6: Tầng bề mặt — triệu chứng | D6: HS-B, CH1-B: CapEx dồn nén nhiều năm | E6: 25 | F6: Không có điều kiện
A7: CD-C | B7: Biểu hiện Thanh khoản tức thời (Liquidity Manifestation) | C7: Tầng biểu hiện — hệ quả của CD-D | D7: HS-C, CH1-C: biên an toàn covenant mỏng | E7: 40 | F7: Không có điều kiện
A8: CD-D | B8: Nguyên nhân Cấu trúc (Structural Driver) | C8: Tầng sâu nhất — trọng tâm thiết kế điểm | D8: HS-D, CH1-D: nợ ~$4.8bn, lãi $457m ≈ Operating Earnings $460m; LBO 2015 | E8: 60 | F8: Không có điều kiện
A9: CD-E | B9: Áp lực Danh mục Sản phẩm (Category Pressure) | C9: Tầng bề mặt — triệu chứng | D9: HS-E, CH1-E: category truyền thống co lại | E9: 20 | F9: Không có điều kiện
A10: CD-F | B10: Chẩn đoán Đa yếu tố (Multi-Factor Diagnosis) | C10: Phạm vi rộng nhất — hợp lệ khi đủ bằng chứng | D10: Cần HS-D + ≥1 trong (HS-A/B/E/F) | E10: 55 | F10: Thiếu điều kiện: Uy tín −1 và điểm chẩn đoán × hệ số phạt (Config)

Sheet M3_Dx_x_File
A1: Matrix M3 — Chẩn đoán (Màn 6) × Hồ sơ (Màn 2): bằng chứng ủng hộ
A2: Hồ sơ mở đầy đủ cộng đủ điểm; câu hỏi CH1-X cộng 50% điểm của khu vực X. Tổng chặn ở dxsup_cap (Config).
A4: Chẩn đoán ↓ / Hồ sơ → | C4: Sales & Customer | D4: Stores & Investment | E4: Liquidity | F4: Capital Structure & Leverage History | G4: Product & Category Trends | H4: Management Track Record | I4: Governance & Family
A5: ID | B5: Option | C5: HS-A | D5: HS-B | E5: HS-C | F5: HS-D | G5: HS-E | H5: HS-F | I5: HS-G
A6: CD-A | B6: Áp lực Cạnh tranh (Competitive Pressure) | C6: 25 | D6: 4 | E6: 0 | F6: 2 | G6: 8 | H6: 6 | I6: 0
A7: CD-B | B7: Nút thắt Vận hành (Operational Bottleneck) | C7: 5 | D7: 25 | E7: 3 | F7: 0 | G7: 0 | H7: 8 | I7: 3
A8: CD-C | B8: Biểu hiện Thanh khoản tức thời (Liquidity Manifestation) | C8: 0 | D8: 4 | E8: 25 | F8: 10 | G8: 0 | H8: 3 | I8: 0
A9: CD-D | B9: Nguyên nhân Cấu trúc (Structural Driver) | C9: 2 | D9: 0 | E9: 10 | F9: 25 | G9: 0 | H9: 8 | I9: 6
A10: CD-E | B10: Áp lực Danh mục Sản phẩm (Category Pressure) | C10: 6 | D10: 0 | E10: 0 | F10: 0 | G10: 25 | H10: 3 | I10: 2
A11: CD-F | B11: Chẩn đoán Đa yếu tố (Multi-Factor Diagnosis) | C11: 6 | D11: 6 | E11: 6 | F11: 15 | G11: 6 | H11: 8 | I11: 10

Sheet S7_Treatment
A1: Screen 7 — Phác đồ (chọn đúng 1 trong 6)
A2: Điểm phù hợp theo chẩn đoán ở M4. Điểm Tài chính theo M7/M8/M9 (sheet S10). Điều kiện Uy tín áp dụng trước khi tính.
A4: ID | B4: Phác đồ | C4: Nội dung | D4: Điều kiện | E4: Đánh đổi / rủi ro | F4: Diễn biến điển hình (Màn 10)
A5: PD-A | B5: Invest to Compete | C5: Đầu tư renovation/digital/omnichannel để cạnh tranh. | D5: Cần Uy tín ≥ Trung bình; nếu không → tự động hạ xuống PD-B — hệ thống hiển thị: "Hội đồng chưa đủ tin tưởng để duyệt kế hoạch đầu tư — bạn buộc phải triển khai phương án cắt giảm chi phí." | E5: Tốn cash khi thanh khoản đã mỏng. | F5: Nếu bị hạ: board tự hạ kế hoạch xuống PD-B tối thiểu.
A6: PD-B | B6: Deep Cost Cutting | C6: Cắt chi phí sâu, đóng cửa hàng yếu. | D6: Không cần điều kiện. | E6: Cash ngắn hạn tốt lên nhưng thu nhỏ sales base dài hạn. | F6: PD-B + TG-A + không ưu tiên Employees → đóng thêm cửa hàng ngoài kế hoạch.
A7: PD-C | B7: Debt Restructuring | C7: Đàm phán gia hạn/tái cấu trúc nợ với chủ nợ. | D7: Phụ thuộc phản ứng chủ nợ; ưu tiên Creditors ở Màn 9 giúp đạt thỏa thuận tốt hơn. | E7: Có thể tăng lãi suất. | F7: PD-C + Creditors → chủ nợ gia hạn nhưng lãi +1.0–1.5%.
A8: PD-D | B8: Asset Sale | C8: Bán tài sản để lấy thanh khoản. | D8: Thường phải bán phần tài sản khỏe nhất (đồ chơi truyền thống). | E8: Mất phần lõi khỏe; −1 Quản trị nếu chưa mở HS-E. | F8: Thanh khoản cải thiện ngay; Richard hưởng lợi.
A9: PD-E | B9: Bankruptcy Restructuring | C9: Chapter 11 — xử lý nợ triệt để; vô hiệu hóa thỏa thuận Michael–Houndstooth chưa kích hoạt. | D9: Ưu tiên Suppliers để giảm sốc vendor. | E9: Rủi ro mất niềm tin vendor/khách hàng cao nhất. | F9: PD-E không ưu tiên Suppliers → vendor đòi cash-in-advance.
A10: PD-F | B10: Combined Restructuring | C10: Kết hợp nhiều mảng chạy song song. | D10: Cần Uy tín Cao; nếu không → hạ xuống PD-B — hệ thống hiển thị: "Hội đồng chưa đủ tin tưởng để duyệt một kế hoạch tái cấu trúc nhiều mặt trận cùng lúc — bạn buộc phải thu hẹp lại thành cắt giảm chi phí." | E10: Rủi ro thực thi cao nhất. | F10: Nếu đủ Uy tín: kết quả tài chính tốt nhất (+4).

Sheet M4_Dx_x_Tx
A1: Matrix M4 — Chẩn đoán (Màn 6) × Phác đồ (Màn 7): độ phù hợp 0–100
A2: Treatment score = 60% × độ phù hợp với NGUYÊN NHÂN GỐC (CD-D) + 40% × độ phù hợp với chẩn đoán của người chơi. Dùng phác đồ HIỆU LỰC (sau kiểm tra Uy tín).
A4: Chẩn đoán ↓ / Phác đồ → | C4: Invest to Compete | D4: Deep Cost Cutting | E4: Debt Restructuring | F4: Asset Sale | G4: Bankruptcy Restructuring | H4: Combined Restructuring
A5: ID | B5: Option | C5: PD-A | D5: PD-B | E5: PD-C | F5: PD-D | G5: PD-E | H5: PD-F
A6: CD-A | B6: Áp lực Cạnh tranh (Competitive Pressure) | C6: 90 | D6: 35 | E6: 30 | F6: 25 | G6: 20 | H6: 60
A7: CD-B | B7: Nút thắt Vận hành (Operational Bottleneck) | C7: 85 | D7: 40 | E7: 30 | F7: 40 | G7: 20 | H7: 60
A8: CD-C | B8: Biểu hiện Thanh khoản tức thời (Liquidity Manifestation) | C8: 30 | D8: 65 | E8: 80 | F8: 85 | G8: 50 | H8: 65
A9: CD-D | B9: Nguyên nhân Cấu trúc (Structural Driver) | C9: 20 | D9: 40 | E9: 85 | F9: 55 | G9: 80 | H9: 90
A10: CD-E | B10: Áp lực Danh mục Sản phẩm (Category Pressure) | C10: 55 | D10: 35 | E10: 30 | F10: 20 | G10: 25 | H10: 50
A11: CD-F | B11: Chẩn đoán Đa yếu tố (Multi-Factor Diagnosis) | C11: 45 | D11: 40 | E11: 65 | F11: 55 | G11: 70 | H11: 90

Sheet S8_Timing
A1: Screen 8 — Thời điểm & Trình tự hành động (chọn đúng 1 trong 4)
A2: TG-C không phải một mốc thời gian như 3 lựa chọn còn lại, mà là một hành động "thử trước khi cam kết". Không có lựa chọn trung lập. Điểm thực thi ở M5.
A4: ID | B4: Thời điểm | C4: Khung | D4: Cơ hội | E4: Rủi ro
A5: TG-A | B5: Thực hiện ngay | C5: 0–30 ngày | D5: Hành động sớm khi vendor/lender còn linh hoạt. | E5: Dữ liệu holiday chưa đầy đủ; Michael có cớ đòi họp cổ đông sớm để bác kế hoạch.
A6: TG-B | B6: Sau holiday season | C6: Sau mùa cao điểm | D6: Có dữ liệu thật. | E6: Nếu holiday kém, thanh khoản xấu đi trước khi kịp hành động.
A7: TG-C | B7: Thử tái cấp vốn trước khi cam kết kế hoạch | C7: Thử trước khi cam kết | D7: Thành công → vị thế mạnh hơn hẳn. | E7: Thất bại → thị trường đọc là tín hiệu yếu; Uy tín −1.
A8: TG-D | B8: Chờ 6 tháng | C8: 6 tháng | D8: Có thêm thời gian quan sát. | E8: Rủi ro cao nhất nếu thanh khoản mỏng — có thể hết runway. Tài chính −1.

Sheet M5_Tx_x_Timing
A1: Matrix M5 — Phác đồ (Màn 7) × Thời điểm (Màn 8): điểm thực thi 0–100
A2: Chiếm 50% điểm Execution Planning.
A4: Phác đồ ↓ / Thời điểm → | C4: Thực hiện ngay | D4: Sau holiday season | E4: Thử tái cấp vốn trước khi cam kết kế hoạch | F4: Chờ 6 tháng
A5: ID | B5: Option | C5: TG-A | D5: TG-B | E5: TG-C | F5: TG-D
A6: PD-A | B6: Invest to Compete | C6: 55 | D6: 85 | E6: 60 | F6: 30
A7: PD-B | B7: Deep Cost Cutting | C7: 80 | D7: 60 | E7: 50 | F7: 25
A8: PD-C | B8: Debt Restructuring | C8: 65 | D8: 60 | E8: 90 | F8: 20
A9: PD-D | B9: Asset Sale | C9: 75 | D9: 55 | E9: 55 | F9: 20
A10: PD-E | B10: Bankruptcy Restructuring | C10: 60 | D10: 85 | E10: 35 | F10: 10
A11: PD-F | B11: Combined Restructuring | C11: 60 | D11: 80 | E11: 70 | F11: 20

Sheet S9_Stakeholders
A1: Screen 9 — Nhóm ưu tiên (chọn đúng 3 trong 7)
A2: Cột D/E = điểm Ổn định Quản trị nếu nhóm được / không được ưu tiên (Governance & Family: +2 / −1). Điểm Tài chính theo nhóm ở M8/M9 (S10). Mã GR-x do file này đặt vì case gốc chỉ có tên nhóm.
A4: ID | B4: Nhóm | C4: Được ưu tiên nghĩa là… | D4: Δ GS nếu ưu tiên | E4: Δ GS nếu KHÔNG ưu tiên
A5: GR-1 | B5: Suppliers | C5: Đàm phán điều khoản trước khi công bố | D5: 0 | E5: 0
A6: GR-2 | B6: Employees | C6: Trấn an nội bộ, giữ nhân sự chủ chốt | D6: 0 | E6: 0
A7: GR-3 | B7: Customers | C7: Giữ niềm tin mua sắm | D7: 0 | E7: 0
A8: GR-4 | B8: Creditors | C8: Đàm phán sớm điều khoản nợ | D8: 0 | E8: 0
A9: GR-5 | B9: Landlords | C9: Giữ quan hệ thuê mặt bằng | D9: 0 | E9: 0
A10: GR-6 | B10: Holiday Inventory | C10: Đảm bảo hàng hóa mùa cao điểm | D10: 0 | E10: 0
A11: GR-7 | B11: Governance & Family | C11: Giữ ban điều hành ổn định; báo trước cổ đông gia đình nhỏ lẻ | D11: 2 | E11: -1

Sheet M6_Tx_x_Stake
A1: Matrix M6 — Phác đồ (Màn 7) × Nhóm ưu tiên (Màn 9): giá trị ưu tiên
A2: Tổng 3 nhóm đã chọn ÷ top-3 tốt nhất của phác đồ (cột J) × 100 = Stakeholder score (50% Execution).
A4: Phác đồ ↓ / Nhóm → | C4: Suppliers | D4: Employees | E4: Customers | F4: Creditors | G4: Landlords | H4: Holiday Inventory | I4: Governance & Family
A5: ID | B5: Option | C5: GR-1 | D5: GR-2 | E5: GR-3 | F5: GR-4 | G5: GR-5 | H5: GR-6 | I5: GR-7 | J5: Top-3 max
A6: PD-A | B6: Invest to Compete | C6: 15 | D6: 10 | E6: 25 | F6: 15 | G6: 20 | H6: 25 | I6: 15 | J6: =LARGE(C6:I6,1)+LARGE(C6:I6,2)+LARGE(C6:I6,3) -> 70
A7: PD-B | B7: Deep Cost Cutting | C7: 15 | D7: 25 | E7: 10 | F7: 15 | G7: 20 | H7: 5 | I7: 10 | J7: =LARGE(C7:I7,1)+LARGE(C7:I7,2)+LARGE(C7:I7,3) -> 60
A8: PD-C | B8: Debt Restructuring | C8: 15 | D8: 10 | E8: 10 | F8: 30 | G8: 10 | H8: 15 | I8: 25 | J8: =LARGE(C8:I8,1)+LARGE(C8:I8,2)+LARGE(C8:I8,3) -> 70
A9: PD-D | B9: Asset Sale | C9: 10 | D9: 15 | E9: 10 | F9: 20 | G9: 25 | H9: 15 | I9: 25 | J9: =LARGE(C9:I9,1)+LARGE(C9:I9,2)+LARGE(C9:I9,3) -> 70
A10: PD-E | B10: Bankruptcy Restructuring | C10: 30 | D10: 15 | E10: 20 | F10: 25 | G10: 25 | H10: 15 | I10: 15 | J10: =LARGE(C10:I10,1)+LARGE(C10:I10,2)+LARGE(C10:I10,3) -> 80
A11: PD-F | B11: Combined Restructuring | C11: 20 | D11: 15 | E11: 15 | F11: 25 | G11: 15 | H11: 15 | I11: 25 | J11: =LARGE(C11:I11,1)+LARGE(C11:I11,2)+LARGE(C11:I11,3) -> 70

Sheet S10_Consequence
A1: Screen 10–12 — Điểm Sức khỏe Tài chính & Diễn biến (rules từ USER_FLOW gốc)
A2: Điểm Tài chính = M7 (theo PD × TG) + Σ M8/M9 theo từng nhóm được / không được ưu tiên. Dùng phác đồ CUỐI CÙNG hiệu lực. Tier: xem Config.
A3: M7 — Điểm Tài chính cơ bản: Phác đồ × Thời điểm (TG-D = −1)
A4: M7: Phác đồ ↓ / Thời điểm → | C4: Thực hiện ngay | D4: Sau holiday season | E4: Thử tái cấp vốn trước khi cam kết kế hoạch | F4: Chờ 6 tháng
A5: ID | B5: Option | C5: TG-A | D5: TG-B | E5: TG-C | F5: TG-D
A6: PD-A | B6: Invest to Compete | C6: 2 | D6: 2 | E6: 2 | F6: 1
A7: PD-B | B7: Deep Cost Cutting | C7: 3 | D7: 3 | E7: 3 | F7: 2
A8: PD-C | B8: Debt Restructuring | C8: 0 | D8: 0 | E8: 0 | F8: -1
A9: PD-D | B9: Asset Sale | C9: 2 | D9: 2 | E9: 2 | F9: 1
A10: PD-E | B10: Bankruptcy Restructuring | C10: 0 | D10: 0 | E10: 0 | F10: -1
A11: PD-F | B11: Combined Restructuring | C11: 4 | D11: 4 | E11: 4 | F11: 3
A13: M8 — Điểm Tài chính KHI nhóm ĐƯỢC ưu tiên (Phác đồ × Nhóm)
A14: M8: Phác đồ ↓ / Nhóm → | C14: Suppliers | D14: Employees | E14: Customers | F14: Creditors | G14: Landlords | H14: Holiday Inventory | I14: Governance & Family
A15: ID | B15: Option | C15: GR-1 | D15: GR-2 | E15: GR-3 | F15: GR-4 | G15: GR-5 | H15: GR-6 | I15: GR-7
A16: PD-A | B16: Invest to Compete | C16: 0 | D16: 0 | E16: 0 | F16: 0 | G16: 0 | H16: 0 | I16: 0
A17: PD-B | B17: Deep Cost Cutting | C17: 0 | D17: 0 | E17: 0 | F17: 0 | G17: 0 | H17: 0 | I17: 0
A18: PD-C | B18: Debt Restructuring | C18: 0 | D18: 0 | E18: 0 | F18: 2 | G18: 0 | H18: 0 | I18: 0
A19: PD-D | B19: Asset Sale | C19: 0 | D19: 0 | E19: 0 | F19: 0 | G19: 0 | H19: 0 | I19: 0
A20: PD-E | B20: Bankruptcy Restructuring | C20: 1 | D20: 0 | E20: 0 | F20: 0 | G20: 0 | H20: 0 | I20: 0
A21: PD-F | B21: Combined Restructuring | C21: 0 | D21: 0 | E21: 0 | F21: 0 | G21: 0 | H21: 0 | I21: 0
A23: M9 — Điểm Tài chính KHI nhóm KHÔNG được ưu tiên (Phác đồ × Nhóm)
A24: M9: Phác đồ ↓ / Nhóm → | C24: Suppliers | D24: Employees | E24: Customers | F24: Creditors | G24: Landlords | H24: Holiday Inventory | I24: Governance & Family
A25: ID | B25: Option | C25: GR-1 | D25: GR-2 | E25: GR-3 | F25: GR-4 | G25: GR-5 | H25: GR-6 | I25: GR-7
A26: PD-A | B26: Invest to Compete | C26: 0 | D26: 0 | E26: 0 | F26: 0 | G26: 0 | H26: -1 | I26: 0
A27: PD-B | B27: Deep Cost Cutting | C27: 0 | D27: 0 | E27: 0 | F27: 0 | G27: 0 | H27: -1 | I27: 0
A28: PD-C | B28: Debt Restructuring | C28: 0 | D28: 0 | E28: 0 | F28: 0 | G28: 0 | H28: -1 | I28: 0
A29: PD-D | B29: Asset Sale | C29: 0 | D29: 0 | E29: 0 | F29: 0 | G29: 0 | H29: -1 | I29: 0
A30: PD-E | B30: Bankruptcy Restructuring | C30: -2 | D30: 0 | E30: 0 | F30: 0 | G30: 0 | H30: -1 | I30: 0
A31: PD-F | B31: Combined Restructuring | C31: 0 | D31: 0 | E31: 0 | F31: 0 | G31: 0 | H31: -1 | I31: 0
A34: Diễn biến Màn 10 — sự kiện & việc có 'dữ liệu mới' để biện minh cho Tái khám (Màn 11)
A35: ID | B35: Diễn biến (tab) | C35: Điều kiện kích hoạt | D35: Biện minh đổi PHÁC ĐỒ (1/0) | E35: Biện minh đổi CHẨN ĐOÁN (1/0) | G35: Tường thuật
A36: E1 | B36: Store Update: đóng thêm cửa hàng ngoài kế hoạch | C36: PD hiệu lực = PD-B + TG-A + KHÔNG ưu tiên Employees | D36: 1 | E36: 0 | G36: Thiếu nhân sự quản lý nên phải đóng thêm cửa hàng.
A37: E2 | B37: Liquidity Update: board hạ kế hoạch xuống PD-B | C37: Chọn PD-A/PD-F nhưng Uy tín không đủ (Màn 7) | D37: 1 | E37: 0 | G37: Board đã tự hạ kế hoạch xuống mức PD-B tối thiểu.
A38: E3 | B38: Debt Update: chủ nợ gia hạn nhưng tăng lãi 1.0–1.5% | C38: PD-C + ưu tiên Creditors | D38: 0 | E38: 0 | G38: Thỏa thuận đạt được với giá lãi suất cao hơn.
A39: E4 | B39: Family/Board Update: Michael & Richard họp riêng, bỏ phiếu chống David | C39: KHÔNG ưu tiên Governance & Family và chẩn đoán ≠ CD-F | D39: 1 | E39: 1 | G39: Nếu đã mở HS-G: Michael dùng đúng thông tin đã lộ để thuyết phục thêm cổ đông. Bằng chứng mâu thuẫn với chẩn đoán chỉ nhìn thị trường/vận hành.
A40: E5 | B40: Vendor Update: nhà cung cấp đòi cash-in-advance | C40: PD-E + KHÔNG ưu tiên Suppliers | D40: 1 | E40: 0 | G40: Vendor siết điều khoản vì lo ngại phá sản.
A41: E6 | B41: Debt Update: thị trường đọc là tín hiệu yếu | C41: TG-C + KHÔNG ưu tiên Creditors (refinance thử thất bại) | D41: 1 | E41: 0 | G41: Refinance thử thất bại; trái phiếu và điều kiện vay xấu đi.
A42: E7 | B42: Liquidity Update: runway cạn dần | C42: Chọn TG-D (Chờ 6 tháng) | D42: 1 | E42: 0 | G42: Cải thiện vận hành chưa kịp phát huy trước khi hết runway.
A43: E8 | B43: Debt Update: phản bác CD-A | C43: Chọn CD-A, chưa mở HS-D | D43: 0 | E43: 1 | G43: Dù traffic đã ổn định trở lại, lãi vay vẫn ăn gần hết Operating Earnings — vấn đề không chỉ nằm ở sales.
A44: E9 | B44: Liquidity Update: phản bác CD-B | C44: Chọn CD-B, chưa mở HS-C | D44: 0 | E44: 1 | G44: Dù CapEx được cấp đủ, biên an toàn covenant vẫn mỏng — mạng lưới cửa hàng không phải nút thắt duy nhất.
A45: E10 | B45: Debt Update: phản bác CD-C | C45: Chọn CD-C, chưa mở HS-D | D45: 0 | E45: 1 | G45: Refinance chỉ mua thêm thời gian — nếu không xử lý cấu trúc nợ, biên thanh khoản sẽ mỏng trở lại sau vài quý.
A46: E11 | B46: Sales Update: phản bác CD-E | C46: Chọn CD-E, chưa mở HS-D | D46: 0 | E46: 1 | G46: Category truyền thống đã phục hồi nhẹ, nhưng đòn bẩy tài chính vẫn ở mức nguy hiểm.
A47: E12 | B47: Store Update: hệ quả ưu tiên Employees | C47: Ưu tiên Employees ở Màn 9 | D47: 0 | E47: 0 | G47: Nhân sự chủ chốt được giữ lại giúp quá trình đóng cửa hàng diễn ra suôn sẻ hơn, giảm rủi ro đóng cửa ngoài kế hoạch.
... A49: E14 | B49: Store Update: hệ quả ưu tiên Landlords | C49: Ưu tiên Landlords ở Màn 9 | D49: 0 | E49: 0 | G49: Chủ nhà đồng ý gia hạn thêm một số hợp đồng thuê, giảm áp lực phải đóng cửa hàng.

Sheet S11_Reassess
A1: Screen 11 — Tái khám (quyết định × tình huống)
A2: Tình huống: WEAK = chẩn đoán đầu ≠ CD-D và ≠ CD-F; STRONG = chẩn đoán đúng và phác đồ hiệu lực có độ phù hợp ≥ ngưỡng (Config); PARTIAL = còn lại. Reassessment = 70% chọn quyết định + 30% chất lượng phán đoán cuối − phạt mỗi lần đổi thiếu căn cứ.
A4: Quyết định ↓ / Tình huống →
A5: Quyết định | B5: Ý nghĩa | C5: Strong | D5: Partial | E5: Weak
A6: Keep | B6: Giữ nguyên chẩn đoán & phác đồ | C6: 95 | D6: 40 | E6: 15
A7: Revise Diagnosis | B7: Đổi chẩn đoán | C7: 40 | D7: 25 | E7: 70
A8: Revise Treatment | B8: Đổi phác đồ | C8: 55 | D8: 95 | E8: 35
A9: Revise Both | B9: Đổi cả hai | C9: 30 | D9: 60 | E9: 95
A12: Chi phí Uy tín (USER_FLOW gốc): đổi chẩn đoán / đổi phác đồ = −1 Uy tín nếu không dựa trên dữ liệu mới từ Màn 10; 0 nếu có (xem cột biện minh ở S10). Mỗi lần mất Uy tín còn −1 Quản trị.
A13: Validation: nếu chọn 'Revise …' phải điền chẩn đoán / phác đồ mới → 'Complete your revised decision before closing the case.'

Sheet Endings
A1: Màn 12 — Ma trận 3×3 kết cục cuối (Tài chính × Quản trị/Gia tộc)
A2: Hàng = tier Sức khỏe Tài chính; cột = tier Ổn định Quản trị. Uy tín KHÔNG đổi ô, chỉ đổi cách mô tả người chơi (bảng dưới).
A4: Tài chính ↓ / Gia tộc →
A5: Tài chính \ Gia tộc | B5: Gia tộc đoàn kết | C5: Gia tộc chia rẽ, chưa vỡ | D5: Mất kiểm soát
A6: Ổn định tài chính | B6: "Người kế nghiệp" — David giữ ghế, công ty ổn định, gia đình miễn cưỡng hợp tác. | C6: "Hưu chiến có điều kiện" — công ty ổn nhưng David nhượng bớt quyền lực/cổ tức để giữ hòa khí. | D6: "Thắng trận, thua nhà" — công ty khỏe nhưng David bị phế truất hoặc buộc bán rẻ cổ phần cho Houndstooth.
A7: Ổn định mong manh | B7: "Cầm cự cùng nhau" — công ty sống nhưng mỏng manh; gia đình đoàn kết vì cùng chung rủi ro. | C7: "Chia phần trước khi chìm" — công ty nhỏ hơn hẳn; Michael/Richard rút được phần lớn giá trị; David bị ép nhượng bộ. | D7: "Tự ăn thịt mình" — công ty còn tồn tại về kỹ thuật nhưng gia đình tan đàn xẻ nghé, kiện tụng tiêu tốn vốn còn lại.
A8: Sụp đổ tài chính | B8: "Chết trong danh dự" — công ty phá sản/bị tiếp quản nhưng ba anh em cùng chịu trách nhiệm, không đổ lỗi nhau. | C8: "Quân cờ của quỹ" — Houndstooth hoặc chủ nợ tiếp quản; gia đình đấu đá đến phút cuối. | D8: "Sụp đổ toàn diện" — tòa án tiếp quản tài sản, ba anh em kiện nhau ngay trong phiên tòa phá sản.
A11: Vai trò của Uy tín (mô tả người chơi trong ô kết cục)
A12: Uy tín | B12: Mô tả
A13: Cao | B13: Được báo chí và hội đồng mô tả là bác sĩ phẫu thuật lạnh lùng, quyết đoán đúng lúc.
A14: Trung bình | B14: Được ghi nhận là làm việc chắc tay nhưng chưa thuyết phục hoàn toàn. (mô tả đề xuất)
A15: Thấp | B15: Bị coi là may mắn hơn là giỏi; hội đồng vẫn còn nghi ngờ năng lực.

Sheet Feedback
A1: Feedback templates — Result → Reason → Meaning → Action → Limit
A2: Ngưỡng band ở Config (High ≥ 80, Mid ≥ 50). Result sinh từ điểm; 4 trường còn lại là mẫu.
A4: Key | B4: Dimension | C4: Band | D4: Reason | E4: Meaning | F4: Action | G4: Limit
A5: =B5&"|"&C5 -> Investigation|High | B5: Investigation | C5: High | D5: Bạn phủ được các khu vực then chốt (nợ 2015, thanh khoản, quản trị) và dùng câu hỏi bổ sung vào khu vực chưa mở. | E5: Chẩn đoán của bạn dựa trên dữ kiện thay vì suy đoán. | F5: Tiếp tục dùng câu hỏi để thu hẹp khoảng trống thông tin, không lặp lại khu vực đã có hồ sơ. | G5: Chỉ được mở 3/7 hồ sơ nên luôn còn khu vực chưa thấy — đó là thiết kế.
A6: =B6&"|"&C6 -> Investigation|Mid | B6: Investigation | C6: Mid | D6: Bạn có một phần bằng chứng cốt lõi nhưng bỏ sót khu vực quan trọng hoặc lặp câu hỏi ở khu vực đã mở. | E6: Chẩn đoán có thể chỉ được ủng hộ một phần. | F6: Chọn hồ sơ bao phủ nợ/thanh khoản/quản trị; dùng 2 câu hỏi cho khu vực còn trống. | G6: Điểm dựa trên thiết kế case; các đường điều tra khác vẫn có thể hợp lệ.
A7: =B7&"|"&C7 -> Investigation|Low | B7: Investigation | C7: Low | D7: Phần lớn lựa chọn nằm ở khu vực ít giải thích áp lực tài chính hoặc bị trùng lặp. | E7: Chẩn đoán xây trên nền bằng chứng mỏng. | F7: Đọc kỹ các con số (lãi vay ≈ Operating Earnings) trước khi chọn hồ sơ. | G7: Vẫn hoàn thành được case; hậu quả thể hiện qua điểm, không chặn game.
A8: =B8&"|"&C8 -> Diagnosis|High | B8: Diagnosis | C8: High | D8: Chẩn đoán của bạn chạm tới tầng cấu trúc sâu nhất (Nguyên nhân Cấu trúc / Đa yếu tố có đủ điều kiện) và có bằng chứng ủng hộ. | E8: Bạn phân biệt được nguyên nhân với triệu chứng, không dừng ở tầng bề mặt. | F8: Luôn hỏi: vấn đề này xảy ra trước hay là hệ quả? | G8: 6 chẩn đoán là 6 TẦNG của cùng vấn đề, không phải đúng/sai; điểm cao hơn vì chạm tầng sâu, không vì 'đoán trúng đáp án'.
A9: =B9&"|"&C9 -> Diagnosis|Mid | B9: Diagnosis | C9: Mid | D9: Chẩn đoán chỉ ra một vấn đề có thật nhưng là hệ quả/triệu chứng hoặc thiếu bằng chứng. | E9: Phác đồ nhắm vào triệu chứng có thể không chữa được bệnh. | F9: Truy ngược về giao dịch 2015 và cấu trúc nợ. | G9: CD-F cần HS-D và ≥1 hồ sơ liên quan, nếu không bị phạt Uy tín.
A10: =B10&"|"&C10 -> Diagnosis|Low | B10: Diagnosis | C10: Low | D10: Chẩn đoán thiếu bằng chứng hoặc là một giả thuyết bị các dữ kiện bác bỏ. | E10: Mọi phác đồ dựng trên đó dễ đi sai hướng. | F10: So chẩn đoán với hồ sơ đã mở trước khi nộp. | G10: Có thể sửa ở Màn 11 nhưng có thể mất Uy tín.
A11: =B11&"|"&C11 -> Treatment|High | B11: Treatment | C11: High | D11: Phác đồ (sau khi qua điều kiện Uy tín) khớp gốc rễ và chẩn đoán của bạn. | E11: Kế hoạch xử lý đúng chỗ thanh khoản/nợ bị kẹt. | F11: Thử xem thời điểm và nhóm ưu tiên thay đổi hậu quả thế nào. | G11: Không phác đồ nào thắng mọi trục; hậu quả còn phụ thuộc thực thi.
A12: =B12&"|"&C12 -> Treatment|Mid | B12: Treatment | C12: Mid | D12: Phác đồ giải quyết một phần vấn đề hoặc bị hạ cấp do thiếu Uy tín. | E12: Có thể mua thời gian nhưng chưa gỡ nguyên nhân. | F12: Cân nhắc phác đồ kết hợp nếu đủ Uy tín. | G12: PD-A cần Uy tín ≥ TB, PD-F cần Uy tín Cao.
A13: =B13&"|"&C13 -> Treatment|Low | B13: Treatment | C13: Low | D13: Phác đồ không khớp vấn đề thật. | E13: Có thể tiêu tốn cash/thời gian công ty không có. | F13: Đọc lại chẩn đoán và hỏi phác đồ nào tác động đúng nguyên nhân đó. | G13: Độ khớp được chấm theo thiết kế case, không theo lý thuyết chung.
A14: =B14&"|"&C14 -> Execution|High | B14: Execution | C14: High | D14: Thời điểm và nhóm ưu tiên phù hợp với phác đồ. | E14: Kế hoạch vừa đúng vừa triển khai được. | F14: Tiếp tục nối phác đồ với đúng nhóm phải thuyết phục. | G14: Phản ứng của Michael/chủ nợ thực tế có thể khó đoán hơn mô hình.
A15: =B15&"|"&C15 -> Execution|Mid | B15: Execution | C15: Mid | D15: Thời điểm hoặc nhóm ưu tiên chỉ hỗ trợ một phần phác đồ. | E15: Phác đồ tốt vẫn có thể yếu đi vì sai thứ tự. | F15: Tự hỏi ai phải đồng ý để phác đồ chạy, và khi nào. | G15: Chỉ chọn 3/7 nhóm — đánh đổi là chủ đích.
A16: =B16&"|"&C16 -> Execution|Low | B16: Execution | C16: Low | D16: Thời điểm/nhóm ưu tiên đi ngược phác đồ (ví dụ bỏ Governance khi Michael đang chờ cơ hội). | E16: Kế hoạch khó thực hiện. | F16: Chọn thời điểm theo runway và holiday; ưu tiên nhóm kiểm soát kết quả. | G16: Kế hoạch yếu không chặn case, chỉ giảm điểm.
... A19: =B19&"|"&C19 -> Reassessment|Low | B19: Reassessment | C19: Low | D19: Tái khám không khớp dữ liệu mới hoặc bị trừ Uy tín vì đổi thiếu căn cứ. | E19: Bỏ qua hoặc phản ứng thái quá làm giảm độ tin cậy. | F19: Quyết định chẩn đoán sai hay chỉ phác đồ sai trước khi đổi. | G19: Có thể chơi lại để thử đường tái khám khác.
